project/chain1.v
module chain1(
    // JTAG signals
    input wire JTCK,
    input wire JTDI,
    input wire JRTI1,
    input wire JSHIFT,
    input wire JUPDATE,
    input wire JRSTN,
    input wire JCE1,
    output wire JTD1,

    // Connection to the ping-pong buffer
    output wire [8:0] pp_address,
    output wire pp_writeEnable,
    output wire [31:0] pp_dataIn,
    input wire [31:0] pp_dataOut,
    output wire pp_switch,

    // Connection with the DMA
    output wire [31:0] dma_address,
    output wire dma_data_ready,
    output wire [3:0] dma_byte_enable
);


reg [35:0] shift_reg;
reg [31:0] data_reg;
reg [3:0] status_reg;
reg [31:0] address_reg;
reg [3:0] byte_enable_reg;
reg [7:0] busrt_size_reg;
reg [7:0] remaining_size_reg;
reg [7:0] pp_address_reg;
wire is_operation_running;
wire s_ready_to_switch;
reg r_data_shifted_in;

assign s_ready_to_switch = 1;

localparam IDLE = 0;
localparam write_FILL_BUFFER = 1;
localparam write_WAIT_FOR_SWITCH = 2;
localparam write_SWITCH_BUFFER = 3;
localparam write_LAUNCH_WRITE = 4;


reg [2:0] chain1_cur_state;
reg [2:0] chain1_nxt_state;

assign is_operation_running = (status_reg[3] == 1'b1) ? 1'b1 : 1'b0;


assign JTD1 = shift_reg[0];
always @(posedge JTCK or negedge JRSTN) begin
    if (JRSTN == 0) begin
        shift_reg <= 34'b0;
        status_reg <= 4'b0;
        address_reg <= 32'b0;
        byte_enable_reg <= 4'b0;
        busrt_size_reg <= 8'b0;
        remaining_size_reg <= 8'b0;
        pp_address_reg <= 8'b0;
    end
    else  begin
        if (r_data_shifted_in) begin
            r_data_shifted_in <= 1'b0;
        end
        if (JCE1) begin
        // Shifting data in
            if (JSHIFT) begin
                shift_reg <= {JTDI, shift_reg[35:1]};
            end
            // capture the status register
            else begin
                shift_reg <= {31'b0, status_reg};
            end 
        end
        // Update datas registers based on the instruction used
        if (JUPDATE) begin
            case (shift_reg[3:0])
                4'b0001: begin
                    // Writting to address register
                    if (~is_operation_running) begin
                        address_reg <= shift_reg[35:4];
                        status_reg <= status_reg | 4'b0001;
                    end
                end
                4'b0010: begin
                    // writting to byte enable register
                    if (~is_operation_running) begin
                        byte_enable_reg <= shift_reg[7:4];
                        status_reg <= status_reg | 4'b0010;
                    end
                end
                4'b0011: begin
                    // writting the size reg
                    if (~is_operation_running) begin
                        busrt_size_reg <= shift_reg[11:4];
                        remaining_size_reg <= shift_reg[11:4];
                        status_reg <= status_reg | 4'b0100;
                    end
                end
                4'b1000: begin
                    // Send data
                    data_reg <= shift_reg[35:4];
                    status_reg <= status_reg | 4'b1000;
                    r_data_shifted_in <= 1'b1;
                end
                default: begin
                end
            endcase 
        end
    end
end

always @(posedge JTCK or negedge JRSTN) 
    begin
        if (JRSTN == 0) begin
            chain1_cur_state <= IDLE;
        end
        else begin 
            chain1_cur_state <= chain1_nxt_state;
        end
    end 

always @(*) begin
    case (chain1_cur_state)
        IDLE: begin
            if (r_data_shifted_in) begin
                chain1_nxt_state <= write_FILL_BUFFER;
            end
            else begin
                chain1_nxt_state <= IDLE;
            end
        end
        write_FILL_BUFFER: begin
            if (remaining_size_reg == 0) begin
                chain1_nxt_state <= write_WAIT_FOR_SWITCH;
            end
            else begin
                remaining_size_reg = remaining_size_reg - 1;
                chain1_nxt_state <= IDLE;
            end
        end

        write_WAIT_FOR_SWITCH: begin
            if (s_ready_to_switch) begin
                chain1_nxt_state <= write_SWITCH_BUFFER;
            end
            else begin
                chain1_nxt_state <= write_WAIT_FOR_SWITCH;
            end
        end

        write_SWITCH_BUFFER: begin
            chain1_nxt_state <= write_LAUNCH_WRITE;
        end

        write_LAUNCH_WRITE: begin
            if (remaining_size_reg ==0) begin
                status_reg <= status_reg & 4'b0111;
            end
            chain1_nxt_state <= IDLE;
        end

        default: begin
            chain1_nxt_state <= IDLE;
        end

    endcase 
end

    assign pp_address = (chain1_cur_state == write_FILL_BUFFER) ? {1'b0, pp_address_reg}: 9'b0;
    assign pp_writeEnable = (chain1_cur_state == write_FILL_BUFFER) ? 1'b1 : 1'b0;
    assign pp_dataIn = (chain1_cur_state == write_FILL_BUFFER) ? data_reg : 32'b0;
    assign pp_switch = (chain1_cur_state == write_SWITCH_BUFFER) ? 1'b1 : 1'b0;
    assign dma_address = (chain1_cur_state == write_LAUNCH_WRITE) ? address_reg : 32'b0;
    assign dma_data_ready = (chain1_cur_state == write_LAUNCH_WRITE) ? 1'b1 : 1'b0;
    assign dma_byte_enable = (chain1_cur_state == write_LAUNCH_WRITE) ? byte_enable_reg : 4'b0;


endmodule

project/testbenches/tb_chain1.v
`timescale 1ps/1ps;

module tb_chain1;
    
    reg JTCK;
    reg JTDI;
    reg JRTI1;
    reg JSHIFT;
    reg JUPDATE;
    reg JRSTN;
    reg JCE1;
    wire JTD1;

    // Instantiate the DUT (Device Under Test)
    chain1 dut (
        .JTCK(JTCK),
        .JTDI(JTDI),
        .JRTI1(JRTI1),
        .JSHIFT(JSHIFT),
        .JUPDATE(JUPDATE),
        .JRSTN(JRSTN),
        .JCE1(JCE1),
        .JTD1(JTD1)
    );

    // Clock generation
    initial begin
        JTCK = 0; // Initialize JTCK
    end

    always #2 JTCK = ~JTCK;

    integer i;
    task sendInstruction(input [35:0] instruction);
        begin
            JRTI1 = 0;
            #8;
            JCE1 = 1;
            #4;
            for (i = 0; i < 36; i = i + 1) begin
                JTDI = instruction[i];
                JSHIFT = 1;
                #4;
            end
            JCE1 = 0;
            JSHIFT = 0;
            #8;
            JUPDATE = 1;
            #4;
            JUPDATE = 0;
            JRTI1 = 1;
            #4;
        end
    endtask

    initial begin
        // Initialize signals
        JTCK = 0;
        JTDI = 0;
        JRTI1 = 0;
        JSHIFT = 0;
        JUPDATE = 0;
        JRSTN = 1;
        JCE1 = 0;

        // Reset the DUT
        #8;
        JRSTN = 0;
        #8;
        JRSTN = 1;
        #8;
        JRTI1 = 1;
        #8;

        // Send an instruction to the DUT
        sendInstruction(36'b010101010101010101010101010101010001);
        $display("Value of address reg: %b", dut.address_reg);

        sendInstruction(36'b11110010);
        $display("Value of byte enable reg: %b", dut.byte_enable_reg);

        // sendInstruction(36'b10101010011);
        sendInstruction(36'b00011);
        $display("Value of busrt size reg: %b", dut.busrt_size_reg);

        $display("Value of status reg: %b", dut.status_reg);
        #4;
        sendInstruction(36'hF8);

        #80;
        $finish;
    end

    initial begin
        $dumpfile("test_chain1.vcd");
        $dumpvars(0, tb_chain1);
    end

endmodule

project/testbenches/test_chain1.vcd
$date
	Tue Apr 22 11:23:00 2025
$end
$version
	Icarus Verilog
$end
$timescale
	1ps
$end
$scope module tb_chain1 $end
$var wire 1 ! JTD1 $end
$var reg 1 " JCE1 $end
$var reg 1 # JRSTN $end
$var reg 1 $ JRTI1 $end
$var reg 1 % JSHIFT $end
$var reg 1 & JTCK $end
$var reg 1 ' JTDI $end
$var reg 1 ( JUPDATE $end
$var integer 32 ) i [31:0] $end
$scope module dut $end
$var wire 1 " JCE1 $end
$var wire 1 # JRSTN $end
$var wire 1 $ JRTI1 $end
$var wire 1 % JSHIFT $end
$var wire 1 & JTCK $end
$var wire 1 ' JTDI $end
$var wire 1 ( JUPDATE $end
$var wire 32 * pp_dataOut [31:0] $end
$var wire 1 + s_ready_to_switch $end
$var wire 1 , pp_writeEnable $end
$var wire 1 - pp_switch $end
$var wire 32 . pp_dataIn [31:0] $end
$var wire 9 / pp_address [8:0] $end
$var wire 1 0 is_operation_running $end
$var wire 1 1 dma_data_ready $end
$var wire 4 2 dma_byte_enable [3:0] $end
$var wire 32 3 dma_address [31:0] $end
$var wire 1 ! JTD1 $end
$var parameter 32 4 IDLE $end
$var parameter 32 5 write_FILL_BUFFER $end
$var parameter 32 6 write_LAUNCH_WRITE $end
$var parameter 32 7 write_SWITCH_BUFFER $end
$var parameter 32 8 write_WAIT_FOR_SWITCH $end
$var reg 32 9 address_reg [31:0] $end
$var reg 8 : busrt_size_reg [7:0] $end
$var reg 4 ; byte_enable_reg [3:0] $end
$var reg 3 < chain1_cur_state [2:0] $end
$var reg 3 = chain1_nxt_state [2:0] $end
$var reg 32 > data_reg [31:0] $end
$var reg 8 ? pp_address_reg [7:0] $end
$var reg 1 @ r_data_shifted_in $end
$var reg 8 A remaining_size_reg [7:0] $end
$var reg 36 B shift_reg [35:0] $end
$var reg 4 C status_reg [3:0] $end
$upscope $end
$scope task sendInstruction $end
$var reg 36 D instruction [35:0] $end
$upscope $end
$upscope $end
$enddefinitions $end
$comment Show the parameter values. $end
$dumpall
b10 8
b11 7
b100 6
b1 5
b0 4
$end
#0
$dumpvars
bx D
bx C
bx B
bx A
x@
bx ?
bx >
b0 =
bx <
bx ;
bx :
bx 9
bx 3
bx 2
x1
x0
b0xxxxxxxx /
bx .
x-
x,
1+
bz *
bx )
0(
0'
0&
0%
0$
1#
0"
x!
$end
#2
b0 /
0,
b0 .
0-
b0 3
01
b0 2
b0 <
1&
#4
0&
#6
1&
#8
00
0!
b0 ?
b0 A
b0 :
b0 ;
b0 9
b0 C
b0 B
0&
0#
#10
1&
#12
0&
#14
1&
#16
0&
1#
#18
1&
#20
0&
#22
1&
#24
0&
1$
#26
1&
#28
0&
#30
1&
#32
0&
0$
b10101010101010101010101010101010001 D
#34
1&
#36
0&
#38
1&
#40
0&
1"
#42
1&
#44
0&
1%
1'
b0 )
#46
b100000000000000000000000000000000000 B
1&
#48
0&
0'
b1 )
#50
b10000000000000000000000000000000000 B
1&
#52
0&
b10 )
#54
b1000000000000000000000000000000000 B
1&
#56
0&
b11 )
#58
b100000000000000000000000000000000 B
1&
#60
0&
1'
b100 )
#62
b100010000000000000000000000000000000 B
1&
#64
0&
0'
b101 )
#66
b10001000000000000000000000000000000 B
1&
#68
0&
1'
b110 )
#70
b101000100000000000000000000000000000 B
1&
#72
0&
0'
b111 )
#74
b10100010000000000000000000000000000 B
1&
#76
0&
1'
b1000 )
#78
b101010001000000000000000000000000000 B
1&
#80
0&
0'
b1001 )
#82
b10101000100000000000000000000000000 B
1&
#84
0&
1'
b1010 )
#86
b101010100010000000000000000000000000 B
1&
#88
0&
0'
b1011 )
#90
b10101010001000000000000000000000000 B
1&
#92
0&
1'
b1100 )
#94
b101010101000100000000000000000000000 B
1&
#96
0&
0'
b1101 )
#98
b10101010100010000000000000000000000 B
1&
#100
0&
1'
b1110 )
#102
b101010101010001000000000000000000000 B
1&
#104
0&
0'
b1111 )
#106
b10101010101000100000000000000000000 B
1&
#108
0&
1'
b10000 )
#110
b101010101010100010000000000000000000 B
1&
#112
0&
0'
b10001 )
#114
b10101010101010001000000000000000000 B
1&
#116
0&
1'
b10010 )
#118
b101010101010101000100000000000000000 B
1&
#120
0&
0'
b10011 )
#122
b10101010101010100010000000000000000 B
1&
#124
0&
1'
b10100 )
#126
b101010101010101010001000000000000000 B
1&
#128
0&
0'
b10101 )
#130
b10101010101010101000100000000000000 B
1&
#132
0&
1'
b10110 )
#134
b101010101010101010100010000000000000 B
1&
#136
0&
0'
b10111 )
#138
b10101010101010101010001000000000000 B
1&
#140
0&
1'
b11000 )
#142
b101010101010101010101000100000000000 B
1&
#144
0&
0'
b11001 )
#146
b10101010101010101010100010000000000 B
1&
#148
0&
1'
b11010 )
#150
b101010101010101010101010001000000000 B
1&
#152
0&
0'
b11011 )
#154
b10101010101010101010101000100000000 B
1&
#156
0&
1'
b11100 )
#158
b101010101010101010101010100010000000 B
1&
#160
0&
0'
b11101 )
#162
b10101010101010101010101010001000000 B
1&
#164
0&
1'
b11110 )
#166
b101010101010101010101010101000100000 B
1&
#168
0&
0'
b11111 )
#170
b10101010101010101010101010100010000 B
1&
#172
0&
1'
b100000 )
#174
b101010101010101010101010101010001000 B
1&
#176
0&
0'
b100001 )
#178
b10101010101010101010101010101000100 B
1&
#180
0&
1'
b100010 )
#182
b101010101010101010101010101010100010 B
1&
#184
0&
0'
b100011 )
#186
1!
b10101010101010101010101010101010001 B
1&
#188
0&
0%
0"
b100100 )
#190
1&
#192
0&
#194
1&
#196
0&
1(
#198
b1 C
b1010101010101010101010101010101 9
1&
#200
0&
1$
0(
#202
1&
#204
0&
0$
b11110010 D
#206
1&
#208
0&
#210
1&
#212
0&
1"
#214
b1 B
1&
#216
0&
1%
b0 )
#218
0!
b0 B
1&
#220
0&
1'
b1 )
#222
b100000000000000000000000000000000000 B
1&
#224
0&
0'
b10 )
#226
b10000000000000000000000000000000000 B
1&
#228
0&
b11 )
#230
b1000000000000000000000000000000000 B
1&
#232
0&
1'
b100 )
#234
b100100000000000000000000000000000000 B
1&
#236
0&
b101 )
#238
b110010000000000000000000000000000000 B
1&
#240
0&
b110 )
#242
b111001000000000000000000000000000000 B
1&
#244
0&
b111 )
#246
b111100100000000000000000000000000000 B
1&
#248
0&
0'
b1000 )
#250
b11110010000000000000000000000000000 B
1&
#252
0&
b1001 )
#254
b1111001000000000000000000000000000 B
1&
#256
0&
b1010 )
#258
b111100100000000000000000000000000 B
1&
#260
0&
b1011 )
#262
b11110010000000000000000000000000 B
1&
#264
0&
b1100 )
#266
b1111001000000000000000000000000 B
1&
#268
0&
b1101 )
#270
b111100100000000000000000000000 B
1&
#272
0&
b1110 )
#274
b11110010000000000000000000000 B
1&
#276
0&
b1111 )
#278
b1111001000000000000000000000 B
1&
#280
0&
b10000 )
#282
b111100100000000000000000000 B
1&
#284
0&
b10001 )
#286
b11110010000000000000000000 B
1&
#288
0&
b10010 )
#290
b1111001000000000000000000 B
1&
#292
0&
b10011 )
#294
b111100100000000000000000 B
1&
#296
0&
b10100 )
#298
b11110010000000000000000 B
1&
#300
0&
b10101 )
#302
b1111001000000000000000 B
1&
#304
0&
b10110 )
#306
b111100100000000000000 B
1&
#308
0&
b10111 )
#310
b11110010000000000000 B
1&
#312
0&
b11000 )
#314
b1111001000000000000 B
1&
#316
0&
b11001 )
#318
b111100100000000000 B
1&
#320
0&
b11010 )
#322
b11110010000000000 B
1&
#324
0&
b11011 )
#326
b1111001000000000 B
1&
#328
0&
b11100 )
#330
b111100100000000 B
1&
#332
0&
b11101 )
#334
b11110010000000 B
1&
#336
0&
b11110 )
#338
b1111001000000 B
1&
#340
0&
b11111 )
#342
b111100100000 B
1&
#344
0&
b100000 )
#346
b11110010000 B
1&
#348
0&
b100001 )
#350
b1111001000 B
1&
#352
0&
b100010 )
#354
b111100100 B
1&
#356
0&
b100011 )
#358
b11110010 B
1&
#360
0&
0%
0"
b100100 )
#362
1&
#364
0&
#366
1&
#368
0&
1(
#370
b11 C
b1111 ;
1&
#372
0&
1$
0(
#374
1&
#376
0&
0$
b11 D
#378
1&
#380
0&
#382
1&
#384
0&
1"
#386
1!
b11 B
1&
#388
0&
1%
1'
b0 )
#390
b100000000000000000000000000000000001 B
1&
#392
0&
b1 )
#394
0!
b110000000000000000000000000000000000 B
1&
#396
0&
0'
b10 )
#398
b11000000000000000000000000000000000 B
1&
#400
0&
b11 )
#402
b1100000000000000000000000000000000 B
1&
#404
0&
b100 )
#406
b110000000000000000000000000000000 B
1&
#408
0&
b101 )
#410
b11000000000000000000000000000000 B
1&
#412
0&
b110 )
#414
b1100000000000000000000000000000 B
1&
#416
0&
b111 )
#418
b110000000000000000000000000000 B
1&
#420
0&
b1000 )
#422
b11000000000000000000000000000 B
1&
#424
0&
b1001 )
#426
b1100000000000000000000000000 B
1&
#428
0&
b1010 )
#430
b110000000000000000000000000 B
1&
#432
0&
b1011 )
#434
b11000000000000000000000000 B
1&
#436
0&
b1100 )
#438
b1100000000000000000000000 B
1&
#440
0&
b1101 )
#442
b110000000000000000000000 B
1&
#444
0&
b1110 )
#446
b11000000000000000000000 B
1&
#448
0&
b1111 )
#450
b1100000000000000000000 B
1&
#452
0&
b10000 )
#454
b110000000000000000000 B
1&
#456
0&
b10001 )
#458
b11000000000000000000 B
1&
#460
0&
b10010 )
#462
b1100000000000000000 B
1&
#464
0&
b10011 )
#466
b110000000000000000 B
1&
#468
0&
b10100 )
#470
b11000000000000000 B
1&
#472
0&
b10101 )
#474
b1100000000000000 B
1&
#476
0&
b10110 )
#478
b110000000000000 B
1&
#480
0&
b10111 )
#482
b11000000000000 B
1&
#484
0&
b11000 )
#486
b1100000000000 B
1&
#488
0&
b11001 )
#490
b110000000000 B
1&
#492
0&
b11010 )
#494
b11000000000 B
1&
#496
0&
b11011 )
#498
b1100000000 B
1&
#500
0&
b11100 )
#502
b110000000 B
1&
#504
0&
b11101 )
#506
b11000000 B
1&
#508
0&
b11110 )
#510
b1100000 B
1&
#512
0&
b11111 )
#514
b110000 B
1&
#516
0&
b100000 )
#518
b11000 B
1&
#520
0&
b100001 )
#522
b1100 B
1&
#524
0&
b100010 )
#526
b110 B
1&
#528
0&
b100011 )
#530
1!
b11 B
1&
#532
0&
0%
0"
b100100 )
#534
1&
#536
0&
#538
1&
#540
0&
1(
#542
b111 C
1&
#544
0&
1$
0(
#546
1&
#548
0&
#550
1&
#552
0&
0$
b11111000 D
#554
1&
#556
0&
#558
1&
#560
0&
1"
#562
b111 B
1&
#564
0&
1%
b0 )
#566
b11 B
1&
#568
0&
b1 )
#570
b1 B
1&
#572
0&
b10 )
#574
0!
b0 B
1&
#576
0&
1'
b11 )
#578
b100000000000000000000000000000000000 B
1&
#580
0&
b100 )
#582
b110000000000000000000000000000000000 B
1&
#584
0&
b101 )
#586
b111000000000000000000000000000000000 B
1&
#588
0&
b110 )
#590
b111100000000000000000000000000000000 B
1&
#592
0&
b111 )
#594
b111110000000000000000000000000000000 B
1&
#596
0&
0'
b1000 )
#598
b11111000000000000000000000000000000 B
1&
#600
0&
b1001 )
#602
b1111100000000000000000000000000000 B
1&
#604
0&
b1010 )
#606
b111110000000000000000000000000000 B
1&
#608
0&
b1011 )
#610
b11111000000000000000000000000000 B
1&
#612
0&
b1100 )
#614
b1111100000000000000000000000000 B
1&
#616
0&
b1101 )
#618
b111110000000000000000000000000 B
1&
#620
0&
b1110 )
#622
b11111000000000000000000000000 B
1&
#624
0&
b1111 )
#626
b1111100000000000000000000000 B
1&
#628
0&
b10000 )
#630
b111110000000000000000000000 B
1&
#632
0&
b10001 )
#634
b11111000000000000000000000 B
1&
#636
0&
b10010 )
#638
b1111100000000000000000000 B
1&
#640
0&
b10011 )
#642
b111110000000000000000000 B
1&
#644
0&
b10100 )
#646
b11111000000000000000000 B
1&
#648
0&
b10101 )
#650
b1111100000000000000000 B
1&
#652
0&
b10110 )
#654
b111110000000000000000 B
1&
#656
0&
b10111 )
#658
b11111000000000000000 B
1&
#660
0&
b11000 )
#662
b1111100000000000000 B
1&
#664
0&
b11001 )
#666
b111110000000000000 B
1&
#668
0&
b11010 )
#670
b11111000000000000 B
1&
#672
0&
b11011 )
#674
b1111100000000000 B
1&
#676
0&
b11100 )
#678
b111110000000000 B
1&
#680
0&
b11101 )
#682
b11111000000000 B
1&
#684
0&
b11110 )
#686
b1111100000000 B
1&
#688
0&
b11111 )
#690
b111110000000 B
1&
#692
0&
b100000 )
#694
b11111000000 B
1&
#696
0&
b100001 )
#698
b1111100000 B
1&
#700
0&
b100010 )
#702
b111110000 B
1&
#704
0&
b100011 )
#706
b11111000 B
1&
#708
0&
0%
0"
b100100 )
#710
1&
#712
0&
#714
1&
#716
0&
1(
#718
b1 =
10
1@
b1111 C
b1111 >
1&
#720
0&
1$
0(
#722
b10 =
1,
b1111 .
b1 <
0@
1&
#724
0&
#726
b11 =
0,
b0 .
b10 <
1&
#728
0&
#730
b100 =
1-
b11 <
1&
#732
0&
#734
00
b0 =
b111 C
0-
b1010101010101010101010101010101 3
11
b1111 2
b100 <
1&
#736
0&
#738
b0 3
01
b0 2
b0 <
1&
#740
0&
#742
1&
#744
0&
#746
1&
#748
0&
#750
1&
#752
0&
#754
1&
#756
0&
#758
1&
#760
0&
#762
1&
#764
0&
#766
1&
#768
0&
#770
1&
#772
0&
#774
1&
#776
0&
#778
1&
#780
0&
#782
1&
#784
0&
#786
1&
#788
0&
#790
1&
#792
0&
#794
1&
#796
0&
#798
1&
#800
0&
#802
1&
#804
0&
