project/DMA.v
module DMA #(
    parameter [31:0] Base = 32'h40000000)
    ( 
    input wire                    clock, reset,
    input wire                    dataReady,
    input wire                    readReady,
    input wire [31:0]             address_to_read,


    // Buffer interface
    output wire [8:0]             bufferAddress,
    output wire [31:0]            dataIn,
    output wire                   writeEnable,
    input wire [31:0]             dataOut,

    // here the bus interface is defined
    input wire [31:0] address_dataIN,
    input wire end_transactionIN, 
    input wire data_validIN, 
    input wire busyIN,
    input wire errorIN,

    output wire [31:0] address_dataOUT,
    output wire [3:0] byte_enableOUT,
    output wire [7:0] busrt_sizeOUT,
    output wire read_n_writeOUT,
    output wire begin_transactionOUT,
    output wire end_transactionOUT,
    output wire data_validOUT,
    output wire busyOUT,



    // here the interface with the arbitrer
    output wire        request,
    input wire         granted
    );


    // Write states
    localparam fsm_idle = 0;
    localparam fsm_write_request = 1;
    localparam fsm_write_sending_handshake = 2;
    localparam fsm_sending_data = 3;
    localparam fsm_end_transaction = 4;
    localparam fsm_reading_from_buffer = 5;
    localparam fsm_asking_for_buffer = 6;
    localparam fsm_read_request = 7;
    localparam fsm_read_sending_handshake = 8;
    localparam fsm_reading_data = 9;
    localparam fsm_writting_buffer = 10;

    reg [3:0] cur_state, nxt_state;
    wire [31:0] buffer_data;
    wire s_reading_from_buffer_done;
    wire [31:0] s_address_to_read;

    always @(posedge clock or posedge reset) begin
        if (reset) begin
            cur_state <= fsm_idle;
        end else begin
            cur_state <= nxt_state;
        end
    end


    always @(*) begin
        if (errorIN) begin
            nxt_state = fsm_idle;
        end else begin
            case(cur_state)
                fsm_idle: nxt_state = (dataReady) ? fsm_asking_for_buffer : (readReady) ? fsm_read_request : fsm_idle;
                fsm_asking_for_buffer: nxt_state = fsm_reading_from_buffer;
                fsm_reading_from_buffer: nxt_state = (s_reading_from_buffer_done) ? fsm_write_request : fsm_reading_from_buffer;
                fsm_write_request: nxt_state = (granted) ? fsm_write_sending_handshake : fsm_write_request;
                fsm_write_sending_handshake: nxt_state = fsm_sending_data;
                fsm_sending_data: nxt_state = (busyIN)? fsm_sending_data : fsm_end_transaction; 
                fsm_end_transaction: nxt_state = fsm_idle;

                fsm_read_request: nxt_state = (granted) ? fsm_read_sending_handshake : fsm_read_request;
                fsm_read_sending_handshake: nxt_state = fsm_reading_data;
                fsm_reading_data: nxt_state = (end_transactionIN) ? fsm_reading_data : fsm_writting_buffer;
                fsm_writting_buffer: nxt_state = fsm_end_transaction;
                // default: nxt_state = fsm_idle;
            endcase
        end
    end

    assign buffer_data = (cur_state == fsm_reading_from_buffer) ? dataOut : 
                         (cur_state == fsm_reading_data && data_validIN == 1'b1) ? address_dataIN :
                         (cur_state == fsm_end_transaction || errorIN == 1'b1 || reset == 1'b1) ? 32'h0 : buffer_data;


    // Buffer interface set to read at the same location
    assign addressBuffer = 32'h0;
    assign dataIn = (cur_state == fsm_writting_buffer) ? buffer_data : 32'h0;
    assign writeEnable = (cur_state == fsm_writting_buffer) ? 1'b1 : 1'b0;
    assign s_reading_from_buffer_done = 1'b1;
    assign s_address_to_read = (cur_state == fsm_idle && readReady) ? address_to_read : 
                               (reset == 1'b1 || cur_state == fsm_end_transaction) ? 32'h0 : s_address_to_read;

    assign address_dataOUT = (cur_state == fsm_write_sending_handshake ) ? 32'h1 : 
                             (cur_state == fsm_read_sending_handshake) ? s_address_to_read :
                             (cur_state == fsm_sending_data) ? buffer_data : 32'h0; //for now only 1 byte
    assign byte_enableOUT = (cur_state == fsm_write_sending_handshake || cur_state == fsm_read_sending_handshake) ? 4'hF : 4'h0; 
    assign busrt_sizeOUT = (cur_state == fsm_write_sending_handshake) ? 8'h0 : 8'h0; //for now only 1 word
    assign read_n_writeOUT = (cur_state == fsm_read_sending_handshake) ? 1'b1 : 1'b0; 
    assign begin_transactionOUT = (cur_state == fsm_write_sending_handshake || cur_state == fsm_read_sending_handshake) ? 1'b1 : 1'b0;

    assign end_transactionOUT = ((cur_state == fsm_sending_data && busyIN == 1'b0) || errorIN == 1'b1) ? 1'b1 : 1'b0;

    assign data_validOUT = (cur_state == fsm_sending_data) ? 1'b1 : 1'b0;

    assign busyOUT = (cur_state == fsm_sending_data) ? 1'b0 : 1'b0; //for now always 0

    assign request = (cur_state == fsm_write_request || cur_state == fsm_read_request) ? 1'b1 : 1'b0;
endmodule

project/testbenches/tb_DMA.v
`timescale 1ps/1ps

module tb_DMA;

    // Testbench signals
    reg clock, reset, dataReady;
    reg [31:0] address_dataIN;
    reg end_transactionIN, data_validIN, busyIN, errorIN;
    reg granted;
    reg [31:0] dataOut;
    wire [31:0] address_dataOUT;
    wire [8:0] addressBuffer;
    wire [3:0] byte_enableOUT;
    wire [7:0] busrt_sizeOUT;
    wire read_n_writeOUT, begin_transactionOUT, end_transactionOUT, data_validOUT, busyOUT, writeEnable, request;
    wire [31:0] dataIn;
    reg readReady;
    reg [31:0] address_to_read;

    // Instantiate the DUT (Device Under Test)
    DMA dut (
        .clock(clock),
        .reset(reset),
        .dataReady(dataReady),
        .readReady(readReady),
        .address_to_read(address_to_read),
        .bufferAddress(addressBuffer),
        .writeEnable(writeEnable),
        .dataIn(dataIn),
        .dataOut(dataOut),
        .address_dataIN(address_dataIN),
        .end_transactionIN(end_transactionIN),
        .data_validIN(data_validIN),
        .busyIN(busyIN),
        .errorIN(errorIN),
        .address_dataOUT(address_dataOUT),
        .byte_enableOUT(byte_enableOUT),
        .busrt_sizeOUT(busrt_sizeOUT),
        .read_n_writeOUT(read_n_writeOUT),
        .begin_transactionOUT(begin_transactionOUT),
        .end_transactionOUT(end_transactionOUT),
        .data_validOUT(data_validOUT),
        .busyOUT(busyOUT),
        .request(request),
        .granted(granted)
    );

    // Clock generation
    always #2 clock = ~clock;

    initial begin
        // Initialize signals
        clock = 0;
        reset = 1;
        dataReady = 0;
        address_dataIN = 32'h0;
        end_transactionIN = 0;
        data_validIN = 0;
        busyIN = 0;
        errorIN = 0;
        granted = 0;
        dataOut = 32'h0;
        readReady = 0;
        address_to_read = 32'h0;

        // Reset sequence
        #4 reset = 0;
        

        // Test case: Write operation
        #4 dataReady = 1; // Indicate data is ready
        #4 dataOut = 32'hA5A5A5A5; 
        #4 dataReady = 0; 
        #4;
        #4 granted = 1;
        #4 granted = 0;
        busyIN = 1;
        dataOut = 32'h0;
        #20 busyIN = 0;

        //Try to read from address 0x0A0A0A0A
        #12

        #4 address_to_read = 32'h0A0A0A0A;
        readReady = 1;
        #4 address_to_read = 32'h0;
        readReady = 0;
        #4 granted = 1;
        #2; //Handshake
        #4 address_dataIN = 32'h12345678;
        granted = 0;
        data_validIN = 1;
        end_transactionIN = 1;
        #4 data_validIN = 0;
        // address_dataIN = 32'h0;
        end_transactionIN = 0;


        
        #20$finish;
    end

    // Monitor signals
    initial begin
        $dumpfile("test_dma.vcd");
        $dumpvars(0, tb_DMA);
    end

endmodule

project/testbenches/test_dma.vcd
$date
	Thu Apr 17 14:01:23 2025
$end
$version
	Icarus Verilog
$end
$timescale
	1ps
$end
$scope module tb_DMA $end
$var wire 9 ! addressBuffer [8:0] $end
$var wire 1 " writeEnable $end
$var wire 1 # request $end
$var wire 1 $ read_n_writeOUT $end
$var wire 1 % end_transactionOUT $end
$var wire 1 & data_validOUT $end
$var wire 32 ' dataIn [31:0] $end
$var wire 4 ( byte_enableOUT [3:0] $end
$var wire 1 ) busyOUT $end
$var wire 8 * busrt_sizeOUT [7:0] $end
$var wire 1 + begin_transactionOUT $end
$var wire 32 , address_dataOUT [31:0] $end
$var reg 32 - address_dataIN [31:0] $end
$var reg 32 . address_to_read [31:0] $end
$var reg 1 / busyIN $end
$var reg 1 0 clock $end
$var reg 32 1 dataOut [31:0] $end
$var reg 1 2 dataReady $end
$var reg 1 3 data_validIN $end
$var reg 1 4 end_transactionIN $end
$var reg 1 5 errorIN $end
$var reg 1 6 granted $end
$var reg 1 7 readReady $end
$var reg 1 8 reset $end
$scope module dut $end
$var wire 1 9 addressBuffer $end
$var wire 32 : address_dataIN [31:0] $end
$var wire 32 ; address_to_read [31:0] $end
$var wire 9 < bufferAddress [8:0] $end
$var wire 1 / busyIN $end
$var wire 1 0 clock $end
$var wire 32 = dataOut [31:0] $end
$var wire 1 2 dataReady $end
$var wire 1 3 data_validIN $end
$var wire 1 4 end_transactionIN $end
$var wire 1 5 errorIN $end
$var wire 1 6 granted $end
$var wire 1 7 readReady $end
$var wire 1 8 reset $end
$var wire 1 > s_reading_from_buffer_done $end
$var wire 1 " writeEnable $end
$var wire 32 ? s_address_to_read [31:0] $end
$var wire 1 # request $end
$var wire 1 $ read_n_writeOUT $end
$var wire 1 % end_transactionOUT $end
$var wire 1 & data_validOUT $end
$var wire 32 @ dataIn [31:0] $end
$var wire 4 A byte_enableOUT [3:0] $end
$var wire 1 ) busyOUT $end
$var wire 8 B busrt_sizeOUT [7:0] $end
$var wire 32 C buffer_data [31:0] $end
$var wire 1 + begin_transactionOUT $end
$var wire 32 D address_dataOUT [31:0] $end
$var parameter 32 E Base $end
$var parameter 32 F fsm_asking_for_buffer $end
$var parameter 32 G fsm_end_transaction $end
$var parameter 32 H fsm_idle $end
$var parameter 32 I fsm_read_request $end
$var parameter 32 J fsm_read_sending_handshake $end
$var parameter 32 K fsm_reading_data $end
$var parameter 32 L fsm_reading_from_buffer $end
$var parameter 32 M fsm_sending_data $end
$var parameter 32 N fsm_write_request $end
$var parameter 32 O fsm_write_sending_handshake $end
$var parameter 32 P fsm_writting_buffer $end
$var reg 4 Q cur_state [3:0] $end
$var reg 4 R nxt_state [3:0] $end
$upscope $end
$upscope $end
$enddefinitions $end
$comment Show the parameter values. $end
$dumpall
b1010 P
b10 O
b1 N
b11 M
b101 L
b1001 K
b1000 J
b111 I
b0 H
b100 G
b110 F
b1000000000000000000000000000000 E
$end
#0
$dumpvars
b0 R
b0 Q
b0 D
b0 C
b0 B
b0 A
b0 @
b0 ?
1>
b0 =
bz <
b0 ;
b0 :
09
18
07
06
05
04
03
02
b0 1
00
0/
b0 .
b0 -
b0 ,
0+
b0 *
0)
b0 (
b0 '
0&
0%
0$
0#
0"
bz !
$end
#2
10
#4
00
08
#6
10
#8
b110 R
00
12
#10
b101 R
b110 Q
10
#12
00
b10100101101001011010010110100101 1
b10100101101001011010010110100101 =
#14
b10100101101001011010010110100101 C
b1 R
b101 Q
10
#16
00
02
#18
1#
b1 Q
10
#20
00
#22
10
#24
b10 R
00
16
#26
b1111 (
b1111 A
1+
0#
b1 ,
b1 D
b11 R
b10 Q
10
#28
00
b0 1
b0 =
1/
06
#30
b0 (
b0 A
0+
b10100101101001011010010110100101 ,
b10100101101001011010010110100101 D
1&
b11 Q
10
#32
00
#34
10
#36
00
#38
10
#40
00
#42
10
#44
00
#46
10
#48
1%
b100 R
00
0/
#50
b0 C
b0 ,
b0 D
0%
0&
b0 R
b100 Q
10
#52
00
#54
b0 Q
10
#56
00
#58
10
#60
00
#62
10
#64
b1010000010100000101000001010 ?
b111 R
00
17
b1010000010100000101000001010 .
b1010000010100000101000001010 ;
#66
1#
b111 Q
10
#68
00
07
b0 .
b0 ;
#70
10
#72
b1000 R
00
16
#74
b1010000010100000101000001010 ,
b1010000010100000101000001010 D
b1111 (
b1111 A
1+
0#
1$
b1001 R
b1000 Q
10
#76
00
#78
b10010001101000101011001111000 C
b0 ,
b0 D
b0 (
b0 A
0+
0$
b1001 Q
10
14
13
06
b10010001101000101011001111000 -
b10010001101000101011001111000 :
#80
00
#82
b10010001101000101011001111000 '
b10010001101000101011001111000 @
1"
b1010 Q
b100 R
10
04
03
#84
00
#86
b0 C
b0 ?
b0 '
b0 @
0"
b0 R
b100 Q
10
#88
00
#90
b0 Q
10
