project/chain1.v
module chain1(
    // JTAG signals
    input wire JTCK,
    input wire JTDI,
    input wire JRTI1,
    input wire JSHIFT,
    input wire JUPDATE,
    input wire JRSTN,
    input wire JCE1,
    output wire JTD1,

    // Connection to the ping-pong buffer
    output wire [8:0] pp_address,
    output wire pp_writeEnable,
    output wire [31:0] pp_dataIn,
    input wire [31:0] pp_dataOut,
    output wire pp_switch,

    // Connection with the DMA
    output wire [31:0] dma_address,
    output wire dma_data_ready,
    output wire [3:0] dma_byte_enable,
    output wire dma_readReady,
    input wire switch_ready
);


reg [35:0] shift_reg;
reg [31:0] data_reg;
reg [5:0] status_reg;
reg [31:0] address_reg;
reg [3:0] byte_enable_reg;
reg [7:0] busrt_size_reg;
reg [7:0] remaining_size_reg;
reg [7:0] pp_address_reg;
wire is_operation_running;
wire s_ready_to_switch;
reg [31:0] read_data_from_buffer;
reg r_data_shifted_in;
reg r_launch_read;
reg r_data_shifted_out;

assign s_ready_to_switch = switch_ready;

localparam IDLE = 0;
localparam write_FILL_BUFFER = 1;
localparam write_WAIT_FOR_SWITCH = 2;
localparam write_SWITCH_BUFFER = 3;
localparam write_LAUNCH_WRITE = 4;
localparam read_LAUNCH_READ = 5;
localparam read_WAIT_FOR_SWITCH = 6;
localparam read_DATA_READY_TO_READ = 7;
localparam read_SWITCH_BUFFER = 8;
localparam read_ASK_BUFFER = 9;
localparam read_STORE_BUFFER_ANSWER = 10;



reg [4:0] chain1_cur_state;
reg [4:0] chain1_nxt_state;

// The status register is used to indicate the current state of the operation
assign is_operation_running = (status_reg[3] == 1'b1 | status_reg[4] == 1'b1) ? 1'b1 : 1'b0;


assign JTD1 = shift_reg[0];
always @(posedge JTCK or negedge JRSTN) begin
    if (JRSTN == 0) begin
        shift_reg <= 34'b0;
        status_reg <= 6'b0;
        address_reg <= 32'b0;
        byte_enable_reg <= 4'b0;
        busrt_size_reg <= 8'b0;
        remaining_size_reg <= 8'b0;
        pp_address_reg <= 8'b0;
        r_data_shifted_in <= 1'b0;
        r_launch_read <= 1'b0;
        r_data_shifted_out <= 1'b0;
    end
    else  begin
        r_data_shifted_in <= 1'b0;
        r_launch_read <= 1'b0;
        r_data_shifted_out <= 1'b0;
        if (JCE1) begin
        // Shifting data in
            if (JSHIFT) begin
                shift_reg <= {JTDI, shift_reg[35:1]};
            end
            // capture the status register
            else begin
                if (status_reg[5] == 1'b1) begin
                    shift_reg <= {3'b111, remaining_size_reg == 0 ? 1'b0 : 1'b1, read_data_from_buffer};
                    r_data_shifted_out <= 1'b1;
                end
                else begin
                    shift_reg <= {29'b0, status_reg};
                end
            end 
        end
        // Update datas registers based on the instruction used
        if (JUPDATE) begin
            case (shift_reg[3:0])
                4'b0001: begin
                    // Writting to address register
                    if (~is_operation_running) begin
                        address_reg <= shift_reg[35:4];
                        status_reg <= status_reg | 6'b0001;
                    end
                end
                4'b0010: begin
                    // writting to byte enable register
                    if (~is_operation_running) begin
                        byte_enable_reg <= shift_reg[7:4];
                        status_reg <= status_reg | 6'b0010;
                    end
                end
                4'b0011: begin
                    // writting the size reg
                    if (~is_operation_running) begin
                        busrt_size_reg <= shift_reg[11:4];
                        remaining_size_reg <= shift_reg[11:4];
                        status_reg <= status_reg | 6'b0100;
                    end
                end
                4'b1000: begin
                    // Send data
                    data_reg <= shift_reg[35:4];
                    status_reg <= status_reg | 6'b1000;
                    r_data_shifted_in <= 1'b1;
                end
                4'b1001: begin
                    // Start the read operation
                    status_reg <= status_reg | 6'b10000;
                    r_launch_read <= 1'b1;
                end
                4'b1010: begin 
                    // Read operation and move to next word
                    status_reg[5] <= 1'b0;
                end
            endcase 
        end
    end
end

always @(posedge JTCK or negedge JRSTN) 
    begin
        if (JRSTN == 0) begin
            chain1_cur_state <= IDLE;
            read_data_from_buffer <= 32'b0;
        end
        else begin 
            chain1_cur_state = chain1_nxt_state;
            case (chain1_cur_state)
                write_FILL_BUFFER: begin 
                    if (remaining_size_reg != 0) begin
                        remaining_size_reg <= remaining_size_reg - 1;
                    end
                end 
                write_LAUNCH_WRITE: begin
                    if (remaining_size_reg == 0) begin
                        status_reg <= status_reg & 6'b0111;
                    end
                end
                read_STORE_BUFFER_ANSWER: begin
                    read_data_from_buffer <= pp_dataOut;
                    status_reg <= status_reg | 6'b100000;
                end
                read_DATA_READY_TO_READ: begin
                    if (r_data_shifted_out) begin
                        status_reg[5] <= 1'b0;
                        if (remaining_size_reg == 0) begin
                            status_reg[4] <= 1'b0;
                        end
                        else begin
                            remaining_size_reg <= remaining_size_reg - 1;
                        end
                    end
                end
        endcase


        end
    end 

always @(*) begin
    case (chain1_cur_state)
        IDLE: begin
            if (r_data_shifted_in) begin
                chain1_nxt_state <= write_FILL_BUFFER;
            end
            else begin
                if (r_launch_read) begin
                    chain1_nxt_state <= read_LAUNCH_READ;
                end
                else begin
                    chain1_nxt_state <= IDLE;
                end
            end
        end
        write_FILL_BUFFER: begin
            if (remaining_size_reg == 0) begin
                chain1_nxt_state <= write_WAIT_FOR_SWITCH;
            end
            else begin
                chain1_nxt_state <= IDLE;
            end
        end

        write_WAIT_FOR_SWITCH: begin
            if (s_ready_to_switch) begin
                chain1_nxt_state <= write_SWITCH_BUFFER;
            end
            else begin
                chain1_nxt_state <= write_WAIT_FOR_SWITCH;
            end
        end

        write_SWITCH_BUFFER: begin
            chain1_nxt_state <= write_LAUNCH_WRITE;
        end

        write_LAUNCH_WRITE: begin
            chain1_nxt_state <= IDLE;
        end

        read_LAUNCH_READ: begin
            chain1_nxt_state <= read_WAIT_FOR_SWITCH;
        end

        read_WAIT_FOR_SWITCH: begin
            if (s_ready_to_switch) begin
                chain1_nxt_state <= read_SWITCH_BUFFER;
            end
            else begin
                chain1_nxt_state <= read_WAIT_FOR_SWITCH;
            end
        end

        read_SWITCH_BUFFER: begin
            chain1_nxt_state <= read_ASK_BUFFER;
        end

        read_ASK_BUFFER: begin
            chain1_nxt_state <= read_STORE_BUFFER_ANSWER;
        end

        read_STORE_BUFFER_ANSWER: begin
            chain1_nxt_state <= read_DATA_READY_TO_READ;
        end

        read_DATA_READY_TO_READ: begin
            if (r_data_shifted_out) begin
                // r_data_shifted_out <= 1'b0;
                if (remaining_size_reg == 0) begin
                    chain1_nxt_state <= IDLE;
                end
                else begin
                    chain1_nxt_state <= read_ASK_BUFFER;
                end
            end
            else begin
                chain1_nxt_state <= read_DATA_READY_TO_READ;
            end
            
        end
        default: begin
            chain1_nxt_state <= IDLE;
        end

    endcase 
end

    assign pp_address = (chain1_cur_state == write_FILL_BUFFER | chain1_cur_state == read_ASK_BUFFER) ? {1'b0, pp_address_reg}: 9'b0;
    assign pp_writeEnable = (chain1_cur_state == write_FILL_BUFFER) ? 1'b1 : 1'b0;
    assign pp_dataIn = (chain1_cur_state == write_FILL_BUFFER) ? data_reg : 32'b0;
    assign pp_switch = (chain1_cur_state == write_SWITCH_BUFFER | chain1_cur_state == read_SWITCH_BUFFER) ? 1'b1 : 1'b0;
    assign dma_address = (chain1_cur_state == write_LAUNCH_WRITE | chain1_cur_state == read_LAUNCH_READ) ? address_reg : 32'b0;
    assign dma_data_ready = (chain1_cur_state == write_LAUNCH_WRITE) ? 1'b1 : 1'b0;
    assign dma_byte_enable = (chain1_cur_state == write_LAUNCH_WRITE | chain1_cur_state == read_LAUNCH_READ) ? byte_enable_reg : 4'b0;
    assign dma_readReady = (chain1_cur_state == read_LAUNCH_READ) ? 1'b1 : 1'b0;


endmodule

project/testbenches/tb_chain1.v
`timescale 1ps/1ps;

module tb_chain1;
    
    reg JTCK;
    reg JTDI;
    reg JRTI1;
    reg JSHIFT;
    reg JUPDATE;
    reg JRSTN;
    reg JCE1;
    wire JTD1;

    // Instantiate the DUT (Device Under Test)
    chain1 dut (
        .JTCK(JTCK),
        .JTDI(JTDI),
        .JRTI1(JRTI1),
        .JSHIFT(JSHIFT),
        .JUPDATE(JUPDATE),
        .JRSTN(JRSTN),
        .JCE1(JCE1),
        .JTD1(JTD1),
        .pp_dataOut(32'hFFFFFFFF),
        .switch_ready(1'b1)
    );

    // Clock generation
    initial begin
        JTCK = 0; // Initialize JTCK
    end

    always #2 JTCK = ~JTCK;

    integer i;
    task sendInstruction(input [35:0] instruction);
        begin
            JRTI1 = 0;
            #8;
            JCE1 = 1;
            #4;
            for (i = 0; i < 36; i = i + 1) begin
                JTDI = instruction[i];
                JSHIFT = 1;
                #4;
            end
            JCE1 = 0;
            JSHIFT = 0;
            #8;
            JUPDATE = 1;
            #4;
            JUPDATE = 0;
            JRTI1 = 1;
            #4;
        end
    endtask

    initial begin
        // Initialize signals
        JTCK = 0;
        JTDI = 0;
        JRTI1 = 0;
        JSHIFT = 0;
        JUPDATE = 0;
        JRSTN = 1;
        JCE1 = 0;

        // Reset the DUT
        #8;
        JRSTN = 0;
        #8;
        JRSTN = 1;
        #8;
        JRTI1 = 1;
        #8;

        // Send an instruction to the DUT
        sendInstruction(36'b010101010101010101010101010101010001);
        $display("Value of address reg: %b", dut.address_reg);

        sendInstruction(36'b11110010);
        $display("Value of byte enable reg: %b", dut.byte_enable_reg);

        // sendInstruction(36'b10101010011);
        sendInstruction(36'b00011);
        $display("Value of busrt size reg: %b", dut.busrt_size_reg);

        $display("Value of status reg: %b", dut.status_reg);
        #4;
        sendInstruction(36'hF8);

        #80;

        // Send a read instruction
        sendInstruction(36'b1001);
        #20

        // Read the data from the buffer
        sendInstruction(36'b1010);
        #160;
        $finish;
    end

    initial begin
        $dumpfile("test_chain1.vcd");
        $dumpvars(0, tb_chain1);
    end

endmodule

project/testbenches/test_chain1.vcd
$date
	Sun Apr 27 14:56:55 2025
$end
$version
	Icarus Verilog
$end
$timescale
	1ps
$end
$scope module tb_chain1 $end
$var wire 1 ! JTD1 $end
$var reg 1 " JCE1 $end
$var reg 1 # JRSTN $end
$var reg 1 $ JRTI1 $end
$var reg 1 % JSHIFT $end
$var reg 1 & JTCK $end
$var reg 1 ' JTDI $end
$var reg 1 ( JUPDATE $end
$var integer 32 ) i [31:0] $end
$scope module dut $end
$var wire 1 " JCE1 $end
$var wire 1 # JRSTN $end
$var wire 1 $ JRTI1 $end
$var wire 1 % JSHIFT $end
$var wire 1 & JTCK $end
$var wire 1 ' JTDI $end
$var wire 1 ( JUPDATE $end
$var wire 32 * pp_dataOut [31:0] $end
$var wire 1 + s_ready_to_switch $end
$var wire 1 , switch_ready $end
$var wire 1 - pp_writeEnable $end
$var wire 1 . pp_switch $end
$var wire 32 / pp_dataIn [31:0] $end
$var wire 9 0 pp_address [8:0] $end
$var wire 1 1 is_operation_running $end
$var wire 1 2 dma_readReady $end
$var wire 1 3 dma_data_ready $end
$var wire 4 4 dma_byte_enable [3:0] $end
$var wire 32 5 dma_address [31:0] $end
$var wire 1 ! JTD1 $end
$var parameter 32 6 IDLE $end
$var parameter 32 7 read_ASK_BUFFER $end
$var parameter 32 8 read_DATA_READY_TO_READ $end
$var parameter 32 9 read_LAUNCH_READ $end
$var parameter 32 : read_STORE_BUFFER_ANSWER $end
$var parameter 32 ; read_SWITCH_BUFFER $end
$var parameter 32 < read_WAIT_FOR_SWITCH $end
$var parameter 32 = write_FILL_BUFFER $end
$var parameter 32 > write_LAUNCH_WRITE $end
$var parameter 32 ? write_SWITCH_BUFFER $end
$var parameter 32 @ write_WAIT_FOR_SWITCH $end
$var reg 32 A address_reg [31:0] $end
$var reg 8 B busrt_size_reg [7:0] $end
$var reg 4 C byte_enable_reg [3:0] $end
$var reg 5 D chain1_cur_state [4:0] $end
$var reg 5 E chain1_nxt_state [4:0] $end
$var reg 32 F data_reg [31:0] $end
$var reg 8 G pp_address_reg [7:0] $end
$var reg 1 H r_data_shifted_in $end
$var reg 1 I r_data_shifted_out $end
$var reg 1 J r_launch_read $end
$var reg 32 K read_data_from_buffer [31:0] $end
$var reg 8 L remaining_size_reg [7:0] $end
$var reg 36 M shift_reg [35:0] $end
$var reg 6 N status_reg [5:0] $end
$upscope $end
$scope task sendInstruction $end
$var reg 36 O instruction [35:0] $end
$upscope $end
$upscope $end
$enddefinitions $end
$comment Show the parameter values. $end
$dumpall
b10 @
b11 ?
b100 >
b1 =
b110 <
b1000 ;
b1010 :
b101 9
b111 8
b1001 7
b0 6
$end
#0
$dumpvars
bx O
bx N
bx M
bx L
bx K
xJ
xI
xH
bx G
bx F
b0 E
bx D
bx C
bx B
bx A
bx 5
bx 4
x3
x2
x1
b0xxxxxxxx 0
bx /
x.
x-
1,
1+
b11111111111111111111111111111111 *
bx )
0(
0'
0&
0%
0$
1#
0"
x!
$end
#2
0I
0J
0H
b0 0
0.
b0 5
b0 4
0-
b0 /
03
02
b0 D
1&
#4
0&
#6
1&
#8
01
0!
b0 G
b0 L
b0 B
b0 C
b0 A
b0 N
b0 M
b0 K
0&
0#
#10
1&
#12
0&
#14
1&
#16
0&
1#
#18
1&
#20
0&
#22
1&
#24
0&
1$
#26
1&
#28
0&
#30
1&
#32
0&
0$
b10101010101010101010101010101010001 O
#34
1&
#36
0&
#38
1&
#40
0&
1"
#42
1&
#44
0&
1%
1'
b0 )
#46
b100000000000000000000000000000000000 M
1&
#48
0&
0'
b1 )
#50
b10000000000000000000000000000000000 M
1&
#52
0&
b10 )
#54
b1000000000000000000000000000000000 M
1&
#56
0&
b11 )
#58
b100000000000000000000000000000000 M
1&
#60
0&
1'
b100 )
#62
b100010000000000000000000000000000000 M
1&
#64
0&
0'
b101 )
#66
b10001000000000000000000000000000000 M
1&
#68
0&
1'
b110 )
#70
b101000100000000000000000000000000000 M
1&
#72
0&
0'
b111 )
#74
b10100010000000000000000000000000000 M
1&
#76
0&
1'
b1000 )
#78
b101010001000000000000000000000000000 M
1&
#80
0&
0'
b1001 )
#82
b10101000100000000000000000000000000 M
1&
#84
0&
1'
b1010 )
#86
b101010100010000000000000000000000000 M
1&
#88
0&
0'
b1011 )
#90
b10101010001000000000000000000000000 M
1&
#92
0&
1'
b1100 )
#94
b101010101000100000000000000000000000 M
1&
#96
0&
0'
b1101 )
#98
b10101010100010000000000000000000000 M
1&
#100
0&
1'
b1110 )
#102
b101010101010001000000000000000000000 M
1&
#104
0&
0'
b1111 )
#106
b10101010101000100000000000000000000 M
1&
#108
0&
1'
b10000 )
#110
b101010101010100010000000000000000000 M
1&
#112
0&
0'
b10001 )
#114
b10101010101010001000000000000000000 M
1&
#116
0&
1'
b10010 )
#118
b101010101010101000100000000000000000 M
1&
#120
0&
0'
b10011 )
#122
b10101010101010100010000000000000000 M
1&
#124
0&
1'
b10100 )
#126
b101010101010101010001000000000000000 M
1&
#128
0&
0'
b10101 )
#130
b10101010101010101000100000000000000 M
1&
#132
0&
1'
b10110 )
#134
b101010101010101010100010000000000000 M
1&
#136
0&
0'
b10111 )
#138
b10101010101010101010001000000000000 M
1&
#140
0&
1'
b11000 )
#142
b101010101010101010101000100000000000 M
1&
#144
0&
0'
b11001 )
#146
b10101010101010101010100010000000000 M
1&
#148
0&
1'
b11010 )
#150
b101010101010101010101010001000000000 M
1&
#152
0&
0'
b11011 )
#154
b10101010101010101010101000100000000 M
1&
#156
0&
1'
b11100 )
#158
b101010101010101010101010100010000000 M
1&
#160
0&
0'
b11101 )
#162
b10101010101010101010101010001000000 M
1&
#164
0&
1'
b11110 )
#166
b101010101010101010101010101000100000 M
1&
#168
0&
0'
b11111 )
#170
b10101010101010101010101010100010000 M
1&
#172
0&
1'
b100000 )
#174
b101010101010101010101010101010001000 M
1&
#176
0&
0'
b100001 )
#178
b10101010101010101010101010101000100 M
1&
#180
0&
1'
b100010 )
#182
b101010101010101010101010101010100010 M
1&
#184
0&
0'
b100011 )
#186
1!
b10101010101010101010101010101010001 M
1&
#188
0&
0%
0"
b100100 )
#190
1&
#192
0&
#194
1&
#196
0&
1(
#198
b1 N
b1010101010101010101010101010101 A
1&
#200
0&
1$
0(
#202
1&
#204
0&
0$
b11110010 O
#206
1&
#208
0&
#210
1&
#212
0&
1"
#214
b1 M
1&
#216
0&
1%
b0 )
#218
0!
b0 M
1&
#220
0&
1'
b1 )
#222
b100000000000000000000000000000000000 M
1&
#224
0&
0'
b10 )
#226
b10000000000000000000000000000000000 M
1&
#228
0&
b11 )
#230
b1000000000000000000000000000000000 M
1&
#232
0&
1'
b100 )
#234
b100100000000000000000000000000000000 M
1&
#236
0&
b101 )
#238
b110010000000000000000000000000000000 M
1&
#240
0&
b110 )
#242
b111001000000000000000000000000000000 M
1&
#244
0&
b111 )
#246
b111100100000000000000000000000000000 M
1&
#248
0&
0'
b1000 )
#250
b11110010000000000000000000000000000 M
1&
#252
0&
b1001 )
#254
b1111001000000000000000000000000000 M
1&
#256
0&
b1010 )
#258
b111100100000000000000000000000000 M
1&
#260
0&
b1011 )
#262
b11110010000000000000000000000000 M
1&
#264
0&
b1100 )
#266
b1111001000000000000000000000000 M
1&
#268
0&
b1101 )
#270
b111100100000000000000000000000 M
1&
#272
0&
b1110 )
#274
b11110010000000000000000000000 M
1&
#276
0&
b1111 )
#278
b1111001000000000000000000000 M
1&
#280
0&
b10000 )
#282
b111100100000000000000000000 M
1&
#284
0&
b10001 )
#286
b11110010000000000000000000 M
1&
#288
0&
b10010 )
#290
b1111001000000000000000000 M
1&
#292
0&
b10011 )
#294
b111100100000000000000000 M
1&
#296
0&
b10100 )
#298
b11110010000000000000000 M
1&
#300
0&
b10101 )
#302
b1111001000000000000000 M
1&
#304
0&
b10110 )
#306
b111100100000000000000 M
1&
#308
0&
b10111 )
#310
b11110010000000000000 M
1&
#312
0&
b11000 )
#314
b1111001000000000000 M
1&
#316
0&
b11001 )
#318
b111100100000000000 M
1&
#320
0&
b11010 )
#322
b11110010000000000 M
1&
#324
0&
b11011 )
#326
b1111001000000000 M
1&
#328
0&
b11100 )
#330
b111100100000000 M
1&
#332
0&
b11101 )
#334
b11110010000000 M
1&
#336
0&
b11110 )
#338
b1111001000000 M
1&
#340
0&
b11111 )
#342
b111100100000 M
1&
#344
0&
b100000 )
#346
b11110010000 M
1&
#348
0&
b100001 )
#350
b1111001000 M
1&
#352
0&
b100010 )
#354
b111100100 M
1&
#356
0&
b100011 )
#358
b11110010 M
1&
#360
0&
0%
0"
b100100 )
#362
1&
#364
0&
#366
1&
#368
0&
1(
#370
b11 N
b1111 C
1&
#372
0&
1$
0(
#374
1&
#376
0&
0$
b11 O
#378
1&
#380
0&
#382
1&
#384
0&
1"
#386
1!
b11 M
1&
#388
0&
1%
1'
b0 )
#390
b100000000000000000000000000000000001 M
1&
#392
0&
b1 )
#394
0!
b110000000000000000000000000000000000 M
1&
#396
0&
0'
b10 )
#398
b11000000000000000000000000000000000 M
1&
#400
0&
b11 )
#402
b1100000000000000000000000000000000 M
1&
#404
0&
b100 )
#406
b110000000000000000000000000000000 M
1&
#408
0&
b101 )
#410
b11000000000000000000000000000000 M
1&
#412
0&
b110 )
#414
b1100000000000000000000000000000 M
1&
#416
0&
b111 )
#418
b110000000000000000000000000000 M
1&
#420
0&
b1000 )
#422
b11000000000000000000000000000 M
1&
#424
0&
b1001 )
#426
b1100000000000000000000000000 M
1&
#428
0&
b1010 )
#430
b110000000000000000000000000 M
1&
#432
0&
b1011 )
#434
b11000000000000000000000000 M
1&
#436
0&
b1100 )
#438
b1100000000000000000000000 M
1&
#440
0&
b1101 )
#442
b110000000000000000000000 M
1&
#444
0&
b1110 )
#446
b11000000000000000000000 M
1&
#448
0&
b1111 )
#450
b1100000000000000000000 M
1&
#452
0&
b10000 )
#454
b110000000000000000000 M
1&
#456
0&
b10001 )
#458
b11000000000000000000 M
1&
#460
0&
b10010 )
#462
b1100000000000000000 M
1&
#464
0&
b10011 )
#466
b110000000000000000 M
1&
#468
0&
b10100 )
#470
b11000000000000000 M
1&
#472
0&
b10101 )
#474
b1100000000000000 M
1&
#476
0&
b10110 )
#478
b110000000000000 M
1&
#480
0&
b10111 )
#482
b11000000000000 M
1&
#484
0&
b11000 )
#486
b1100000000000 M
1&
#488
0&
b11001 )
#490
b110000000000 M
1&
#492
0&
b11010 )
#494
b11000000000 M
1&
#496
0&
b11011 )
#498
b1100000000 M
1&
#500
0&
b11100 )
#502
b110000000 M
1&
#504
0&
b11101 )
#506
b11000000 M
1&
#508
0&
b11110 )
#510
b1100000 M
1&
#512
0&
b11111 )
#514
b110000 M
1&
#516
0&
b100000 )
#518
b11000 M
1&
#520
0&
b100001 )
#522
b1100 M
1&
#524
0&
b100010 )
#526
b110 M
1&
#528
0&
b100011 )
#530
1!
b11 M
1&
#532
0&
0%
0"
b100100 )
#534
1&
#536
0&
#538
1&
#540
0&
1(
#542
b111 N
1&
#544
0&
1$
0(
#546
1&
#548
0&
#550
1&
#552
0&
0$
b11111000 O
#554
1&
#556
0&
#558
1&
#560
0&
1"
#562
b111 M
1&
#564
0&
1%
b0 )
#566
b11 M
1&
#568
0&
b1 )
#570
b1 M
1&
#572
0&
b10 )
#574
0!
b0 M
1&
#576
0&
1'
b11 )
#578
b100000000000000000000000000000000000 M
1&
#580
0&
b100 )
#582
b110000000000000000000000000000000000 M
1&
#584
0&
b101 )
#586
b111000000000000000000000000000000000 M
1&
#588
0&
b110 )
#590
b111100000000000000000000000000000000 M
1&
#592
0&
b111 )
#594
b111110000000000000000000000000000000 M
1&
#596
0&
0'
b1000 )
#598
b11111000000000000000000000000000000 M
1&
#600
0&
b1001 )
#602
b1111100000000000000000000000000000 M
1&
#604
0&
b1010 )
#606
b111110000000000000000000000000000 M
1&
#608
0&
b1011 )
#610
b11111000000000000000000000000000 M
1&
#612
0&
b1100 )
#614
b1111100000000000000000000000000 M
1&
#616
0&
b1101 )
#618
b111110000000000000000000000000 M
1&
#620
0&
b1110 )
#622
b11111000000000000000000000000 M
1&
#624
0&
b1111 )
#626
b1111100000000000000000000000 M
1&
#628
0&
b10000 )
#630
b111110000000000000000000000 M
1&
#632
0&
b10001 )
#634
b11111000000000000000000000 M
1&
#636
0&
b10010 )
#638
b1111100000000000000000000 M
1&
#640
0&
b10011 )
#642
b111110000000000000000000 M
1&
#644
0&
b10100 )
#646
b11111000000000000000000 M
1&
#648
0&
b10101 )
#650
b1111100000000000000000 M
1&
#652
0&
b10110 )
#654
b111110000000000000000 M
1&
#656
0&
b10111 )
#658
b11111000000000000000 M
1&
#660
0&
b11000 )
#662
b1111100000000000000 M
1&
#664
0&
b11001 )
#666
b111110000000000000 M
1&
#668
0&
b11010 )
#670
b11111000000000000 M
1&
#672
0&
b11011 )
#674
b1111100000000000 M
1&
#676
0&
b11100 )
#678
b111110000000000 M
1&
#680
0&
b11101 )
#682
b11111000000000 M
1&
#684
0&
b11110 )
#686
b1111100000000 M
1&
#688
0&
b11111 )
#690
b111110000000 M
1&
#692
0&
b100000 )
#694
b11111000000 M
1&
#696
0&
b100001 )
#698
b1111100000 M
1&
#700
0&
b100010 )
#702
b111110000 M
1&
#704
0&
b100011 )
#706
b11111000 M
1&
#708
0&
0%
0"
b100100 )
#710
1&
#712
0&
#714
1&
#716
0&
1(
#718
b1 E
11
1H
b1111 N
b1111 F
1&
#720
0&
1$
0(
#722
b10 E
0H
1-
b1111 /
b1 D
1&
#724
0&
#726
b11 E
0-
b0 /
b10 D
1&
#728
0&
#730
b100 E
1.
b11 D
1&
#732
0&
#734
01
b0 E
b111 N
0.
b1010101010101010101010101010101 5
b1111 4
13
b100 D
1&
#736
0&
#738
b0 5
b0 4
03
b0 D
1&
#740
0&
#742
1&
#744
0&
#746
1&
#748
0&
#750
1&
#752
0&
#754
1&
#756
0&
#758
1&
#760
0&
#762
1&
#764
0&
#766
1&
#768
0&
#770
1&
#772
0&
#774
1&
#776
0&
#778
1&
#780
0&
#782
1&
#784
0&
#786
1&
#788
0&
#790
1&
#792
0&
#794
1&
#796
0&
#798
1&
#800
0&
#802
1&
#804
0&
0$
b1001 O
#806
1&
#808
0&
#810
1&
#812
0&
1"
#814
1!
b111 M
1&
#816
0&
1%
1'
b0 )
#818
b100000000000000000000000000000000011 M
1&
#820
0&
0'
b1 )
#822
b10000000000000000000000000000000001 M
1&
#824
0&
b10 )
#826
0!
b1000000000000000000000000000000000 M
1&
#828
0&
1'
b11 )
#830
b100100000000000000000000000000000000 M
1&
#832
0&
0'
b100 )
#834
b10010000000000000000000000000000000 M
1&
#836
0&
b101 )
#838
b1001000000000000000000000000000000 M
1&
#840
0&
b110 )
#842
b100100000000000000000000000000000 M
1&
#844
0&
b111 )
#846
b10010000000000000000000000000000 M
1&
#848
0&
b1000 )
#850
b1001000000000000000000000000000 M
1&
#852
0&
b1001 )
#854
b100100000000000000000000000000 M
1&
#856
0&
b1010 )
#858
b10010000000000000000000000000 M
1&
#860
0&
b1011 )
#862
b1001000000000000000000000000 M
1&
#864
0&
b1100 )
#866
b100100000000000000000000000 M
1&
#868
0&
b1101 )
#870
b10010000000000000000000000 M
1&
#872
0&
b1110 )
#874
b1001000000000000000000000 M
1&
#876
0&
b1111 )
#878
b100100000000000000000000 M
1&
#880
0&
b10000 )
#882
b10010000000000000000000 M
1&
#884
0&
b10001 )
#886
b1001000000000000000000 M
1&
#888
0&
b10010 )
#890
b100100000000000000000 M
1&
#892
0&
b10011 )
#894
b10010000000000000000 M
1&
#896
0&
b10100 )
#898
b1001000000000000000 M
1&
#900
0&
b10101 )
#902
b100100000000000000 M
1&
#904
0&
b10110 )
#906
b10010000000000000 M
1&
#908
0&
b10111 )
#910
b1001000000000000 M
1&
#912
0&
b11000 )
#914
b100100000000000 M
1&
#916
0&
b11001 )
#918
b10010000000000 M
1&
#920
0&
b11010 )
#922
b1001000000000 M
1&
#924
0&
b11011 )
#926
b100100000000 M
1&
#928
0&
b11100 )
#930
b10010000000 M
1&
#932
0&
b11101 )
#934
b1001000000 M
1&
#936
0&
b11110 )
#938
b100100000 M
1&
#940
0&
b11111 )
#942
b10010000 M
1&
#944
0&
b100000 )
#946
b1001000 M
1&
#948
0&
b100001 )
#950
b100100 M
1&
#952
0&
b100010 )
#954
b10010 M
1&
#956
0&
b100011 )
#958
1!
b1001 M
1&
#960
0&
0%
0"
b100100 )
#962
1&
#964
0&
#966
1&
#968
0&
1(
#970
b101 E
11
1J
b10111 N
1&
#972
0&
1$
0(
#974
b110 E
0J
b1010101010101010101010101010101 5
b1111 4
12
b101 D
1&
#976
0&
#978
b1000 E
b0 5
b0 4
02
b110 D
1&
#980
0&
#982
b1001 E
1.
b1000 D
1&
#984
0&
#986
b1010 E
0.
b1001 D
1&
#988
0&
#990
b111 E
b110111 N
b11111111111111111111111111111111 K
b1010 D
1&
#992
0&
#994
b111 D
1&
#996
0&
0$
b1010 O
#998
1&
#1000
0&
#1002
1&
#1004
0&
1"
#1006
b0 E
1I
b111011111111111111111111111111111111 M
1&
#1008
0&
1%
b0 )
#1010
b11101111111111111111111111111111111 M
0I
b0 D
1&
#1012
0&
1'
b1 )
#1014
b101110111111111111111111111111111111 M
1&
#1016
0&
0'
b10 )
#1018
b10111011111111111111111111111111111 M
1&
#1020
0&
1'
b11 )
#1022
b101011101111111111111111111111111111 M
1&
#1024
0&
0'
b100 )
#1026
b10101110111111111111111111111111111 M
1&
#1028
0&
b101 )
#1030
b1010111011111111111111111111111111 M
1&
#1032
0&
b110 )
#1034
b101011101111111111111111111111111 M
1&
#1036
0&
b111 )
#1038
b10101110111111111111111111111111 M
1&
#1040
0&
b1000 )
#1042
b1010111011111111111111111111111 M
1&
#1044
0&
b1001 )
#1046
b101011101111111111111111111111 M
1&
#1048
0&
b1010 )
#1050
b10101110111111111111111111111 M
1&
#1052
0&
b1011 )
#1054
b1010111011111111111111111111 M
1&
#1056
0&
b1100 )
#1058
b101011101111111111111111111 M
1&
#1060
0&
b1101 )
#1062
b10101110111111111111111111 M
1&
#1064
0&
b1110 )
#1066
b1010111011111111111111111 M
1&
#1068
0&
b1111 )
#1070
b101011101111111111111111 M
1&
#1072
0&
b10000 )
#1074
b10101110111111111111111 M
1&
#1076
0&
b10001 )
#1078
b1010111011111111111111 M
1&
#1080
0&
b10010 )
#1082
b101011101111111111111 M
1&
#1084
0&
b10011 )
#1086
b10101110111111111111 M
1&
#1088
0&
b10100 )
#1090
b1010111011111111111 M
1&
#1092
0&
b10101 )
#1094
b101011101111111111 M
1&
#1096
0&
b10110 )
#1098
b10101110111111111 M
1&
#1100
0&
b10111 )
#1102
b1010111011111111 M
1&
#1104
0&
b11000 )
#1106
b101011101111111 M
1&
#1108
0&
b11001 )
#1110
b10101110111111 M
1&
#1112
0&
b11010 )
#1114
b1010111011111 M
1&
#1116
0&
b11011 )
#1118
b101011101111 M
1&
#1120
0&
b11100 )
#1122
b10101110111 M
1&
#1124
0&
b11101 )
#1126
b1010111011 M
1&
#1128
0&
b11110 )
#1130
b101011101 M
1&
#1132
0&
b11111 )
#1134
0!
b10101110 M
1&
#1136
0&
b100000 )
#1138
1!
b1010111 M
1&
#1140
0&
b100001 )
#1142
b101011 M
1&
#1144
0&
b100010 )
#1146
b10101 M
1&
#1148
0&
b100011 )
#1150
0!
b1010 M
1&
#1152
0&
0%
0"
b100100 )
#1154
1&
#1156
0&
#1158
1&
#1160
0&
1(
#1162
b10111 N
1&
#1164
0&
1$
0(
#1166
1&
#1168
0&
#1170
1&
#1172
0&
#1174
1&
#1176
0&
#1178
1&
#1180
0&
#1182
1&
#1184
0&
#1186
1&
#1188
0&
#1190
1&
#1192
0&
#1194
1&
#1196
0&
#1198
1&
#1200
0&
#1202
1&
#1204
0&
#1206
1&
#1208
0&
#1210
1&
#1212
0&
#1214
1&
#1216
0&
#1218
1&
#1220
0&
#1222
1&
#1224
0&
#1226
1&
#1228
0&
#1230
1&
#1232
0&
#1234
1&
#1236
0&
#1238
1&
#1240
0&
#1242
1&
#1244
0&
#1246
1&
#1248
0&
#1250
1&
#1252
0&
#1254
1&
