project/DMA.v
module DMA #(
    parameter [31:0] Base = 32'h40000000)
    ( 
    input wire                    clock, reset,
    input wire                    dataReady,
    input wire                    readReady,
    input wire [31:0]             address_to_read,


    // Buffer interface
    output wire [31:0]            pushAddress,
    output wire [31:0]            popAddress,
    output wire [31:0]            pushData,
    output wire                   push,
    output wire                   switch,
    input wire [31:0]          popData,

    // here the bus interface is defined
    input wire [31:0] address_dataIN,
    input wire end_transactionIN, 
    input wire data_validIN, 
    input wire busyIN,
    input wire errorIN,

    output wire [31:0] address_dataOUT,
    output wire [3:0] byte_enableOUT,
    output wire [7:0] busrt_sizeOUT,
    output wire read_n_writeOUT,
    output wire begin_transactionOUT,
    output wire end_transactionOUT,
    output wire data_validOUT,
    output wire busyOUT,



    // here the interface with the arbitrer
    output wire        request,
    input wire         granted
    );


    // Write states
    localparam fsm_idle = 0;
    localparam fsm_write_request = 1;
    localparam fsm_write_sending_handshake = 2;
    localparam fsm_sending_data = 3;
    localparam fsm_end_transaction = 4;
    localparam fsm_reading_from_buffer = 5;
    localparam fsm_asking_for_buffer = 6;
    localparam fsm_read_request = 7;
    localparam fsm_read_sending_handshake = 8;
    localparam fsm_reading_data = 9;
    localparam fsm_writting_buffer = 10;

    reg [3:0] cur_state, nxt_state;
    wire [31:0] buffer_data;
    wire s_reading_from_buffer_done;
    wire [31:0] s_address_to_read;

    always @(posedge clock or posedge reset) begin
        if (reset) begin
            cur_state <= fsm_idle;
        end else begin
            cur_state <= nxt_state;
        end
    end


    always @(*) begin
        if (errorIN) begin
            nxt_state = fsm_idle;
        end else begin
            case(cur_state)
                fsm_idle: nxt_state = (dataReady) ? fsm_asking_for_buffer : (readReady) ? fsm_read_request : fsm_idle;
                fsm_asking_for_buffer: nxt_state = fsm_reading_from_buffer;
                fsm_reading_from_buffer: nxt_state = (s_reading_from_buffer_done) ? fsm_write_request : fsm_reading_from_buffer;
                fsm_write_request: nxt_state = (granted) ? fsm_write_sending_handshake : fsm_write_request;
                fsm_write_sending_handshake: nxt_state = fsm_sending_data;
                fsm_sending_data: nxt_state = (busyIN)? fsm_sending_data : fsm_end_transaction; 
                fsm_end_transaction: nxt_state = fsm_idle;

                fsm_read_request: nxt_state = (granted) ? fsm_read_sending_handshake : fsm_read_request;
                fsm_read_sending_handshake: nxt_state = fsm_reading_data;
                fsm_reading_data: nxt_state = (end_transactionIN) ? fsm_reading_data : fsm_writting_buffer;
                fsm_writting_buffer: nxt_state = fsm_end_transaction;
                // default: nxt_state = fsm_idle;
            endcase
        end
    end

    assign buffer_data = (cur_state == fsm_reading_from_buffer) ? popData : 
                         (cur_state == fsm_reading_data) ? address_dataIN :
                         (cur_state == fsm_end_transaction || errorIN == 1'b1 || reset == 1'b1) ? 32'h0 : buffer_data;


    // Buffer interface set to read at the same location
    assign pushAddress = 32'h0;
    assign popAddress = (cur_state == fsm_asking_for_buffer) ? 32'h0 : 32'h0; 
    assign pushData = (cur_state == fsm_writting_buffer) ? buffer_data : 32'h0;
    assign push = (cur_state == fsm_writting_buffer) ? 1'b1 : 1'b0;
    assign switch = 1'b0;
    assign s_reading_from_buffer_done = 1'b1;
    assign s_address_to_read = (cur_state == fsm_idle && readReady) ? address_to_read : 
                               (reset == 1'b1 || cur_state == fsm_end_transaction) ? 32'h0 : s_address_to_read;

    assign address_dataOUT = (cur_state == fsm_write_sending_handshake ) ? 32'h1 : 
                             (cur_state == fsm_read_sending_handshake) ? s_address_to_read :
                             (cur_state == fsm_sending_data) ? buffer_data : 32'h0; //for now only 1 byte
    assign byte_enableOUT = (cur_state == fsm_write_sending_handshake || cur_state == fsm_read_sending_handshake) ? 4'hF : 4'h0; 
    assign busrt_sizeOUT = (cur_state == fsm_write_sending_handshake) ? 8'h0 : 8'h0; //for now only 1 word
    assign read_n_writeOUT = (cur_state == fsm_write_sending_handshake) ? 1'b0 : 1'b1; 
    assign begin_transactionOUT = (cur_state == fsm_write_sending_handshake || cur_state == fsm_read_sending_handshake) ? 1'b1 : 1'b0;

    assign end_transactionOUT = ((cur_state == fsm_sending_data && busyIN == 1'b0) || errorIN == 1'b1) ? 1'b1 : 1'b0;

    assign data_validOUT = (cur_state == fsm_sending_data) ? 1'b1 : 1'b0;

    assign busyOUT = (cur_state == fsm_sending_data) ? 1'b0 : 1'b0; //for now always 0

    assign request = (cur_state == fsm_write_request || cur_state == fsm_read_request) ? 1'b1 : 1'b0;
endmodule

project/testbenches/tb_DMA.v
`timescale 1ps/1ps

module tb_DMA;

    // Testbench signals
    reg clock, reset, dataReady;
    reg [31:0] address_dataIN;
    reg end_transactionIN, data_validIN, busyIN, errorIN;
    reg granted;
    wire [31:0] address_dataOUT, pushAddress, popAddress, pushData;
    wire [3:0] byte_enableOUT;
    wire [7:0] busrt_sizeOUT;
    wire read_n_writeOUT, begin_transactionOUT, end_transactionOUT, data_validOUT, busyOUT, push, switch, request;
    reg [31:0] popData;
    reg readReady;
    reg [31:0] address_to_read;

    // Instantiate the DUT (Device Under Test)
    DMA dut (
        .clock(clock),
        .reset(reset),
        .dataReady(dataReady),
        .readReady(readReady),
        .address_to_read(address_to_read),
        .pushAddress(pushAddress),
        .popAddress(popAddress),
        .pushData(pushData),
        .push(push),
        .switch(switch),
        .popData(popData), // Not used in this testbench
        .address_dataIN(address_dataIN),
        .end_transactionIN(end_transactionIN),
        .data_validIN(data_validIN),
        .busyIN(busyIN),
        .errorIN(errorIN),
        .address_dataOUT(address_dataOUT),
        .byte_enableOUT(byte_enableOUT),
        .busrt_sizeOUT(busrt_sizeOUT),
        .read_n_writeOUT(read_n_writeOUT),
        .begin_transactionOUT(begin_transactionOUT),
        .end_transactionOUT(end_transactionOUT),
        .data_validOUT(data_validOUT),
        .busyOUT(busyOUT),
        .request(request),
        .granted(granted)
    );

    // Clock generation
    always #2 clock = ~clock;

    initial begin
        // Initialize signals
        clock = 0;
        reset = 1;
        dataReady = 0;
        address_dataIN = 32'h0;
        end_transactionIN = 0;
        data_validIN = 0;
        busyIN = 0;
        errorIN = 0;
        granted = 0;
        popData = 32'h0;
        readReady = 0;
        address_to_read = 32'h0;

        // Reset sequence
        #4 reset = 0;

        // Test case: Write operation
        #4 dataReady = 1; // Indicate data is ready
        #4 popData = 32'hA5A5A5A5; 
        #4 dataReady = 0; 
        #4;
        #4 granted = 1;
        #4 granted = 0;
        busyIN = 1;
        popData = 32'h0;
        #20 busyIN = 0;

        //Try to read from address 0x0A0A0A0A
        #12

        #4 address_to_read = 32'h0A0A0A0A;
        readReady = 1;
        #4 address_to_read = 32'h0;
        readReady = 0;
        #4 granted = 1;
        #2; //Handshake
        #4 address_dataIN = 32'h12345678;
        granted = 0;
        data_validIN = 1;
        end_transactionIN = 1;
        #4 data_validIN = 0;
        end_transactionIN = 0;

        
        #20$finish;
    end

    // Monitor signals
    initial begin
        $dumpfile("test_dma.vcd");
        $dumpvars(0, tb_DMA);
    end

endmodule

project/testbenches/test_dma.vcd
$date
	Mon Apr  7 14:45:41 2025
$end
$version
	Icarus Verilog
$end
$timescale
	1ps
$end
$scope module tb_DMA $end
$var wire 32 ! pushAddress [31:0] $end
$var wire 1 " switch $end
$var wire 1 # request $end
$var wire 1 $ read_n_writeOUT $end
$var wire 32 % pushData [31:0] $end
$var wire 1 & push $end
$var wire 32 ' popAddress [31:0] $end
$var wire 1 ( end_transactionOUT $end
$var wire 1 ) data_validOUT $end
$var wire 4 * byte_enableOUT [3:0] $end
$var wire 1 + busyOUT $end
$var wire 8 , busrt_sizeOUT [7:0] $end
$var wire 1 - begin_transactionOUT $end
$var wire 32 . address_dataOUT [31:0] $end
$var reg 32 / address_dataIN [31:0] $end
$var reg 32 0 address_to_read [31:0] $end
$var reg 1 1 busyIN $end
$var reg 1 2 clock $end
$var reg 1 3 dataReady $end
$var reg 1 4 data_validIN $end
$var reg 1 5 end_transactionIN $end
$var reg 1 6 errorIN $end
$var reg 1 7 granted $end
$var reg 32 8 popData [31:0] $end
$var reg 1 9 readReady $end
$var reg 1 : reset $end
$scope module dut $end
$var wire 32 ; address_dataIN [31:0] $end
$var wire 32 < address_to_read [31:0] $end
$var wire 1 1 busyIN $end
$var wire 1 2 clock $end
$var wire 1 3 dataReady $end
$var wire 1 4 data_validIN $end
$var wire 1 5 end_transactionIN $end
$var wire 1 6 errorIN $end
$var wire 1 7 granted $end
$var wire 32 = popData [31:0] $end
$var wire 32 > pushAddress [31:0] $end
$var wire 1 9 readReady $end
$var wire 1 : reset $end
$var wire 1 ? s_reading_from_buffer_done $end
$var wire 1 " switch $end
$var wire 32 @ s_address_to_read [31:0] $end
$var wire 1 # request $end
$var wire 1 $ read_n_writeOUT $end
$var wire 32 A pushData [31:0] $end
$var wire 1 & push $end
$var wire 32 B popAddress [31:0] $end
$var wire 1 ( end_transactionOUT $end
$var wire 1 ) data_validOUT $end
$var wire 4 C byte_enableOUT [3:0] $end
$var wire 1 + busyOUT $end
$var wire 8 D busrt_sizeOUT [7:0] $end
$var wire 32 E buffer_data [31:0] $end
$var wire 1 - begin_transactionOUT $end
$var wire 32 F address_dataOUT [31:0] $end
$var parameter 32 G Base $end
$var parameter 32 H fsm_asking_for_buffer $end
$var parameter 32 I fsm_end_transaction $end
$var parameter 32 J fsm_idle $end
$var parameter 32 K fsm_read_request $end
$var parameter 32 L fsm_read_sending_handshake $end
$var parameter 32 M fsm_reading_data $end
$var parameter 32 N fsm_reading_from_buffer $end
$var parameter 32 O fsm_sending_data $end
$var parameter 32 P fsm_write_request $end
$var parameter 32 Q fsm_write_sending_handshake $end
$var parameter 32 R fsm_writting_buffer $end
$var reg 4 S cur_state [3:0] $end
$var reg 4 T nxt_state [3:0] $end
$upscope $end
$upscope $end
$enddefinitions $end
$comment Show the parameter values. $end
$dumpall
b1010 R
b10 Q
b1 P
b11 O
b101 N
b1001 M
b1000 L
b111 K
b0 J
b100 I
b110 H
b1000000000000000000000000000000 G
$end
#0
$dumpvars
b0 T
b0 S
b0 F
b0 E
b0 D
b0 C
b0 B
b0 A
b0 @
1?
b0 >
b0 =
b0 <
b0 ;
1:
09
b0 8
07
06
05
04
03
02
01
b0 0
b0 /
b0 .
0-
b0 ,
0+
b0 *
0)
0(
b0 '
0&
b0 %
1$
0#
0"
b0 !
$end
#2
12
#4
02
0:
#6
12
#8
b110 T
02
13
#10
b101 T
b110 S
12
#12
02
b10100101101001011010010110100101 8
b10100101101001011010010110100101 =
#14
b10100101101001011010010110100101 E
b1 T
b101 S
12
#16
02
03
#18
1#
b1 S
12
#20
02
#22
12
#24
b10 T
02
17
#26
b1111 *
b1111 C
1-
0#
b1 .
b1 F
0$
b11 T
b10 S
12
#28
02
b0 8
b0 =
11
07
#30
b0 *
b0 C
0-
b10100101101001011010010110100101 .
b10100101101001011010010110100101 F
1$
1)
b11 S
12
#32
02
#34
12
#36
02
#38
12
#40
02
#42
12
#44
02
#46
12
#48
1(
b100 T
02
01
#50
b0 E
b0 .
b0 F
0(
0)
b0 T
b100 S
12
#52
02
#54
b0 S
12
#56
02
#58
12
#60
02
#62
12
#64
b1010000010100000101000001010 @
b111 T
02
19
b1010000010100000101000001010 0
b1010000010100000101000001010 <
#66
1#
b111 S
12
#68
02
09
b0 0
b0 <
#70
12
#72
b1000 T
02
17
#74
b1010000010100000101000001010 .
b1010000010100000101000001010 F
b1111 *
b1111 C
1-
0#
b1001 T
b1000 S
12
#76
02
#78
b10010001101000101011001111000 E
b0 .
b0 F
b0 *
b0 C
0-
b1001 S
12
15
14
07
b10010001101000101011001111000 /
b10010001101000101011001111000 ;
#80
02
#82
b10010001101000101011001111000 %
b10010001101000101011001111000 A
1&
b1010 S
b100 T
12
05
04
#84
02
#86
b0 E
b0 @
b0 %
b0 A
0&
b0 T
b100 S
12
#88
02
#90
b0 S
12
