project/modules/jtag_interface/clock_synchronizer.v
module clock_synchronizer #(
    parameter integer SYNC_WIDTH = 1)
    (
        input wire clk_in,
        input wire clk_out,
        input wire[SYNC_WIDTH-1:0] to_sync,
        input wire n_reset,
        output wire[SYNC_WIDTH-1:0] sync_out
    );

    reg[SYNC_WIDTH-1:0] sync_reg_1, sync_reg_2, sync_reg_3;
    assign sync_out = sync_reg_3;


    always @(posedge clk_in or negedge n_reset or posedge sync_reg_3) begin
        if (!n_reset | sync_reg_3) begin
            sync_reg_1 <= 0;
        end else begin
            sync_reg_1 <= to_sync | sync_reg_1;
        end
    end

    always @(posedge clk_out or negedge n_reset or posedge sync_reg_3) begin
        if (!n_reset | sync_reg_3) begin
            sync_reg_2 <= 0;
        end else begin
            sync_reg_2 <= sync_reg_1;
        end
    end

    always @(posedge clk_out or negedge n_reset) begin
        if (!n_reset) begin
            sync_reg_3 <= 0;
        end else begin
            sync_reg_3 <= sync_reg_2;
        end
    end
endmodule

project/modules/jtag_interface/testbenches/tb_clock_synchronizer.v
`timescale 1ns/1ps

module tb_clock_synchronizer;

    // Testbench signals
    reg clk_in;
    reg clk_out;
    reg[9:0] to_sync;
    reg n_reset;
    wire[9:0] sync_out;

    // Instantiate the DUT (Device Under Test)
    clock_synchronizer #(10) uut (
        .clk_in(clk_in),
        .clk_out(clk_out),
        .to_sync(to_sync),
        .sync_out(sync_out),
        .n_reset(n_reset)
    );

    // Clock generation for clk_in
    initial begin
        clk_in = 0;
        forever #5 clk_in = ~clk_in; // 10ns period
    end

    // Clock generation for clk_out
    initial begin
        clk_out = 0;
        forever #7 clk_out = ~clk_out; // 14ns period
    end

    // Test stimulus
    initial begin
        // Initialize inputs
        to_sync = 0; // Set to_sync high
        n_reset = 0;
        #10 n_reset = 1; // Release reset after 10ns


        #10 to_sync = 10'h3FF;

        // Finish simulation
        #100 $finish;
    end

    // Monitor signals
    initial begin
         $dumpfile("test_clock_sync.vcd");
        $dumpvars(0, tb_clock_synchronizer);
    end

endmodule

project/testbenches/test_clock_sync.vcd
$date
	Thu May  1 12:00:28 2025
$end
$version
	Icarus Verilog
$end
$timescale
	1ps
$end
$scope module tb_clock_synchronizer $end
$var wire 10 ! sync_out [9:0] $end
$var reg 1 " clk_in $end
$var reg 1 # clk_out $end
$var reg 1 $ n_reset $end
$var reg 10 % to_sync [9:0] $end
$scope module uut $end
$var wire 1 " clk_in $end
$var wire 1 # clk_out $end
$var wire 1 $ n_reset $end
$var wire 10 & sync_out [9:0] $end
$var wire 10 ' to_sync [9:0] $end
$var parameter 32 ( SYNC_WIDTH $end
$var reg 10 ) sync_reg_1 [9:0] $end
$var reg 10 * sync_reg_2 [9:0] $end
$var reg 10 + sync_reg_3 [9:0] $end
$upscope $end
$upscope $end
$enddefinitions $end
$comment Show the parameter values. $end
$dumpall
b1010 (
$end
#0
$dumpvars
b0 +
b0 *
b0 )
b0 '
b0 &
b0 %
0$
0#
0"
b0 !
$end
#5000
1"
#7000
1#
#10000
0"
1$
#14000
0#
#15000
1"
#20000
0"
b1111111111 %
b1111111111 '
#21000
1#
#25000
b1111111111 )
1"
#28000
0#
#30000
0"
#35000
b1111111111 *
1"
1#
#40000
0"
#42000
0#
#45000
1"
#49000
b0 *
b0 )
b1111111111 !
b1111111111 &
b1111111111 +
1#
#50000
0"
#55000
1"
#56000
0#
#60000
0"
#63000
b0 !
b0 &
b0 +
1#
#65000
b1111111111 )
1"
#70000
0"
0#
#75000
1"
#77000
b1111111111 *
1#
#80000
0"
#84000
0#
#85000
1"
#90000
0"
#91000
b0 *
b0 )
b1111111111 !
b1111111111 &
b1111111111 +
1#
#95000
1"
#98000
0#
#100000
0"
#105000
b0 !
b0 &
b0 +
1"
1#
#110000
0"
#112000
0#
#115000
b1111111111 )
1"
#119000
b1111111111 *
1#
