project/DMA.v
module DMA #(
    parameter [31:0] Base = 32'h40000000)
    ( 
    input wire                    clock, reset,
    input wire                    dataReady,

    // Buffer interface
    output wire [31:0]            pushAddress,
    output wire [31:0]            popAddress,
    output wire [31:0]            pushData,
    output wire                   push,
    output wire                   switch,
    input wire [31:0]          popData,

    // here the bus interface is defined
    input wire [31:0] address_dataIN,
    input wire end_transactionIN, 
    input wire data_validIN, 
    input wire busyIN,
    input wire errorIN,

    output wire [31:0] address_dataOUT,
    output wire [3:0] byte_enableOUT,
    output wire [7:0] busrt_sizeOUT,
    output wire read_n_writeOUT,
    output wire begin_transactionOUT,
    output wire end_transactionOUT,
    output wire data_validOUT,
    output wire busyOUT,



    // here the interface with the arbitrer
    output wire        request,
    input wire         granted
    );


    // Write states
    localparam fsm_idle = 0;
    localparam fsm_write_request = 1;
    localparam fsm_sending_handshake = 2;
    localparam fsm_sending_data = 3;
    localparam fsm_end_transaction = 4;
    localparam fsm_reading_from_buffer = 5;
    localparam fsm_asking_for_buffer = 6;

    reg [2:0] cur_state, nxt_state;
    wire [31:0] buffer_data;
    wire s_reading_from_buffer_done;

    always @(posedge clock or posedge reset) begin
        if (reset) begin
            cur_state <= fsm_idle;
        end else begin
            cur_state <= nxt_state;
        end
    end


    always @(*) begin
        if (errorIN) begin
            nxt_state = fsm_idle;
        end else begin
            case(cur_state)
                fsm_idle: nxt_state = (dataReady) ? fsm_asking_for_buffer : fsm_idle;
                fsm_asking_for_buffer: nxt_state = fsm_reading_from_buffer;
                fsm_reading_from_buffer: nxt_state = (s_reading_from_buffer_done) ? fsm_write_request : fsm_reading_from_buffer;
                fsm_write_request: nxt_state = (granted) ? fsm_sending_handshake : fsm_write_request;
                fsm_sending_handshake: nxt_state = fsm_sending_data;

                fsm_sending_data: nxt_state = (busyIN)? fsm_sending_data : fsm_end_transaction; 
                fsm_end_transaction: nxt_state = fsm_idle;
                default: nxt_state = fsm_idle;
            endcase
        end
    end

    assign buffer_data = (cur_state == fsm_reading_from_buffer) ? popData : 
                         (cur_state == fsm_end_transaction || errorIN == 1'b1 || reset == 1'b1) ? 32'h0 : buffer_data;


    // Buffer interface set to read at the same location
    assign pushAddress = 32'h0;
    assign popAddress = (cur_state == fsm_asking_for_buffer) ? 32'h0 : 32'h0; 
    assign pushData = 32'h0;
    assign push = 1'b0;
    assign switch = 1'b0;
    assign s_reading_from_buffer_done = 1'b1;

    assign address_dataOUT = (cur_state == fsm_sending_handshake) ? 32'h1 : (cur_state == fsm_sending_data) ? buffer_data : 32'h0; //for now only 1 byte
    assign byte_enableOUT = (cur_state == fsm_sending_handshake) ? 4'hF : 4'h0; 
    assign busrt_sizeOUT = (cur_state == fsm_sending_handshake) ? 8'h0 : 8'h0; //for now only 1 word
    assign read_n_writeOUT = (cur_state == fsm_sending_handshake) ? 1'b0 : 1'b0; // for now only write
    assign begin_transactionOUT = (cur_state == fsm_sending_handshake) ? 1'b1 : 1'b0;

    assign end_transactionOUT = ((cur_state == fsm_sending_data && busyIN == 1'b0) || errorIN == 1'b1) ? 1'b1 : 1'b0;

    assign data_validOUT = (cur_state == fsm_sending_data) ? 1'b1 : 1'b0;

    assign busyOUT = (cur_state == fsm_sending_data) ? 1'b0 : 1'b0; //for now always 0

    assign request = (cur_state == fsm_write_request) ? 1'b1 : 1'b0;


endmodule

project/testbenches/tb_DMA.v
`timescale 1ps/1ps

module tb_DMA;

    // Testbench signals
    reg clock, reset, dataReady;
    reg [31:0] address_dataIN;
    reg end_transactionIN, data_validIN, busyIN, errorIN;
    reg granted;
    wire [31:0] address_dataOUT, pushAddress, popAddress, pushData;
    wire [3:0] byte_enableOUT;
    wire [7:0] busrt_sizeOUT;
    wire read_n_writeOUT, begin_transactionOUT, end_transactionOUT, data_validOUT, busyOUT, push, switch, request;
    reg [31:0] popData;

    // Instantiate the DUT (Device Under Test)
    DMA dut (
        .clock(clock),
        .reset(reset),
        .dataReady(dataReady),
        .pushAddress(pushAddress),
        .popAddress(popAddress),
        .pushData(pushData),
        .push(push),
        .switch(switch),
        .popData(popData), // Not used in this testbench
        .address_dataIN(address_dataIN),
        .end_transactionIN(end_transactionIN),
        .data_validIN(data_validIN),
        .busyIN(busyIN),
        .errorIN(errorIN),
        .address_dataOUT(address_dataOUT),
        .byte_enableOUT(byte_enableOUT),
        .busrt_sizeOUT(busrt_sizeOUT),
        .read_n_writeOUT(read_n_writeOUT),
        .begin_transactionOUT(begin_transactionOUT),
        .end_transactionOUT(end_transactionOUT),
        .data_validOUT(data_validOUT),
        .busyOUT(busyOUT),
        .request(request),
        .granted(granted)
    );

    // Clock generation
    always #2 clock = ~clock;

    initial begin
        // Initialize signals
        clock = 0;
        reset = 1;
        dataReady = 0;
        address_dataIN = 32'h0;
        end_transactionIN = 0;
        data_validIN = 0;
        busyIN = 0;
        errorIN = 0;
        granted = 0;
        popData = 32'h0;

        // Reset sequence
        #4 reset = 0;

        // Test case: Write operation
        #4 dataReady = 1; // Indicate data is ready
        #4 popData = 32'hA5A5A5A5; 
        #4 dataReady = 0; 
        #4;
        #4 granted = 1;
        #4 granted = 0;
        busyIN = 1;
        popData = 32'h0;
        #20 busyIN = 0;
        #20$finish;
    end

    // Monitor signals
    initial begin
        $dumpfile("test_dma.vcd");
        $dumpvars(0, tb_DMA);
    end

endmodule

project/testbenches/test_dma.vcd
$date
	Mon Apr  7 12:00:08 2025
$end
$version
	Icarus Verilog
$end
$timescale
	1ps
$end
$scope module tb_DMA $end
$var wire 1 ! push $end
$var wire 32 " pushAddress [31:0] $end
$var wire 32 # pushData [31:0] $end
$var wire 1 $ switch $end
$var wire 1 % request $end
$var wire 1 & read_n_writeOUT $end
$var wire 32 ' popAddress [31:0] $end
$var wire 1 ( end_transactionOUT $end
$var wire 1 ) data_validOUT $end
$var wire 4 * byte_enableOUT [3:0] $end
$var wire 1 + busyOUT $end
$var wire 8 , busrt_sizeOUT [7:0] $end
$var wire 1 - begin_transactionOUT $end
$var wire 32 . address_dataOUT [31:0] $end
$var reg 32 / address_dataIN [31:0] $end
$var reg 1 0 busyIN $end
$var reg 1 1 clock $end
$var reg 1 2 dataReady $end
$var reg 1 3 data_validIN $end
$var reg 1 4 end_transactionIN $end
$var reg 1 5 errorIN $end
$var reg 1 6 granted $end
$var reg 32 7 popData [31:0] $end
$var reg 1 8 reset $end
$scope module dut $end
$var wire 32 9 address_dataIN [31:0] $end
$var wire 1 0 busyIN $end
$var wire 1 1 clock $end
$var wire 1 2 dataReady $end
$var wire 1 3 data_validIN $end
$var wire 1 4 end_transactionIN $end
$var wire 1 5 errorIN $end
$var wire 1 6 granted $end
$var wire 32 : popData [31:0] $end
$var wire 1 ! push $end
$var wire 32 ; pushAddress [31:0] $end
$var wire 32 < pushData [31:0] $end
$var wire 1 8 reset $end
$var wire 1 = s_reading_from_buffer_done $end
$var wire 1 $ switch $end
$var wire 1 % request $end
$var wire 1 & read_n_writeOUT $end
$var wire 32 > popAddress [31:0] $end
$var wire 1 ( end_transactionOUT $end
$var wire 1 ) data_validOUT $end
$var wire 4 ? byte_enableOUT [3:0] $end
$var wire 1 + busyOUT $end
$var wire 8 @ busrt_sizeOUT [7:0] $end
$var wire 32 A buffer_data [31:0] $end
$var wire 1 - begin_transactionOUT $end
$var wire 32 B address_dataOUT [31:0] $end
$var parameter 32 C Base $end
$var parameter 32 D fsm_asking_for_buffer $end
$var parameter 32 E fsm_end_transaction $end
$var parameter 32 F fsm_idle $end
$var parameter 32 G fsm_reading_from_buffer $end
$var parameter 32 H fsm_sending_data $end
$var parameter 32 I fsm_sending_handshake $end
$var parameter 32 J fsm_write_request $end
$var reg 3 K cur_state [2:0] $end
$var reg 3 L nxt_state [2:0] $end
$upscope $end
$upscope $end
$enddefinitions $end
$comment Show the parameter values. $end
$dumpall
b1 J
b10 I
b11 H
b101 G
b0 F
b100 E
b110 D
b1000000000000000000000000000000 C
$end
#0
$dumpvars
b0 L
b0 K
b0 B
b0 A
b0 @
b0 ?
b0 >
1=
b0 <
b0 ;
b0 :
b0 9
18
b0 7
06
05
04
03
02
01
00
b0 /
b0 .
0-
b0 ,
0+
b0 *
0)
0(
b0 '
0&
0%
0$
b0 #
b0 "
0!
$end
#2
11
#4
01
08
#6
11
#8
b110 L
01
12
#10
b101 L
b110 K
11
#12
01
b10100101101001011010010110100101 7
b10100101101001011010010110100101 :
#14
b10100101101001011010010110100101 A
b1 L
b101 K
11
#16
01
02
#18
1%
b1 K
11
#20
01
#22
11
#24
b10 L
01
16
#26
b1 .
b1 B
b1111 *
b1111 ?
1-
0%
b11 L
b10 K
11
#28
01
b0 7
b0 :
10
06
#30
b10100101101001011010010110100101 .
b10100101101001011010010110100101 B
b0 *
b0 ?
0-
1)
b11 K
11
#32
01
#34
11
#36
01
#38
11
#40
01
#42
11
#44
01
#46
11
#48
1(
b100 L
01
00
#50
b0 A
0(
b0 .
b0 B
0)
b0 L
b100 K
11
#52
01
#54
b0 K
11
