project/modules/jtag_interface/chain1.v
module chain1(
    // JTAG signals
    input wire JTCK,
    input wire JTDI,
    input wire JRTI1,
    input wire JSHIFT,
    input wire JUPDATE,
    input wire JRSTN,
    input wire JCE1,
    output wire JTD1,

    // Connection to the ping-pong buffer
    output wire [8:0] pp_address,
    output wire pp_writeEnable,
    output wire [31:0] pp_dataIn,
    input wire [31:0] pp_dataOut,
    output wire pp_switch,

    // Connection with the DMA
    output wire [31:0] dma_address,
    output wire dma_data_ready,
    output wire [3:0] dma_byte_enable,
    output wire dma_readReady,
    input wire switch_ready,

    // Visual Clues 
    output wire [5:0] status_reg_out
);


reg [31:0] data_reg;
reg [7:0] remaining_size_reg;
reg [7:0] pp_address_reg;
wire is_operation_running;
wire s_ready_to_switch;
reg [31:0] read_data_from_buffer;
reg r_data_shifted_in;
reg r_launch_read;
reg r_data_shifted_out;

assign s_ready_to_switch = switch_ready;

assign n_reset = JRSTN;

reg [31:0] address_reg;
reg [3:0] byte_enable_reg;
reg [7:0] busrt_size_reg;
reg [7:0] block_size_reg;

reg [35:0] shadow_reg;
reg [35:0] shift_reg;
reg [35:0] updated_data_reg;

reg update_reg;

reg [5:0] status_next;
reg [5:0] status_reg;

localparam IDLE =                       0;
localparam write_FILL_BUFFER =          1;
localparam write_WAIT_FOR_SWITCH =      2;
localparam write_SWITCH_BUFFER =        3;
localparam write_LAUNCH_WRITE =         4;
localparam read_LAUNCH_READ =           5;
localparam read_WAIT_FOR_SWITCH =       6;
localparam read_DATA_READY_TO_READ =    7;
localparam read_SWITCH_BUFFER =         8;
localparam read_ASK_BUFFER =            9;
localparam read_STORE_BUFFER_ANSWER =   10;



reg [4:0] chain1_cur_state;
reg [4:0] chain1_nxt_state;
assign status_reg_out = status_reg;

// The status register is used to indicate the current state of the operation
assign is_operation_running = (status_reg[3] == 1'b1 | status_reg[4] == 1'b1) ? 1'b1 : 1'b0;


assign JTD1 = shift_reg[0];

always @(posedge JTCK) begin
    if (n_reset == 0) begin
        shift_reg <= 36'b0;
    end
    // handle the JTAG signals
    else begin
         if (JCE1) begin
        // Shifting data in
            if (JSHIFT) begin
                shift_reg <= {JTDI, shift_reg[35:1]};
            end
            // capture the status register
            else begin
                shift_reg <= shadow_reg;
            end
        end 

    end
    update_reg <= (n_reset == 1'b0) ? 0 : JUPDATE;
    updated_data_reg <= (n_reset == 1'b0) ? 0 : (JUPDATE == 1'b1) ? shift_reg : updated_data_reg;
    // Precompute the status register
    if (JUPDATE == 1'b1) begin
        case (shift_reg[3:0])
            4'b0001: status_next = status_reg | 6'b000001;
            4'b0010: status_next = status_reg | 6'b000010;
            4'b0011: status_next = status_reg | 6'b000100;
            default: status_next = status_reg;
        endcase
    end
end

always @(posedge JTCK) begin
    if (n_reset == 0) begin
        shadow_reg <= 36'b0;
        address_reg <= 32'b0;
        byte_enable_reg <= 4'b1111;
        busrt_size_reg <= 8'b0;
        remaining_size_reg <= 8'b0;
        status_reg <= 6'b0;
    end
    else if (update_reg == 1'b1) begin

        status_reg <= status_next;
                        
        shadow_reg <=   (updated_data_reg[3:0] == 4'b0100) ? address_reg :
                        (updated_data_reg[3:0] == 4'b0101) ? byte_enable_reg :
                        (updated_data_reg[3:0] == 4'b0110) ? busrt_size_reg :
                        {30'b0, status_next}; 

        address_reg <= (updated_data_reg[3:0] == 4'b0001) ? updated_data_reg[35:4] : address_reg;

        byte_enable_reg <= (updated_data_reg[3:0] == 4'b0010) ? updated_data_reg[7:4] : byte_enable_reg;

        busrt_size_reg <= (updated_data_reg[3:0] == 4'b0011) ? updated_data_reg[11:4] : busrt_size_reg;

    end
end

// always @(posedge JTCK or negedge JRSTN) begin
//     if (JRSTN == 0) begin
//         shift_reg <= 34'b0;
//         status_reg <= 6'b0;
//         address_reg <= 32'b0;
//         byte_enable_reg <= 4'b0;
//         busrt_size_reg <= 8'b0;
//         remaining_size_reg <= 8'b0;
//         pp_address_reg <= 8'b0;
//         r_data_shifted_in <= 1'b0;
//         r_launch_read <= 1'b0;
//         r_data_shifted_out <= 1'b0;
//         read_data_from_buffer <= 32'b0;
//         chain1_cur_state <= IDLE;
//     end
//     else  begin
//         // Reset the registers
//         r_data_shifted_in <= 1'b0;
//         r_launch_read <= 1'b0;
//         r_data_shifted_out <= 1'b0;
        
//         // Move to the next state
//         chain1_cur_state <= chain1_nxt_state;

//         // Handle internal signals
//         case (chain1_cur_state)
//             write_FILL_BUFFER: begin 
//                 if (remaining_size_reg != 0) begin
//                     remaining_size_reg <= remaining_size_reg - 1;
//                 end
//             end 
//             write_LAUNCH_WRITE: begin
//                 if (remaining_size_reg == 0) begin
//                     status_reg <= status_reg & 6'b0111;
//                 end
//             end
//             read_STORE_BUFFER_ANSWER: begin
//                 read_data_from_buffer <= pp_dataOut;
//                 status_reg <= status_reg | 6'b100000;
//             end
//             read_DATA_READY_TO_READ: begin
//                 if (r_data_shifted_out) begin
//                     status_reg[5] <= 1'b0;
//                     if (remaining_size_reg == 0) begin
//                         status_reg[4] <= 1'b0;
//                     end
//                     else begin
//                         remaining_size_reg <= remaining_size_reg - 1;
//                     end
//                 end
//             end
//         endcase

//         // Update datas registers based on the instruction used
//         if (JUPDATE) begin
//             case (shift_reg[3:0])
//                 4'b0001: begin
//                     // Writting to address register
//                     if (~is_operation_running) begin
//                         address_reg <= shift_reg[35:4];
//                         status_reg <= status_reg | 6'b0001;
//                     end
//                 end
//                 4'b0010: begin
//                     // writting to byte enable register
//                     if (~is_operation_running) begin
//                         byte_enable_reg <= shift_reg[7:4];
//                         status_reg <= status_reg | 6'b0010;
//                     end
//                 end
//                 4'b0011: begin
//                     // writting the size reg
//                     if (~is_operation_running) begin
//                         busrt_size_reg <= shift_reg[11:4];
//                         remaining_size_reg <= shift_reg[11:4];
//                         status_reg <= status_reg | 6'b0100;
//                     end
//                 end
//                 4'b1000: begin
//                     // Send data
//                     data_reg <= shift_reg[35:4];
//                     status_reg <= status_reg | 6'b1000;
//                     r_data_shifted_in <= 1'b1;
//                 end
//                 4'b1001: begin
//                     // Start the read operation
//                     status_reg <= status_reg | 6'b10000;
//                     r_launch_read <= 1'b1;
//                 end
//                 4'b1010: begin 
//                     // Read operation and move to next word
//                     status_reg[5] <= 1'b0;
//                 end
//             endcase 
//         end
//     end
// end

// always @(posedge JTCK or negedge JRSTN) 
//     begin
//         if (JRSTN == 0) begin
//             // chain1_cur_state <= IDLE;
//             // read_data_from_buffer <= 32'b0;
//         end
//         else begin 
//         //     chain1_cur_state = chain1_nxt_state;
//         //     case (chain1_cur_state)
//         //         write_FILL_BUFFER: begin 
//         //             if (remaining_size_reg != 0) begin
//         //                 remaining_size_reg <= remaining_size_reg - 1;
//         //             end
//         //         end 
//         //         write_LAUNCH_WRITE: begin
//         //             if (remaining_size_reg == 0) begin
//         //                 status_reg <= status_reg & 6'b0111;
//         //             end
//         //         end
//         //         read_STORE_BUFFER_ANSWER: begin
//         //             read_data_from_buffer <= pp_dataOut;
//         //             status_reg <= status_reg | 6'b100000;
//         //         end
//         //         read_DATA_READY_TO_READ: begin
//         //             if (r_data_shifted_out) begin
//         //                 status_reg[5] <= 1'b0;
//         //                 if (remaining_size_reg == 0) begin
//         //                     status_reg[4] <= 1'b0;
//         //                 end
//         //                 else begin
//         //                     remaining_size_reg <= remaining_size_reg - 1;
//         //                 end
//         //             end
//         //         end
//         // endcase
//         end
//     end 

// always @(*) begin
//     case (chain1_cur_state)
//         IDLE: begin
//             if (r_data_shifted_in) begin
//                 chain1_nxt_state <= write_FILL_BUFFER;
//             end
//             else begin
//                 if (r_launch_read) begin
//                     chain1_nxt_state <= read_LAUNCH_READ;
//                 end
//                 else begin
//                     chain1_nxt_state <= IDLE;
//                 end
//             end
//         end
//         write_FILL_BUFFER: begin
//             if (remaining_size_reg == 0) begin
//                 chain1_nxt_state <= write_WAIT_FOR_SWITCH;
//             end
//             else begin
//                 chain1_nxt_state <= IDLE;
//             end
//         end

//         write_WAIT_FOR_SWITCH: begin
//             if (s_ready_to_switch) begin
//                 chain1_nxt_state <= write_SWITCH_BUFFER;
//             end
//             else begin
//                 chain1_nxt_state <= write_WAIT_FOR_SWITCH;
//             end
//         end

//         write_SWITCH_BUFFER: begin
//             chain1_nxt_state <= write_LAUNCH_WRITE;
//         end

//         write_LAUNCH_WRITE: begin
//             chain1_nxt_state <= IDLE;
//         end

//         read_LAUNCH_READ: begin
//             chain1_nxt_state <= read_WAIT_FOR_SWITCH;
//         end

//         read_WAIT_FOR_SWITCH: begin
//             if (s_ready_to_switch) begin
//                 chain1_nxt_state <= read_SWITCH_BUFFER;
//             end
//             else begin
//                 chain1_nxt_state <= read_WAIT_FOR_SWITCH;
//             end
//         end

//         read_SWITCH_BUFFER: begin
//             chain1_nxt_state <= read_ASK_BUFFER;
//         end

//         read_ASK_BUFFER: begin
//             chain1_nxt_state <= read_STORE_BUFFER_ANSWER;
//         end

//         read_STORE_BUFFER_ANSWER: begin
//             chain1_nxt_state <= read_DATA_READY_TO_READ;
//         end

//         read_DATA_READY_TO_READ: begin
//             if (r_data_shifted_out) begin
//                 // r_data_shifted_out <= 1'b0;
//                 if (remaining_size_reg == 0) begin
//                     chain1_nxt_state <= IDLE;
//                 end
//                 else begin
//                     chain1_nxt_state <= read_ASK_BUFFER;
//                 end
//             end
//             else begin
//                 chain1_nxt_state <= read_DATA_READY_TO_READ;
//             end
            
//         end
//         default: begin
//             chain1_nxt_state <= IDLE;
//         end

//     endcase 
// end

//     assign pp_address = (chain1_cur_state == write_FILL_BUFFER | chain1_cur_state == read_ASK_BUFFER) ? {1'b0, pp_address_reg}: 9'b0;
//     assign pp_writeEnable = (chain1_cur_state == write_FILL_BUFFER) ? 1'b1 : 1'b0;
//     assign pp_dataIn = (chain1_cur_state == write_FILL_BUFFER) ? data_reg : 32'b0;
//     assign pp_switch = (chain1_cur_state == write_SWITCH_BUFFER | chain1_cur_state == read_SWITCH_BUFFER) ? 1'b1 : 1'b0;
//     assign dma_address = (chain1_cur_state == write_LAUNCH_WRITE | chain1_cur_state == read_LAUNCH_READ) ? address_reg : 32'b0;
//     assign dma_data_ready = (chain1_cur_state == write_LAUNCH_WRITE) ? 1'b1 : 1'b0;
//     assign dma_byte_enable = (chain1_cur_state == write_LAUNCH_WRITE | chain1_cur_state == read_LAUNCH_READ) ? byte_enable_reg : 4'b0;
//     assign dma_readReady = (chain1_cur_state == read_LAUNCH_READ) ? 1'b1 : 1'b0;


endmodule

project/modules/jtag_interface/testbenches/tb_chain1.v
`timescale 1ns/1ps;

module tb_chain1;
    
    reg JTCK;
    reg JTDI;
    reg JRTI1;
    reg JSHIFT;
    reg JUPDATE;
    reg JRSTN;
    reg JCE1;
    wire JTD1;

    // Instantiate the DUT (Device Under Test)
    chain1 dut (
        .JTCK(JTCK),
        .JTDI(JTDI),
        .JRTI1(JRTI1),
        .JSHIFT(JSHIFT),
        .JUPDATE(JUPDATE),
        .JRSTN(JRSTN),
        .JCE1(JCE1),
        .JTD1(JTD1),
        .pp_dataOut(32'hFFFFFFFF),
        .switch_ready(1'b1)
    );

    // Clock generation
    initial begin
        JTCK = 0; // Initialize JTCK
    end

    always #2 JTCK = ~JTCK;

    integer i;
    task sendInstruction(input [35:0] instruction);
        begin
            JRTI1 = 0;
            #8;
            JCE1 = 1;
            #4;
            for (i = 0; i < 36; i = i + 1) begin
                JTDI = instruction[i];
                JSHIFT = 1;
                #4;
            end
            JCE1 = 0;
            JSHIFT = 0;
            #8;
            JUPDATE = 1;
            #4;
            JUPDATE = 0;
            JRTI1 = 1;
            #4;
        end
    endtask

    initial begin
        // Initialize signals
        JTCK = 0;
        JTDI = 0;
        JRTI1 = 0;
        JSHIFT = 0;
        JUPDATE = 0;
        JRSTN = 1;
        JCE1 = 0;

        // Reset the DUT
        #8;
        JRSTN = 0;
        #8;
        JRSTN = 1;
        #8;
        JRTI1 = 1;
        #8;

        // Send an instruction to the DUT
        sendInstruction(36'b010101010101010101010101010101010001);
        $display("Value of address reg: %b", dut.address_reg);

        sendInstruction(36'b11100010);
        $display("Value of byte enable reg: %b", dut.byte_enable_reg);

        sendInstruction(36'b10101010011);
        // sendInstruction(36'b00011);
        $display("Value of busrt size reg: %b", dut.busrt_size_reg);

        $display("Value of status reg: %b", dut.status_reg);
        #4;


        // try to read the address register 
        sendInstruction(36'b100);
        #12;
        sendInstruction(36'b0);

        // try to read the byte enable register and the busrt size register
        sendInstruction(36'b101);
        #12;
        sendInstruction(36'b110);
        #12;
        sendInstruction(36'b000);


        // // Send a read instruction
        // sendInstruction(36'b1001);
        // #20

        // // Read the data from the buffer
        // sendInstruction(36'b1010);
        #160;
        $finish;
    end

    initial begin
        $dumpfile("test_chain1.vcd");
        $dumpvars(0, tb_chain1);
    end

endmodule

project/modules/jtag_interface/testbenches/test_chain1.vcd
$date
	Wed May 14 18:04:19 2025
$end
$version
	Icarus Verilog
$end
$timescale
	1ps
$end
$scope module tb_chain1 $end
$var wire 1 ! JTD1 $end
$var reg 1 " JCE1 $end
$var reg 1 # JRSTN $end
$var reg 1 $ JRTI1 $end
$var reg 1 % JSHIFT $end
$var reg 1 & JTCK $end
$var reg 1 ' JTDI $end
$var reg 1 ( JUPDATE $end
$var integer 32 ) i [31:0] $end
$scope module dut $end
$var wire 1 " JCE1 $end
$var wire 1 # JRSTN $end
$var wire 1 $ JRTI1 $end
$var wire 1 % JSHIFT $end
$var wire 1 & JTCK $end
$var wire 1 ' JTDI $end
$var wire 1 ( JUPDATE $end
$var wire 32 * dma_address [31:0] $end
$var wire 4 + dma_byte_enable [3:0] $end
$var wire 1 , dma_data_ready $end
$var wire 1 - dma_readReady $end
$var wire 1 . n_reset $end
$var wire 9 / pp_address [8:0] $end
$var wire 32 0 pp_dataIn [31:0] $end
$var wire 32 1 pp_dataOut [31:0] $end
$var wire 1 2 pp_switch $end
$var wire 1 3 pp_writeEnable $end
$var wire 1 4 s_ready_to_switch $end
$var wire 6 5 status_reg_out [5:0] $end
$var wire 1 6 switch_ready $end
$var wire 1 7 is_operation_running $end
$var wire 1 ! JTD1 $end
$var parameter 32 8 IDLE $end
$var parameter 32 9 read_ASK_BUFFER $end
$var parameter 32 : read_DATA_READY_TO_READ $end
$var parameter 32 ; read_LAUNCH_READ $end
$var parameter 32 < read_STORE_BUFFER_ANSWER $end
$var parameter 32 = read_SWITCH_BUFFER $end
$var parameter 32 > read_WAIT_FOR_SWITCH $end
$var parameter 32 ? write_FILL_BUFFER $end
$var parameter 32 @ write_LAUNCH_WRITE $end
$var parameter 32 A write_SWITCH_BUFFER $end
$var parameter 32 B write_WAIT_FOR_SWITCH $end
$var reg 32 C address_reg [31:0] $end
$var reg 8 D busrt_size_reg [7:0] $end
$var reg 4 E byte_enable_reg [3:0] $end
$var reg 8 F remaining_size_reg [7:0] $end
$var reg 36 G shadow_reg [35:0] $end
$var reg 36 H shift_reg [35:0] $end
$var reg 6 I status_next [5:0] $end
$var reg 6 J status_reg [5:0] $end
$var reg 1 K update_reg $end
$var reg 36 L updated_data_reg [35:0] $end
$upscope $end
$scope task sendInstruction $end
$var reg 36 M instruction [35:0] $end
$upscope $end
$upscope $end
$enddefinitions $end
$comment Show the parameter values. $end
$dumpall
b10 B
b11 A
b100 @
b1 ?
b110 >
b1000 =
b1010 <
b101 ;
b111 :
b1001 9
b0 8
$end
#0
$dumpvars
bx M
bx L
xK
bx J
bx I
bx H
bx G
bx F
bx E
bx D
bx C
x7
16
bx 5
14
z3
z2
b11111111111111111111111111111111 1
bz 0
bz /
1.
z-
z,
bz +
bz *
bx )
0(
0'
0&
0%
0$
1#
0"
x!
$end
#2000
0K
1&
#4000
0&
#6000
1&
#8000
0&
0.
0#
#10000
07
0!
b0 L
b0 H
b0 5
b0 J
b0 F
b0 D
b1111 E
b0 C
b0 G
1&
#12000
0&
#14000
1&
#16000
0&
1.
1#
#18000
1&
#20000
0&
#22000
1&
#24000
0&
1$
#26000
1&
#28000
0&
#30000
1&
#32000
0&
0$
b10101010101010101010101010101010001 M
#34000
1&
#36000
0&
#38000
1&
#40000
0&
1"
#42000
1&
#44000
0&
1%
1'
b0 )
#46000
b100000000000000000000000000000000000 H
1&
#48000
0&
0'
b1 )
#50000
b10000000000000000000000000000000000 H
1&
#52000
0&
b10 )
#54000
b1000000000000000000000000000000000 H
1&
#56000
0&
b11 )
#58000
b100000000000000000000000000000000 H
1&
#60000
0&
1'
b100 )
#62000
b100010000000000000000000000000000000 H
1&
#64000
0&
0'
b101 )
#66000
b10001000000000000000000000000000000 H
1&
#68000
0&
1'
b110 )
#70000
b101000100000000000000000000000000000 H
1&
#72000
0&
0'
b111 )
#74000
b10100010000000000000000000000000000 H
1&
#76000
0&
1'
b1000 )
#78000
b101010001000000000000000000000000000 H
1&
#80000
0&
0'
b1001 )
#82000
b10101000100000000000000000000000000 H
1&
#84000
0&
1'
b1010 )
#86000
b101010100010000000000000000000000000 H
1&
#88000
0&
0'
b1011 )
#90000
b10101010001000000000000000000000000 H
1&
#92000
0&
1'
b1100 )
#94000
b101010101000100000000000000000000000 H
1&
#96000
0&
0'
b1101 )
#98000
b10101010100010000000000000000000000 H
1&
#100000
0&
1'
b1110 )
#102000
b101010101010001000000000000000000000 H
1&
#104000
0&
0'
b1111 )
#106000
b10101010101000100000000000000000000 H
1&
#108000
0&
1'
b10000 )
#110000
b101010101010100010000000000000000000 H
1&
#112000
0&
0'
b10001 )
#114000
b10101010101010001000000000000000000 H
1&
#116000
0&
1'
b10010 )
#118000
b101010101010101000100000000000000000 H
1&
#120000
0&
0'
b10011 )
#122000
b10101010101010100010000000000000000 H
1&
#124000
0&
1'
b10100 )
#126000
b101010101010101010001000000000000000 H
1&
#128000
0&
0'
b10101 )
#130000
b10101010101010101000100000000000000 H
1&
#132000
0&
1'
b10110 )
#134000
b101010101010101010100010000000000000 H
1&
#136000
0&
0'
b10111 )
#138000
b10101010101010101010001000000000000 H
1&
#140000
0&
1'
b11000 )
#142000
b101010101010101010101000100000000000 H
1&
#144000
0&
0'
b11001 )
#146000
b10101010101010101010100010000000000 H
1&
#148000
0&
1'
b11010 )
#150000
b101010101010101010101010001000000000 H
1&
#152000
0&
0'
b11011 )
#154000
b10101010101010101010101000100000000 H
1&
#156000
0&
1'
b11100 )
#158000
b101010101010101010101010100010000000 H
1&
#160000
0&
0'
b11101 )
#162000
b10101010101010101010101010001000000 H
1&
#164000
0&
1'
b11110 )
#166000
b101010101010101010101010101000100000 H
1&
#168000
0&
0'
b11111 )
#170000
b10101010101010101010101010100010000 H
1&
#172000
0&
1'
b100000 )
#174000
b101010101010101010101010101010001000 H
1&
#176000
0&
0'
b100001 )
#178000
b10101010101010101010101010101000100 H
1&
#180000
0&
1'
b100010 )
#182000
b101010101010101010101010101010100010 H
1&
#184000
0&
0'
b100011 )
#186000
1!
b10101010101010101010101010101010001 H
1&
#188000
0&
0%
0"
b100100 )
#190000
1&
#192000
0&
#194000
1&
#196000
0&
1(
#198000
b10101010101010101010101010101010001 L
1K
b1 I
1&
#200000
0&
1$
0(
#202000
0K
b1010101010101010101010101010101 C
b1 G
b1 5
b1 J
1&
#204000
0&
0$
b11100010 M
#206000
1&
#208000
0&
#210000
1&
#212000
0&
1"
#214000
b1 H
1&
#216000
0&
1%
b0 )
#218000
0!
b0 H
1&
#220000
0&
1'
b1 )
#222000
b100000000000000000000000000000000000 H
1&
#224000
0&
0'
b10 )
#226000
b10000000000000000000000000000000000 H
1&
#228000
0&
b11 )
#230000
b1000000000000000000000000000000000 H
1&
#232000
0&
b100 )
#234000
b100000000000000000000000000000000 H
1&
#236000
0&
1'
b101 )
#238000
b100010000000000000000000000000000000 H
1&
#240000
0&
b110 )
#242000
b110001000000000000000000000000000000 H
1&
#244000
0&
b111 )
#246000
b111000100000000000000000000000000000 H
1&
#248000
0&
0'
b1000 )
#250000
b11100010000000000000000000000000000 H
1&
#252000
0&
b1001 )
#254000
b1110001000000000000000000000000000 H
1&
#256000
0&
b1010 )
#258000
b111000100000000000000000000000000 H
1&
#260000
0&
b1011 )
#262000
b11100010000000000000000000000000 H
1&
#264000
0&
b1100 )
#266000
b1110001000000000000000000000000 H
1&
#268000
0&
b1101 )
#270000
b111000100000000000000000000000 H
1&
#272000
0&
b1110 )
#274000
b11100010000000000000000000000 H
1&
#276000
0&
b1111 )
#278000
b1110001000000000000000000000 H
1&
#280000
0&
b10000 )
#282000
b111000100000000000000000000 H
1&
#284000
0&
b10001 )
#286000
b11100010000000000000000000 H
1&
#288000
0&
b10010 )
#290000
b1110001000000000000000000 H
1&
#292000
0&
b10011 )
#294000
b111000100000000000000000 H
1&
#296000
0&
b10100 )
#298000
b11100010000000000000000 H
1&
#300000
0&
b10101 )
#302000
b1110001000000000000000 H
1&
#304000
0&
b10110 )
#306000
b111000100000000000000 H
1&
#308000
0&
b10111 )
#310000
b11100010000000000000 H
1&
#312000
0&
b11000 )
#314000
b1110001000000000000 H
1&
#316000
0&
b11001 )
#318000
b111000100000000000 H
1&
#320000
0&
b11010 )
#322000
b11100010000000000 H
1&
#324000
0&
b11011 )
#326000
b1110001000000000 H
1&
#328000
0&
b11100 )
#330000
b111000100000000 H
1&
#332000
0&
b11101 )
#334000
b11100010000000 H
1&
#336000
0&
b11110 )
#338000
b1110001000000 H
1&
#340000
0&
b11111 )
#342000
b111000100000 H
1&
#344000
0&
b100000 )
#346000
b11100010000 H
1&
#348000
0&
b100001 )
#350000
b1110001000 H
1&
#352000
0&
b100010 )
#354000
b111000100 H
1&
#356000
0&
b100011 )
#358000
b11100010 H
1&
#360000
0&
0%
0"
b100100 )
#362000
1&
#364000
0&
#366000
1&
#368000
0&
1(
#370000
b11100010 L
1K
b11 I
1&
#372000
0&
1$
0(
#374000
b1110 E
b11 G
b11 5
b11 J
0K
1&
#376000
0&
0$
b10101010011 M
#378000
1&
#380000
0&
#382000
1&
#384000
0&
1"
#386000
1!
b11 H
1&
#388000
0&
1%
1'
b0 )
#390000
b100000000000000000000000000000000001 H
1&
#392000
0&
b1 )
#394000
0!
b110000000000000000000000000000000000 H
1&
#396000
0&
0'
b10 )
#398000
b11000000000000000000000000000000000 H
1&
#400000
0&
b11 )
#402000
b1100000000000000000000000000000000 H
1&
#404000
0&
1'
b100 )
#406000
b100110000000000000000000000000000000 H
1&
#408000
0&
0'
b101 )
#410000
b10011000000000000000000000000000000 H
1&
#412000
0&
1'
b110 )
#414000
b101001100000000000000000000000000000 H
1&
#416000
0&
0'
b111 )
#418000
b10100110000000000000000000000000000 H
1&
#420000
0&
1'
b1000 )
#422000
b101010011000000000000000000000000000 H
1&
#424000
0&
0'
b1001 )
#426000
b10101001100000000000000000000000000 H
1&
#428000
0&
1'
b1010 )
#430000
b101010100110000000000000000000000000 H
1&
#432000
0&
0'
b1011 )
#434000
b10101010011000000000000000000000000 H
1&
#436000
0&
b1100 )
#438000
b1010101001100000000000000000000000 H
1&
#440000
0&
b1101 )
#442000
b101010100110000000000000000000000 H
1&
#444000
0&
b1110 )
#446000
b10101010011000000000000000000000 H
1&
#448000
0&
b1111 )
#450000
b1010101001100000000000000000000 H
1&
#452000
0&
b10000 )
#454000
b101010100110000000000000000000 H
1&
#456000
0&
b10001 )
#458000
b10101010011000000000000000000 H
1&
#460000
0&
b10010 )
#462000
b1010101001100000000000000000 H
1&
#464000
0&
b10011 )
#466000
b101010100110000000000000000 H
1&
#468000
0&
b10100 )
#470000
b10101010011000000000000000 H
1&
#472000
0&
b10101 )
#474000
b1010101001100000000000000 H
1&
#476000
0&
b10110 )
#478000
b101010100110000000000000 H
1&
#480000
0&
b10111 )
#482000
b10101010011000000000000 H
1&
#484000
0&
b11000 )
#486000
b1010101001100000000000 H
1&
#488000
0&
b11001 )
#490000
b101010100110000000000 H
1&
#492000
0&
b11010 )
#494000
b10101010011000000000 H
1&
#496000
0&
b11011 )
#498000
b1010101001100000000 H
1&
#500000
0&
b11100 )
#502000
b101010100110000000 H
1&
#504000
0&
b11101 )
#506000
b10101010011000000 H
1&
#508000
0&
b11110 )
#510000
b1010101001100000 H
1&
#512000
0&
b11111 )
#514000
b101010100110000 H
1&
#516000
0&
b100000 )
#518000
b10101010011000 H
1&
#520000
0&
b100001 )
#522000
b1010101001100 H
1&
#524000
0&
b100010 )
#526000
b101010100110 H
1&
#528000
0&
b100011 )
#530000
1!
b10101010011 H
1&
#532000
0&
0%
0"
b100100 )
#534000
1&
#536000
0&
#538000
1&
#540000
0&
1(
#542000
b10101010011 L
1K
b111 I
1&
#544000
0&
1$
0(
#546000
0K
b1010101 D
b111 G
b111 5
b111 J
1&
#548000
0&
#550000
1&
#552000
0&
0$
b100 M
#554000
1&
#556000
0&
#558000
1&
#560000
0&
1"
#562000
b111 H
1&
#564000
0&
1%
b0 )
#566000
b11 H
1&
#568000
0&
b1 )
#570000
b1 H
1&
#572000
0&
1'
b10 )
#574000
0!
b100000000000000000000000000000000000 H
1&
#576000
0&
0'
b11 )
#578000
b10000000000000000000000000000000000 H
1&
#580000
0&
b100 )
#582000
b1000000000000000000000000000000000 H
1&
#584000
0&
b101 )
#586000
b100000000000000000000000000000000 H
1&
#588000
0&
b110 )
#590000
b10000000000000000000000000000000 H
1&
#592000
0&
b111 )
#594000
b1000000000000000000000000000000 H
1&
#596000
0&
b1000 )
#598000
b100000000000000000000000000000 H
1&
#600000
0&
b1001 )
#602000
b10000000000000000000000000000 H
1&
#604000
0&
b1010 )
#606000
b1000000000000000000000000000 H
1&
#608000
0&
b1011 )
#610000
b100000000000000000000000000 H
1&
#612000
0&
b1100 )
#614000
b10000000000000000000000000 H
1&
#616000
0&
b1101 )
#618000
b1000000000000000000000000 H
1&
#620000
0&
b1110 )
#622000
b100000000000000000000000 H
1&
#624000
0&
b1111 )
#626000
b10000000000000000000000 H
1&
#628000
0&
b10000 )
#630000
b1000000000000000000000 H
1&
#632000
0&
b10001 )
#634000
b100000000000000000000 H
1&
#636000
0&
b10010 )
#638000
b10000000000000000000 H
1&
#640000
0&
b10011 )
#642000
b1000000000000000000 H
1&
#644000
0&
b10100 )
#646000
b100000000000000000 H
1&
#648000
0&
b10101 )
#650000
b10000000000000000 H
1&
#652000
0&
b10110 )
#654000
b1000000000000000 H
1&
#656000
0&
b10111 )
#658000
b100000000000000 H
1&
#660000
0&
b11000 )
#662000
b10000000000000 H
1&
#664000
0&
b11001 )
#666000
b1000000000000 H
1&
#668000
0&
b11010 )
#670000
b100000000000 H
1&
#672000
0&
b11011 )
#674000
b10000000000 H
1&
#676000
0&
b11100 )
#678000
b1000000000 H
1&
#680000
0&
b11101 )
#682000
b100000000 H
1&
#684000
0&
b11110 )
#686000
b10000000 H
1&
#688000
0&
b11111 )
#690000
b1000000 H
1&
#692000
0&
b100000 )
#694000
b100000 H
1&
#696000
0&
b100001 )
#698000
b10000 H
1&
#700000
0&
b100010 )
#702000
b1000 H
1&
#704000
0&
b100011 )
#706000
b100 H
1&
#708000
0&
0%
0"
b100100 )
#710000
1&
#712000
0&
#714000
1&
#716000
0&
1(
#718000
b100 L
1K
1&
#720000
0&
1$
0(
#722000
0K
b1010101010101010101010101010101 G
1&
#724000
0&
#726000
1&
#728000
0&
#730000
1&
#732000
0&
#734000
1&
#736000
0&
0$
b0 M
#738000
1&
#740000
0&
#742000
1&
#744000
0&
1"
#746000
1!
b1010101010101010101010101010101 H
1&
#748000
0&
1%
b0 )
#750000
0!
b101010101010101010101010101010 H
1&
#752000
0&
b1 )
#754000
1!
b10101010101010101010101010101 H
1&
#756000
0&
b10 )
#758000
0!
b1010101010101010101010101010 H
1&
#760000
0&
b11 )
#762000
1!
b101010101010101010101010101 H
1&
#764000
0&
b100 )
#766000
0!
b10101010101010101010101010 H
1&
#768000
0&
b101 )
#770000
1!
b1010101010101010101010101 H
1&
#772000
0&
b110 )
#774000
0!
b101010101010101010101010 H
1&
#776000
0&
b111 )
#778000
1!
b10101010101010101010101 H
1&
#780000
0&
b1000 )
#782000
0!
b1010101010101010101010 H
1&
#784000
0&
b1001 )
#786000
1!
b101010101010101010101 H
1&
#788000
0&
b1010 )
#790000
0!
b10101010101010101010 H
1&
#792000
0&
b1011 )
#794000
1!
b1010101010101010101 H
1&
#796000
0&
b1100 )
#798000
0!
b101010101010101010 H
1&
#800000
0&
b1101 )
#802000
1!
b10101010101010101 H
1&
#804000
0&
b1110 )
#806000
0!
b1010101010101010 H
1&
#808000
0&
b1111 )
#810000
1!
b101010101010101 H
1&
#812000
0&
b10000 )
#814000
0!
b10101010101010 H
1&
#816000
0&
b10001 )
#818000
1!
b1010101010101 H
1&
#820000
0&
b10010 )
#822000
0!
b101010101010 H
1&
#824000
0&
b10011 )
#826000
1!
b10101010101 H
1&
#828000
0&
b10100 )
#830000
0!
b1010101010 H
1&
#832000
0&
b10101 )
#834000
1!
b101010101 H
1&
#836000
0&
b10110 )
#838000
0!
b10101010 H
1&
#840000
0&
b10111 )
#842000
1!
b1010101 H
1&
#844000
0&
b11000 )
#846000
0!
b101010 H
1&
#848000
0&
b11001 )
#850000
1!
b10101 H
1&
#852000
0&
b11010 )
#854000
0!
b1010 H
1&
#856000
0&
b11011 )
#858000
1!
b101 H
1&
#860000
0&
b11100 )
#862000
0!
b10 H
1&
#864000
0&
b11101 )
#866000
1!
b1 H
1&
#868000
0&
b11110 )
#870000
0!
b0 H
1&
#872000
0&
b11111 )
#874000
1&
#876000
0&
b100000 )
#878000
1&
#880000
0&
b100001 )
#882000
1&
#884000
0&
b100010 )
#886000
1&
#888000
0&
b100011 )
#890000
1&
#892000
0&
0%
0"
b100100 )
#894000
1&
#896000
0&
#898000
1&
#900000
0&
1(
#902000
b0 L
1K
1&
#904000
0&
1$
0(
#906000
0K
b111 G
1&
