project/modules/jtag_interface/DMA.v
module DMA #(
    parameter [31:0] Base = 32'h40000000)
    ( 
    input wire                    clock, n_reset,
    input wire                    ipcore_launch_write,
    input wire                    ipcore_launch_read,
    input wire                    ipcore_launch_simple_switch,
    input wire [3:0]              ipcore_byte_enable,
    input wire [31:0]             ipcore_address,
    input wire [7:0]              ipcore_burst_size,
    output wire                   ipcore_dma_busy,
    output wire                   ipcore_operation_ended,
    output wire [7:0]             ipcore_block_sizeOUT,
    input wire [7:0]              ipcore_block_sizeIN,


    // Buffer interface
    output wire [8:0]             pp_address,
    output wire [31:0]            pp_dataIn,
    output wire                   pp_writeEnable,
    input wire [31:0]             pp_dataOut,

    // here the bus interface is defined
    input wire [31:0] address_dataIN,
    input wire end_transactionIN, 
    input wire data_validIN, 
    input wire busyIN,
    input wire bus_errorIN,

    output wire [31:0] address_dataOUT,
    output wire [3:0] byte_enableOUT,
    output wire [7:0] busrt_sizeOUT,
    output wire read_n_writeOUT,
    output wire begin_transactionOUT,
    output wire end_transactionOUT,
    output wire data_validOUT,
    output wire busyOUT,



    // here the interface with the arbitrer
    output wire        requestTransaction,
    input wire         transactionGranted,


    output wire [7:0]  s_dma_cur_state

    );

    // Reg for sdram control

    reg [31:0] bus_start_address_reg;
    reg [7:0] bus_burst_size_reg;
    reg [3:0] bus_byte_enable_reg;
    reg [31:0] bus_block_size_reg;

    always @(posedge clock) begin
        bus_start_address_reg <= (n_reset == 1'b0) ? 32'h0 : 
                                (ipcore_launch_write == 1'b1 || ipcore_launch_read == 1'b1) ? ipcore_address : bus_start_address_reg;
        bus_burst_size_reg <= (n_reset == 1'b0) ? 8'h0 :
                                (ipcore_launch_write == 1'b1 || ipcore_launch_read == 1'b1) ? ipcore_burst_size : bus_burst_size_reg;
        bus_byte_enable_reg <= (n_reset == 1'b0) ? 4'h0 :
                                (ipcore_launch_write == 1'b1 || ipcore_launch_read == 1'b1) ? ipcore_byte_enable : bus_byte_enable_reg;
        bus_block_size_reg <= (n_reset == 1'b0) ? 32'h0 :
                                (ipcore_launch_write == 1'b1 || ipcore_launch_read == 1'b1 || ipcore_launch_simple_switch == 1'b1) ? ipcore_block_sizeIN : bus_block_size_reg;
    end

    // regs for all bus-in signals
    reg [31:0] address_dataIN_reg;
    reg end_transactionIN_reg;
    reg data_validIN_reg;

    always @(posedge clock) begin
        address_dataIN_reg <= address_dataIN;
        end_transactionIN_reg <= end_transactionIN;
        data_validIN_reg <= data_validIN;
    end



    // DMA state machine
    localparam [4:0] fsm_idle = 4'd0;
    localparam [4:0] fsm_init = 4'd1;
    localparam [4:0] fsm_request_bus = 4'd2;
    localparam [4:0] fsm_set_up_transaction = 4'd3;
    localparam [4:0] fsm_read = 4'd4;
    localparam [4:0] fsm_wait_end = 4'd5;
    localparam [4:0] fsm_write = 4'd6;
    localparam [4:0] fsm_end_transaction_error = 4'd7;
    localparam [4:0] fsm_end_write_transaction = 4'd8;

    reg [4:0] cur_state, nxt_state;
    reg read_n_write_reg;
    // One more bit to indicate when it reaches 0
    reg [8:0] words_written_reg;

    assign ipcore_dma_busy = (cur_state == fsm_idle) ? 1'b0 : 1'b1;
    wire s_dma_done;

    always @* begin
        case (cur_state)
            fsm_idle                  : nxt_state <= (ipcore_launch_write == 1'b1 || ipcore_launch_read == 1'b1) ? fsm_init : fsm_idle;
            fsm_init                  : nxt_state <= fsm_request_bus;
            fsm_request_bus           : nxt_state <= (transactionGranted == 1'b1) ? fsm_set_up_transaction : fsm_request_bus;
            fsm_set_up_transaction    : nxt_state <= (read_n_write_reg == 1'b1) ? fsm_read : fsm_write;
            fsm_read                  : nxt_state <= (bus_errorIN == 1'b1) ? fsm_wait_end :
                                                // End of the transacsion
                                                (end_transactionIN_reg == 1'b1 && s_dma_done == 1'b1) ? fsm_idle :
                                                // End of the burst
                                                (end_transactionIN_reg == 1'b1) ? fsm_request_bus : fsm_read;
                                                    //Wait for the end of the transaction
            fsm_wait_end              : nxt_state <= (end_transactionIN_reg == 1'b1) ? fsm_idle : fsm_wait_end;
            fsm_write                 : nxt_state <= (bus_errorIN == 1'b1) ? fsm_end_transaction_error :
                                                    // End of the burst
                                                    (words_written_reg == 8'b1 && busyIN == 1'b0) ? fsm_end_write_transaction : fsm_write;
                                                    // Either end of the transaction or end of the burst
            fsm_end_write_transaction : nxt_state <= (s_dma_done == 1'b1) ? fsm_idle : fsm_request_bus;
            default                   : nxt_state <= fsm_idle;
        endcase
    end

    always @(posedge clock) begin
        // Update the state machine
        cur_state <= (n_reset == 1'b0) ? fsm_idle : nxt_state;
        // Update if it is a read or a write
        read_n_write_reg <= (cur_state == fsm_idle) ? ipcore_launch_read : read_n_write_reg;
    end

    // All the register that are to be updated during the burst
    reg [31:0] updated_bus_start_address_reg;
    reg [8:0] updated_block_size_reg;
    reg [8:0] pp_address_reg;
    reg operation_launch_reg;
    reg operation_ended_reg;

    // Is the teransaction done?
    assign s_dma_done = (updated_block_size_reg == 9'b0) ? 1'b1 : 
                              // end of transaction at the same time of last valid data
                              (updated_block_size_reg == 9'b1 && end_transactionIN_reg == 1'b1) ? 1'b1 : 1'b0;
    // Write in buffer iff the data read is valid
    assign pp_writeEnable = (cur_state == fsm_read && data_validIN_reg == 1'b1) ? 1'b1 : 1'b0;
    // Say if we actually wrote data on the bus or it was busy or the burst was over
    wire busWrite = (cur_state == fsm_write ) ? ~busyIN & ~words_written_reg[7] : 1'b0;

    always @(posedge clock) begin
        // Update all the regs : bus start address + 4, block size - 1 and pp address + 1
        updated_bus_start_address_reg <= (n_reset == 1'b0) ? 32'h0 : 
                                        (cur_state == fsm_init) ? bus_start_address_reg : 
                                        (busWrite == 1'b1 || pp_writeEnable == 1'b1) ? updated_bus_start_address_reg + 32'h4 : updated_bus_start_address_reg;
        updated_block_size_reg <= (n_reset == 1'b0) ? 9'h0 :
                                    (cur_state == fsm_init) ? bus_block_size_reg : 
                                    (busWrite == 1'b1 || pp_writeEnable == 1'b1) ? updated_block_size_reg - 9'h1 : updated_block_size_reg;
        pp_address_reg <= (n_reset == 1'b0 || cur_state == fsm_init) ? 9'h0 :
                          (busWrite == 1'b1 || pp_writeEnable == 1'b1) ? pp_address_reg + 8'h1 : pp_address_reg;
        operation_launch_reg <= (n_reset == 1'b0) ? 1'b0 :
                                (operation_ended_reg == 1'b1) ? 1'b0 :
                                (cur_state == fsm_init) ? ~ipcore_launch_simple_switch : operation_launch_reg;
        operation_ended_reg <= (n_reset == 1'b0) ? 1'b0 :
                                (ipcore_launch_read == 1'b1 || ipcore_launch_write == 1'b1 || ipcore_launch_simple_switch == 1'b1) ? 1'b0 :
                                (cur_state == fsm_idle && operation_launch_reg == 1'b1) ? 1'b1 : operation_ended_reg;
    end


    // Bus output signals
    reg data_validOUT_reg;
    reg [3:0] byte_enableOUT_reg;
    reg [7:0] burst_sizeOUT_reg;
    reg [31:0] address_dataOUT_reg;
    reg read_n_writeOUT_reg, begin_transactionOUT_reg, end_transactionOUT_reg;

    always @(posedge clock) begin
        begin_transactionOUT_reg <= (cur_state == fsm_set_up_transaction) ? 1'b1 : 1'b0;
        read_n_writeOUT_reg <= (cur_state == fsm_set_up_transaction) ? read_n_write_reg : 1'b0;
        byte_enableOUT_reg <= (cur_state == fsm_set_up_transaction) ? bus_byte_enable_reg : 4'h0;
        burst_sizeOUT_reg <= (cur_state == fsm_set_up_transaction) ? bus_burst_size_reg : 8'h0;
        address_dataOUT_reg <= (cur_state == fsm_set_up_transaction) ? {updated_bus_start_address_reg[31:2], 2'b00} :
                                (busWrite == 1'b1) ? pp_dataOut :
                                // stall in case of busy in
                                (cur_state == fsm_read && busyIN == 1'b1) ? address_dataOUT_reg : 32'h0;
        end_transactionOUT_reg <= (cur_state == fsm_end_transaction_error || cur_state == fsm_end_write_transaction) ? 1'b1 : 1'b0;
        data_validOUT_reg <= (cur_state == fsm_write && busyIN == 1'b1) ? data_validOUT_reg: busWrite;
    end

    assign address_dataOUT = (data_validOUT_reg == 1'b1) ? pp_dataOut : address_dataOUT_reg;
    assign byte_enableOUT = byte_enableOUT_reg;
    assign busrt_sizeOUT = burst_sizeOUT_reg;
    assign read_n_writeOUT = read_n_writeOUT_reg;
    assign begin_transactionOUT = begin_transactionOUT_reg;
    assign end_transactionOUT = end_transactionOUT_reg;
    assign data_validOUT = data_validOUT_reg;
    assign busyOUT = 0; // never busy


    // Bus arbitrer signals
    assign requestTransaction = (cur_state == fsm_request_bus) ? 1'b1 : 1'b0;

    // words written update 

    wire [7:0] s_actual_burst_size;
    assign s_actual_burst_size = bus_burst_size_reg + 8'h1;
    always @(posedge clock) begin
        if (n_reset == 1'b0) begin
            words_written_reg <= 9'h0;
        end else if (cur_state == fsm_set_up_transaction) begin
            if (updated_block_size_reg > s_actual_burst_size) begin
                words_written_reg <= s_actual_burst_size;
            end else begin
                words_written_reg <= updated_block_size_reg;
            end
        end else if (busWrite == 1'b1) begin
            words_written_reg <= words_written_reg - 9'h1;
        end
    end

    assign ipcore_block_sizeOUT = bus_block_size_reg;
    assign pp_address = pp_address_reg;
    assign pp_dataIn = address_dataIN_reg;
    assign ipcore_operation_ended = operation_ended_reg;


    assign s_dma_cur_state = {updated_bus_start_address_reg[9:2]};

endmodule

project/modules/jtag_interface/testbenches/tb_DMA.v
`timescale 1ns/1ps

module tb_DMA;

    // DUT signals
    reg clock;
    reg n_reset;
    reg ipcore_launch_write;
    reg ipcore_launch_read;
    reg [3:0] ipcore_byte_enable;
    reg [31:0] ipcore_address;
    reg [7:0] ipcore_burst_size;
    wire ipcore_dma_busy;
    wire [7:0] ipcore_block_sizeOUT;
    reg [7:0] ipcore_block_sizeIN;

    wire [8:0] pp_address;
    wire [31:0] pp_dataIn;
    wire pp_writeEnable;
    reg [31:0] pp_dataOut;

    reg [31:0] address_dataIN;
    reg end_transactionIN;
    reg data_validIN;
    reg busyIN;
    reg bus_errorIN;

    wire [31:0] address_dataOUT;
    wire [3:0] byte_enableOUT;
    wire [7:0] busrt_sizeOUT;
    wire read_n_writeOUT;
    wire begin_transactionOUT;
    wire end_transactionOUT;
    wire data_validOUT;
    wire busyOUT;

    wire requestTransaction;
    reg transactionGranted;

    wire [3:0] s_dma_cur_state;

    // Instantiate the DUT
    DMA dut (
        .clock(clock),
        .n_reset(n_reset),
        .ipcore_launch_write(ipcore_launch_write),
        .ipcore_launch_read(ipcore_launch_read),
        .ipcore_byte_enable(ipcore_byte_enable),
        .ipcore_address(ipcore_address),
        .ipcore_burst_size(ipcore_burst_size),
        .ipcore_dma_busy(ipcore_dma_busy),
        .ipcore_block_sizeIN(ipcore_block_sizeIN),
        .ipcore_block_sizeOUT(ipcore_block_sizeOUT),
        .pp_address(pp_address),
        .pp_dataIn(pp_dataIn),
        .pp_writeEnable(pp_writeEnable),
        .pp_dataOut(pp_dataOut),
        .address_dataIN(address_dataIN),
        .end_transactionIN(end_transactionIN),
        .data_validIN(data_validIN),
        .busyIN(busyIN),
        .bus_errorIN(bus_errorIN),
        .address_dataOUT(address_dataOUT),
        .byte_enableOUT(byte_enableOUT),
        .busrt_sizeOUT(busrt_sizeOUT),
        .read_n_writeOUT(read_n_writeOUT),
        .begin_transactionOUT(begin_transactionOUT),
        .end_transactionOUT(end_transactionOUT),
        .data_validOUT(data_validOUT),
        .busyOUT(busyOUT),
        .requestTransaction(requestTransaction),
        .transactionGranted(transactionGranted),
        .s_dma_cur_state(s_dma_cur_state)
    );

    // Clock generation
    initial begin
        clock = 0;
        forever #2 clock = ~clock; // 100MHz clock
    end
    initial begin
        // Initialize all signals to default values
        n_reset = 0;
        ipcore_launch_write = 0;
        ipcore_launch_read = 0;
        ipcore_byte_enable = 4'b0000;
        ipcore_address = 32'b0;
        ipcore_burst_size = 8'b0;
        ipcore_block_sizeIN = 8'b0;
        pp_dataOut = 32'b0;
        address_dataIN = 32'b0;
        end_transactionIN = 0;
        data_validIN = 0;
        busyIN = 0;
        bus_errorIN = 0;
        transactionGranted = 0;

        // Release reset after 10ns
        #20 n_reset = 1;

        // Test write transaction
        #12 ipcore_launch_write = 1;
        ipcore_address = 32'hAABBCCDD;
        ipcore_burst_size = 8'd10;
        ipcore_byte_enable = 4'b1111;
        ipcore_block_sizeIN = 8'd19;

        #4 ipcore_launch_write = 0; // Deassert write signal
        transactionGranted = 1; // Grant transaction
        #20 transactionGranted = 0; // Simulate data input
        #4 busyIN = 1; // Simulate busy signal
        #40 busyIN = 0; // Simulate end of transaction
        #4 transactionGranted = 1; // Grant transaction

        #80;

        n_reset = 0; // Assert reset
        #4 n_reset = 1; // Deassert reset

        // Test write transaction with error
        #12 ipcore_launch_write = 1;
        ipcore_address = 32'hAABBCCDD;
        ipcore_burst_size = 8'd100;
        ipcore_byte_enable = 4'b1111;
        ipcore_block_sizeIN = 8'd200;
        #4 ipcore_launch_write = 0; // Deassert write signal
        transactionGranted = 1; // Grant transaction
        #20 transactionGranted = 0; // Simulate data input
        #100 bus_errorIN = 1; // Simulate bus error
        #4 bus_errorIN = 0; // Clear bus error

        // Test read transaction
        #12 ipcore_launch_read = 1;
        ipcore_address = 32'h00f00000;
        ipcore_burst_size = 8'd10;
        ipcore_byte_enable = 4'b1111;
        ipcore_block_sizeIN = 8'd20;
        #4 ipcore_launch_read = 0; // Deassert read signal
        transactionGranted = 1; // Grant transaction
        #20 transactionGranted = 0; // Simulate data input
        #4 data_validIN = 1; // Simulate data valid signal
        #80 data_validIN = 0; // Simulate end of transaction
        #4 end_transactionIN = 1; // Grant transaction



        #800
        $finish;
    end

    // Monitor signals
    initial begin
        $dumpfile("test_dma.vcd");
        $dumpvars(0, tb_DMA);
    end
    
    always @(pp_address) begin
        pp_dataOut <= {24'hFFFFFF, pp_address}; // Simulate data input
    end

    always @(posedge clock) begin
        if (n_reset == 1'b0) begin
            address_dataIN <= 32'hA0000000;
        end else if (data_validIN == 1'b1) begin
            address_dataIN <= address_dataIN + 1;
        end
    end

endmodule

project/modules/jtag_interface/testbenches/test_dma.vcd
$date
	Sat May 24 18:21:40 2025
$end
$version
	Icarus Verilog
$end
$timescale
	1ps
$end
$scope module tb_DMA $end
$var wire 1 ! busyOUT $end
$var wire 4 " s_dma_cur_state [3:0] $end
$var wire 1 # requestTransaction $end
$var wire 1 $ read_n_writeOUT $end
$var wire 1 % pp_writeEnable $end
$var wire 32 & pp_dataIn [31:0] $end
$var wire 9 ' pp_address [8:0] $end
$var wire 1 ( ipcore_dma_busy $end
$var wire 8 ) ipcore_block_sizeOUT [7:0] $end
$var wire 1 * end_transactionOUT $end
$var wire 1 + data_validOUT $end
$var wire 4 , byte_enableOUT [3:0] $end
$var wire 8 - busrt_sizeOUT [7:0] $end
$var wire 1 . begin_transactionOUT $end
$var wire 32 / address_dataOUT [31:0] $end
$var reg 32 0 address_dataIN [31:0] $end
$var reg 1 1 bus_errorIN $end
$var reg 1 2 busyIN $end
$var reg 1 3 clock $end
$var reg 1 4 data_validIN $end
$var reg 1 5 end_transactionIN $end
$var reg 32 6 ipcore_address [31:0] $end
$var reg 8 7 ipcore_block_sizeIN [7:0] $end
$var reg 8 8 ipcore_burst_size [7:0] $end
$var reg 4 9 ipcore_byte_enable [3:0] $end
$var reg 1 : ipcore_launch_read $end
$var reg 1 ; ipcore_launch_write $end
$var reg 1 < n_reset $end
$var reg 32 = pp_dataOut [31:0] $end
$var reg 1 > transactionGranted $end
$scope module dut $end
$var wire 32 ? address_dataIN [31:0] $end
$var wire 1 . begin_transactionOUT $end
$var wire 1 1 bus_errorIN $end
$var wire 8 @ busrt_sizeOUT [7:0] $end
$var wire 1 2 busyIN $end
$var wire 1 ! busyOUT $end
$var wire 4 A byte_enableOUT [3:0] $end
$var wire 1 3 clock $end
$var wire 1 4 data_validIN $end
$var wire 1 + data_validOUT $end
$var wire 1 5 end_transactionIN $end
$var wire 1 * end_transactionOUT $end
$var wire 32 B ipcore_address [31:0] $end
$var wire 8 C ipcore_block_sizeIN [7:0] $end
$var wire 8 D ipcore_burst_size [7:0] $end
$var wire 4 E ipcore_byte_enable [3:0] $end
$var wire 1 : ipcore_launch_read $end
$var wire 1 F ipcore_launch_simple_switch $end
$var wire 1 ; ipcore_launch_write $end
$var wire 1 G ipcore_operation_ended $end
$var wire 1 < n_reset $end
$var wire 9 H pp_address [8:0] $end
$var wire 32 I pp_dataIn [31:0] $end
$var wire 32 J pp_dataOut [31:0] $end
$var wire 1 $ read_n_writeOUT $end
$var wire 1 > transactionGranted $end
$var wire 1 K s_dma_done $end
$var wire 8 L s_dma_cur_state [7:0] $end
$var wire 8 M s_actual_burst_size [7:0] $end
$var wire 1 # requestTransaction $end
$var wire 1 % pp_writeEnable $end
$var wire 1 ( ipcore_dma_busy $end
$var wire 8 N ipcore_block_sizeOUT [7:0] $end
$var wire 1 O busWrite $end
$var wire 32 P address_dataOUT [31:0] $end
$var parameter 32 Q Base $end
$var parameter 5 R fsm_end_transaction_error $end
$var parameter 5 S fsm_end_write_transaction $end
$var parameter 5 T fsm_idle $end
$var parameter 5 U fsm_init $end
$var parameter 5 V fsm_read $end
$var parameter 5 W fsm_request_bus $end
$var parameter 5 X fsm_set_up_transaction $end
$var parameter 5 Y fsm_wait_end $end
$var parameter 5 Z fsm_write $end
$var reg 32 [ address_dataIN_reg [31:0] $end
$var reg 32 \ address_dataOUT_reg [31:0] $end
$var reg 1 ] begin_transactionOUT_reg $end
$var reg 8 ^ burst_sizeOUT_reg [7:0] $end
$var reg 32 _ bus_block_size_reg [31:0] $end
$var reg 8 ` bus_burst_size_reg [7:0] $end
$var reg 4 a bus_byte_enable_reg [3:0] $end
$var reg 32 b bus_start_address_reg [31:0] $end
$var reg 4 c byte_enableOUT_reg [3:0] $end
$var reg 5 d cur_state [4:0] $end
$var reg 1 e data_validIN_reg $end
$var reg 1 f data_validOUT_reg $end
$var reg 1 g end_transactionIN_reg $end
$var reg 1 h end_transactionOUT_reg $end
$var reg 5 i nxt_state [4:0] $end
$var reg 1 j operation_ended_reg $end
$var reg 1 k operation_launch_reg $end
$var reg 9 l pp_address_reg [8:0] $end
$var reg 1 m read_n_writeOUT_reg $end
$var reg 1 n read_n_write_reg $end
$var reg 9 o updated_block_size_reg [8:0] $end
$var reg 32 p updated_bus_start_address_reg [31:0] $end
$var reg 9 q words_written_reg [8:0] $end
$upscope $end
$upscope $end
$enddefinitions $end
$comment Show the parameter values. $end
$dumpall
b110 Z
b101 Y
b11 X
b10 W
b100 V
b1 U
b0 T
b1000 S
b111 R
b1000000000000000000000000000000 Q
$end
#0
$dumpvars
bx q
bx p
bx o
xn
xm
bx l
xk
xj
b0 i
xh
xg
xf
xe
bx d
bx c
bx b
bx a
bx `
bx _
bx ^
x]
bx \
bx [
bx P
xO
bx N
bx M
bx L
xK
b0 J
bx I
bx H
xG
zF
b0 E
b0 D
b0 C
b0 B
bx A
bx @
b0 ?
0>
b0 =
0<
0;
0:
b0 9
b0 8
b0 7
b0 6
05
04
03
02
01
b0 0
bx /
x.
bx -
bx ,
x+
x*
bx )
x(
bx '
bx &
x%
x$
x#
bx "
0!
$end
#2000
b11111111111111111111111000000000 =
b11111111111111111111111000000000 J
0%
b0 "
b0 )
b0 N
0(
0O
0#
1K
b0 L
bx00 /
bx00 P
b0 _
b0 a
b1 M
b0 `
b0 b
0e
0g
b0 &
b0 I
b0 [
b0 d
0G
0j
0k
b0 '
b0 H
b0 l
b0 o
b0 p
bx00 \
b0 q
b10100000000000000000000000000000 0
b10100000000000000000000000000000 ?
13
#4000
03
#6000
b0 /
b0 P
0+
0f
0*
0h
b0 \
b0 -
b0 @
b0 ^
b0 ,
b0 A
b0 c
0$
0m
0.
0]
0n
b10100000000000000000000000000000 &
b10100000000000000000000000000000 I
b10100000000000000000000000000000 [
13
#8000
03
#10000
13
#12000
03
#14000
13
#16000
03
#18000
13
#20000
03
1<
#22000
13
#24000
03
#26000
13
#28000
03
#30000
13
#32000
b1 i
03
b10011 7
b10011 C
b1111 9
b1111 E
b1010 8
b1010 D
b10101010101110111100110011011101 6
b10101010101110111100110011011101 B
1;
#34000
b10 i
b10011 )
b10011 N
1(
b10011 _
b1111 a
b1011 M
b1010 `
b10101010101110111100110011011101 b
b1 d
13
#36000
03
1>
0;
#38000
b11 i
b111 "
0K
b110111 L
1#
xk
b10011 o
b10101010101110111100110011011101 p
b10 d
13
#40000
03
#42000
b110 i
0#
b11 d
13
#44000
03
#46000
b10101010101110111100110011011100 /
b10101010101110111100110011011100 P
1O
b1011 q
b10101010101110111100110011011100 \
b1010 -
b1010 @
b1010 ^
b1111 ,
b1111 A
b1111 c
1.
1]
b110 d
13
#48000
03
#50000
b11111111111111111111111000000001 =
b11111111111111111111111000000001 J
b1000 "
b111000 L
b11111111111111111111111000000001 /
b11111111111111111111111000000001 P
b1 '
b1 H
b1 l
b10010 o
b10101010101110111100110011100001 p
1+
1f
b11111111111111111111111000000000 \
b0 -
b0 @
b0 ^
b0 ,
b0 A
b0 c
0.
0]
b1010 q
13
#52000
03
#54000
b11111111111111111111111000000010 /
b11111111111111111111111000000010 P
b11111111111111111111111000000010 =
b11111111111111111111111000000010 J
b1001 "
b111001 L
b1001 q
b11111111111111111111111000000001 \
b10 '
b10 H
b10 l
b10001 o
b10101010101110111100110011100101 p
13
#56000
03
0>
#58000
b11111111111111111111111000000011 /
b11111111111111111111111000000011 P
b11111111111111111111111000000011 =
b11111111111111111111111000000011 J
b1010 "
b111010 L
b11 '
b11 H
b11 l
b10000 o
b10101010101110111100110011101001 p
b11111111111111111111111000000010 \
b1000 q
13
#60000
0O
03
12
#62000
b0 \
13
#64000
03
#66000
13
#68000
03
#70000
13
#72000
03
#74000
13
#76000
03
#78000
13
#80000
03
#82000
13
#84000
03
#86000
13
#88000
03
#90000
13
#92000
03
#94000
13
#96000
03
#98000
13
#100000
1O
03
02
#102000
b11111111111111111111111000000100 /
b11111111111111111111111000000100 P
b11111111111111111111111000000100 =
b11111111111111111111111000000100 J
b1011 "
b111011 L
b111 q
b11111111111111111111111000000011 \
b100 '
b100 H
b100 l
b1111 o
b10101010101110111100110011101101 p
13
#104000
03
1>
#106000
b11111111111111111111111000000101 /
b11111111111111111111111000000101 P
b11111111111111111111111000000101 =
b11111111111111111111111000000101 J
b1100 "
b111100 L
b101 '
b101 H
b101 l
b1110 o
b10101010101110111100110011110001 p
b11111111111111111111111000000100 \
b110 q
13
#108000
03
#110000
b11111111111111111111111000000110 /
b11111111111111111111111000000110 P
b11111111111111111111111000000110 =
b11111111111111111111111000000110 J
b1101 "
b111101 L
b101 q
b11111111111111111111111000000101 \
b110 '
b110 H
b110 l
b1101 o
b10101010101110111100110011110101 p
13
#112000
03
#114000
b11111111111111111111111000000111 /
b11111111111111111111111000000111 P
b11111111111111111111111000000111 =
b11111111111111111111111000000111 J
b1110 "
b111110 L
b111 '
b111 H
b111 l
b1100 o
b10101010101110111100110011111001 p
b11111111111111111111111000000110 \
b100 q
13
#116000
03
#118000
b11111111111111111111111000001000 /
b11111111111111111111111000001000 P
b11111111111111111111111000001000 =
b11111111111111111111111000001000 J
b1111 "
b111111 L
b11 q
b11111111111111111111111000000111 \
b1000 '
b1000 H
b1000 l
b1011 o
b10101010101110111100110011111101 p
13
#120000
03
#122000
b11111111111111111111111000001001 /
b11111111111111111111111000001001 P
b11111111111111111111111000001001 =
b11111111111111111111111000001001 J
b0 "
b1000000 L
b1001 '
b1001 H
b1001 l
b1010 o
b10101010101110111100110100000001 p
b11111111111111111111111000001000 \
b10 q
13
#124000
03
#126000
b11111111111111111111111000001010 /
b11111111111111111111111000001010 P
b1000 i
b11111111111111111111111000001010 =
b11111111111111111111111000001010 J
b1 "
b1000001 L
b1 q
b11111111111111111111111000001001 \
b1010 '
b1010 H
b1010 l
b1001 o
b10101010101110111100110100000101 p
13
#128000
03
#130000
b11111111111111111111111000001011 /
b11111111111111111111111000001011 P
b11111111111111111111111000001011 =
b11111111111111111111111000001011 J
b10 i
b10 "
0O
b1000010 L
b1000 d
b1011 '
b1011 H
b1011 l
b1000 o
b10101010101110111100110100001001 p
b11111111111111111111111000001010 \
b0 q
13
#132000
03
#134000
b11 i
b0 /
b0 P
1#
0+
0f
1*
1h
b0 \
b10 d
13
#136000
03
#138000
b110 i
0#
b11 d
0*
0h
13
#140000
03
#142000
b10101010101110111100110100001000 /
b10101010101110111100110100001000 P
1O
b1000 q
b10101010101110111100110100001000 \
b1010 -
b1010 @
b1010 ^
b1111 ,
b1111 A
b1111 c
1.
1]
b110 d
13
#144000
03
#146000
b11111111111111111111111000001100 =
b11111111111111111111111000001100 J
b11 "
b1000011 L
b11111111111111111111111000001100 /
b11111111111111111111111000001100 P
b1100 '
b1100 H
b1100 l
b111 o
b10101010101110111100110100001101 p
1+
1f
b11111111111111111111111000001011 \
b0 -
b0 @
b0 ^
b0 ,
b0 A
b0 c
0.
0]
b111 q
13
#148000
03
#150000
b11111111111111111111111000001101 /
b11111111111111111111111000001101 P
b11111111111111111111111000001101 =
b11111111111111111111111000001101 J
b100 "
b1000100 L
b110 q
b11111111111111111111111000001100 \
b1101 '
b1101 H
b1101 l
b110 o
b10101010101110111100110100010001 p
13
#152000
03
#154000
b11111111111111111111111000001110 /
b11111111111111111111111000001110 P
b11111111111111111111111000001110 =
b11111111111111111111111000001110 J
b101 "
b1000101 L
b1110 '
b1110 H
b1110 l
b101 o
b10101010101110111100110100010101 p
b11111111111111111111111000001101 \
b101 q
13
#156000
03
#158000
b11111111111111111111111000001111 /
b11111111111111111111111000001111 P
b11111111111111111111111000001111 =
b11111111111111111111111000001111 J
b110 "
b1000110 L
b100 q
b11111111111111111111111000001110 \
b1111 '
b1111 H
b1111 l
b100 o
b10101010101110111100110100011001 p
13
#160000
03
#162000
b11111111111111111111111000010000 /
b11111111111111111111111000010000 P
b11111111111111111111111000010000 =
b11111111111111111111111000010000 J
b111 "
b1000111 L
b10000 '
b10000 H
b10000 l
b11 o
b10101010101110111100110100011101 p
b11111111111111111111111000001111 \
b11 q
13
#164000
03
#166000
b11111111111111111111111000010001 /
b11111111111111111111111000010001 P
b11111111111111111111111000010001 =
b11111111111111111111111000010001 J
b1000 "
b1001000 L
b10 q
b11111111111111111111111000010000 \
b10001 '
b10001 H
b10001 l
b10 o
b10101010101110111100110100100001 p
13
#168000
03
#170000
b11111111111111111111111000010010 /
b11111111111111111111111000010010 P
b11111111111111111111111000010010 =
b11111111111111111111111000010010 J
b1000 i
b1001 "
b1001001 L
b10010 '
b10010 H
b10010 l
b1 o
b10101010101110111100110100100101 p
b11111111111111111111111000010001 \
b1 q
13
#172000
03
#174000
b11111111111111111111111000010011 /
b11111111111111111111111000010011 P
b11111111111111111111111000010011 =
b11111111111111111111111000010011 J
b0 i
b1010 "
1K
b1001010 L
0O
b0 q
b11111111111111111111111000010010 \
b10011 '
b10011 H
b10011 l
b0 o
b10101010101110111100110100101001 p
b1000 d
13
#176000
03
#178000
b0 /
b0 P
0(
b0 d
0+
0f
1*
1h
b0 \
13
#180000
03
#182000
0*
0h
xG
xj
13
#184000
03
0<
#186000
b11111111111111111111111000000000 =
b11111111111111111111111000000000 J
b0 "
b0 )
b0 N
b0 L
b0 _
b0 a
b1 M
b0 `
b0 b
0G
0j
0k
b0 '
b0 H
b0 l
b0 p
13
#188000
03
1<
#190000
b0x00xx )
b0x00xx N
b0x00xx _
13
#192000
03
#194000
13
#196000
03
#198000
13
#200000
b1 i
03
b11001000 7
b11001000 C
b1100100 8
b1100100 D
1;
#202000
b10 i
b11001000 )
b11001000 N
1(
b11001000 _
b1111 a
b1100101 M
b1100100 `
b10101010101110111100110011011101 b
b1 d
13
#204000
03
0;
#206000
b11 i
b111 "
0K
b110111 L
1#
xk
b11001000 o
b10101010101110111100110011011101 p
b10 d
13
#208000
03
#210000
b110 i
0#
b11 d
13
#212000
03
#214000
b10101010101110111100110011011100 /
b10101010101110111100110011011100 P
1O
b1100101 q
b10101010101110111100110011011100 \
b1100100 -
b1100100 @
b1100100 ^
b1111 ,
b1111 A
b1111 c
1.
1]
b110 d
13
#216000
03
#218000
b11111111111111111111111000000001 =
b11111111111111111111111000000001 J
b1000 "
b111000 L
b11111111111111111111111000000001 /
b11111111111111111111111000000001 P
b1 '
b1 H
b1 l
b11000111 o
b10101010101110111100110011100001 p
1+
1f
b11111111111111111111111000000000 \
b0 -
b0 @
b0 ^
b0 ,
b0 A
b0 c
0.
0]
b1100100 q
13
#220000
03
#222000
b11111111111111111111111000000010 /
b11111111111111111111111000000010 P
b11111111111111111111111000000010 =
b11111111111111111111111000000010 J
b1001 "
b111001 L
b1100011 q
b11111111111111111111111000000001 \
b10 '
b10 H
b10 l
b11000110 o
b10101010101110111100110011100101 p
13
#224000
03
0>
#226000
b11111111111111111111111000000011 /
b11111111111111111111111000000011 P
b11111111111111111111111000000011 =
b11111111111111111111111000000011 J
b1010 "
b111010 L
b11 '
b11 H
b11 l
b11000101 o
b10101010101110111100110011101001 p
b11111111111111111111111000000010 \
b1100010 q
13
#228000
03
#230000
b11111111111111111111111000000100 /
b11111111111111111111111000000100 P
b11111111111111111111111000000100 =
b11111111111111111111111000000100 J
b1011 "
b111011 L
b1100001 q
b11111111111111111111111000000011 \
b100 '
b100 H
b100 l
b11000100 o
b10101010101110111100110011101101 p
13
#232000
03
#234000
b11111111111111111111111000000101 /
b11111111111111111111111000000101 P
b11111111111111111111111000000101 =
b11111111111111111111111000000101 J
b1100 "
b111100 L
b101 '
b101 H
b101 l
b11000011 o
b10101010101110111100110011110001 p
b11111111111111111111111000000100 \
b1100000 q
13
#236000
03
