project/modules/jtag_interface/DMA.v
module DMA #(
    parameter [31:0] Base = 32'h40000000)
    ( 
    input wire                    clock, n_reset,
    input wire                    ipcore_launch_write,
    input wire                    ipcore_launch_read,
    input wire [3:0]              ipcore_byte_enable,
    input wire [31:0]             ipcore_address,
    input wire [7:0]              ipcore_burst_size,
    output wire                   ipcore_dma_busy,
    output wire [7:0]             ipcore_block_sizeOUT,
    input wire [7:0]              ipcore_block_sizeIN,


    // Buffer interface
    output wire [8:0]             pp_address,
    output wire [31:0]            pp_dataIn,
    output wire                   pp_writeEnable,
    input wire [31:0]             pp_dataOut,

    // here the bus interface is defined
    input wire [31:0] address_dataIN,
    input wire end_transactionIN, 
    input wire data_validIN, 
    input wire busyIN,
    input wire bus_errorIN,

    output wire [31:0] address_dataOUT,
    output wire [3:0] byte_enableOUT,
    output wire [7:0] busrt_sizeOUT,
    output wire read_n_writeOUT,
    output wire begin_transactionOUT,
    output wire end_transactionOUT,
    output wire data_validOUT,
    output wire busyOUT,



    // here the interface with the arbitrer
    output wire        requestTransaction,
    input wire         transactionGranted,


    output wire [3:0]  s_dma_cur_state

    );

    // Reg for sdram control

    reg [31:0] bus_start_address_reg;
    reg [7:0] bus_burst_size_reg;
    reg [3:0] bus_byte_enable_reg;
    reg [31:0] bus_block_size_reg;

    always @(posedge clock) begin
        bus_start_address_reg <= (n_reset == 1'b0) ? 32'h0 : 
                                (ipcore_launch_write == 1'b1 || ipcore_launch_read == 1'b1) ? ipcore_address : bus_start_address_reg;
        bus_burst_size_reg <= (n_reset == 1'b0) ? 8'h0 :
                                (ipcore_launch_write == 1'b1 || ipcore_launch_read == 1'b1) ? ipcore_burst_size : bus_burst_size_reg;
        bus_byte_enable_reg <= (n_reset == 1'b0) ? 4'h0 :
                                (ipcore_launch_write == 1'b1 || ipcore_launch_read == 1'b1) ? ipcore_byte_enable : bus_byte_enable_reg;
        bus_block_size_reg <= (n_reset == 1'b0) ? 32'h0 :
                                (ipcore_launch_write == 1'b1 || ipcore_launch_read == 1'b1) ? ipcore_block_sizeIN : bus_block_size_reg;
    end

    // regs for all bus-in signals
    reg [31:0] address_dataIN_reg;
    reg end_transactionIN_reg;
    reg data_validIN_reg;

    always @(posedge clock) begin
        address_dataIN_reg <= address_dataIN;
        end_transactionIN_reg <= end_transactionIN;
        data_validIN_reg <= data_validIN;
    end



    // DMA state machine
    localparam [4:0] fsm_idle = 4'd0;
    localparam [4:0] fsm_init = 4'd1;
    localparam [4:0] fsm_request_bus = 4'd2;
    localparam [4:0] fsm_set_up_transaction = 4'd3;
    localparam [4:0] fsm_read = 4'd4;
    localparam [4:0] fsm_wait_end = 4'd5;
    localparam [4:0] fsm_write = 4'd6;
    localparam [4:0] fsm_end_transaction_error = 4'd7;
    localparam [4:0] fsm_end_write_transaction = 4'd8;

    reg [4:0] cur_state, nxt_state;
    reg read_n_write_reg;
    // One more bit to indicate when it reaches 0
    reg [8:0] words_written_reg;

    assign ipcore_dma_busy = (cur_state == fsm_idle) ? 1'b0 : 1'b1;
    wire s_dma_done;

    always @* begin
        case (cur_state)
            fsm_idle                  : nxt_state <= (ipcore_launch_write == 1'b1 || ipcore_launch_read == 1'b1) ? fsm_init : fsm_idle;
            fsm_init                  : nxt_state <= fsm_request_bus;
            fsm_request_bus           : nxt_state <= (transactionGranted == 1'b1) ? fsm_set_up_transaction : fsm_request_bus;
            fsm_set_up_transaction    : nxt_state <= (read_n_write_reg == 1'b1) ? fsm_read : fsm_write;
            fsm_read                  : nxt_state <= (bus_errorIN == 1'b1) ? fsm_wait_end :
                                                // End of the transacsion
                                                (end_transactionIN_reg == 1'b1 && s_dma_done == 1'b1) ? fsm_idle :
                                                // End of the burst
                                                (end_transactionIN_reg == 1'b1) ? fsm_request_bus : fsm_read;
                                                    //Wait for the end of the transaction
            fsm_wait_end              : nxt_state <= (end_transactionIN_reg == 1'b1) ? fsm_idle : fsm_wait_end;
            fsm_write                 : nxt_state <= (bus_errorIN == 1'b1) ? fsm_end_transaction_error :
                                                    // End of the burst
                                                    (words_written_reg == 8'b1 && busyIN == 1'b0) ? fsm_end_write_transaction : fsm_write;
                                                    // Either end of the transaction or end of the burst
            fsm_end_write_transaction : nxt_state <= (s_dma_done == 1'b1) ? fsm_idle : fsm_request_bus;
            default                   : nxt_state <= fsm_idle;
        endcase
    end

    always @(posedge clock) begin
        // Update the state machine
        cur_state <= (n_reset == 1'b0) ? fsm_idle : nxt_state;
        // Update if it is a read or a write
        read_n_write_reg <= (cur_state == fsm_idle) ? ipcore_launch_read : read_n_write_reg;
    end

    // All the register that are to be updated during the burst
    reg [31:0] updated_bus_start_address_reg;
    reg [8:0] updated_block_size_reg;
    reg [8:0] pp_address_reg;

    // Is the teransaction done?
    assign s_dma_done = (updated_block_size_reg == 9'b0) ? 1'b1 : 
                              // end of transaction at the same time of last valid data
                              (updated_block_size_reg == 9'b1 && end_transactionIN_reg == 1'b1) ? 1'b1 : 1'b0;
    // Write in buffer iff the data read is valid
    assign pp_writeEnable = (cur_state == fsm_read && data_validIN_reg == 1'b1) ? 1'b1 : 1'b0;
    // Say if we actually wrote data on the bus or it was busy or the burst was over
    wire busWrite = (cur_state == fsm_write && busyIN == 1'b0 && words_written_reg[8] == 1'b0) ? 1'b1 : 1'b0;

    always @(posedge clock) begin
        // Update all the regs : bus start address + 4, block size - 1 and pp address + 1
        updated_bus_start_address_reg <= (n_reset == 1'b0) ? 32'h0 : 
                                        (cur_state == fsm_init) ? bus_start_address_reg : 
                                        (busWrite == 1'b1 || pp_writeEnable == 1'b1) ? updated_bus_start_address_reg + 32'h4 : updated_bus_start_address_reg;
        updated_block_size_reg <= (n_reset == 1'b0) ? 9'h0 :
                                    (cur_state == fsm_init) ? bus_block_size_reg : 
                                    (busWrite == 1'b1 || pp_writeEnable == 1'b1) ? updated_block_size_reg - 9'h1 : updated_block_size_reg;
        pp_address_reg <= (n_reset == 1'b0 || cur_state == fsm_init) ? 9'h0 :
                          (busWrite == 1'b1 || pp_writeEnable == 1'b1) ? pp_address_reg + 8'h1 : pp_address_reg;
    end


    // Bus output signals
    reg data_validOUT_reg;
    reg [3:0] byte_enableOUT_reg;
    reg [7:0] burst_sizeOUT_reg;
    reg [31:0] address_dataOUT_reg;
    reg read_n_writeOUT_reg, begin_transactionOUT_reg, end_transactionOUT_reg;

    always @(posedge clock) begin
        begin_transactionOUT_reg <= (cur_state == fsm_set_up_transaction) ? 1'b1 : 1'b0;
        read_n_writeOUT_reg <= (cur_state == fsm_set_up_transaction) ? read_n_write_reg : 1'b0;
        byte_enableOUT_reg <= (cur_state == fsm_set_up_transaction) ? bus_byte_enable_reg : 4'h0;
        burst_sizeOUT_reg <= (cur_state == fsm_set_up_transaction) ? bus_burst_size_reg : 8'h0;
        address_dataOUT_reg <= (cur_state == fsm_set_up_transaction) ? {updated_bus_start_address_reg[31:2], 2'b00} :
                                (busWrite == 1'b1) ? pp_dataOut :
                                // stall in case of busy in
                                (cur_state == fsm_read && busyIN == 1'b1) ? address_dataOUT_reg : 32'h0;
        end_transactionOUT_reg <= (cur_state == fsm_end_transaction_error || cur_state == fsm_end_write_transaction) ? 1'b1 : 1'b0;
        data_validOUT_reg <= (cur_state == fsm_write && busyIN == 1'b1) ? data_validOUT_reg: busWrite;
    end

    assign address_dataOUT = address_dataOUT_reg;
    assign byte_enableOUT = byte_enableOUT_reg;
    assign busrt_sizeOUT = burst_sizeOUT_reg;
    assign read_n_writeOUT = read_n_writeOUT_reg;
    assign begin_transactionOUT = begin_transactionOUT_reg;
    assign end_transactionOUT = end_transactionOUT_reg;
    assign data_validOUT = data_validOUT_reg;
    assign busyOUT = 0; // never busy


    // Bus arbitrer signals
    assign requestTransaction = (cur_state == fsm_request_bus) ? 1'b1 : 1'b0;

    // words written update 

    always @(posedge clock) begin
        if (n_reset == 1'b0) begin
            words_written_reg <= 9'h0;
        end else if (cur_state == fsm_set_up_transaction) begin
            if (updated_block_size_reg > bus_burst_size_reg) begin
                words_written_reg <= bus_burst_size_reg;
            end else begin
                words_written_reg <= updated_block_size_reg;
            end
        end else if (busWrite == 1'b1) begin
            words_written_reg <= words_written_reg - 9'h1;
        end
    end

    assign ipcore_block_sizeOUT = bus_block_size_reg;
    assign pp_address = pp_address_reg;
    assign pp_dataIn = address_dataIN_reg;

    assign s_dma_cur_state = {cur_state[3:0]};


    // // Write states
    // localparam fsm_idle = 15;
    // localparam fsm_write_request = 1;
    // localparam fsm_write_sending_handshake = 2;
    // localparam fsm_sending_data = 3;
    // localparam fsm_end_transaction = 4;
    // localparam fsm_reading_from_buffer = 5;
    // localparam fsm_asking_for_buffer = 6;
    // localparam fsm_read_request = 7;
    // localparam fsm_read_sending_handshake = 8;
    // localparam fsm_reading_data = 9;
    // localparam fsm_writting_buffer = 10;
    // localparam fsm_test = 14;

    // reg [3:0] cur_state, nxt_state;
    // reg [31:0] buffer_data;
    // wire s_reading_from_buffer_done;
    // reg [31:0] s_address;
    // reg [3:0] s_byte_enable;

    // assign s_dma_cur_state = {cur_state[2:0], ipcore_dataReady};


    // // always @(posedge clock or negedge reset) begin
    // //     if (~reset) begin
    // //         cur_state <= fsm_idle;
    // //     end else begin
    // //         cur_state <= nxt_state;
    // //     end
    // // end


    // always @(*) begin
    //     if (errorIN) begin
    //         nxt_state = fsm_idle;
    //     end else begin
    //         case(cur_state)
    //             fsm_idle:                       nxt_state <= (ipcore_dataReady == 1'b1) ? fsm_asking_for_buffer : 
    //                                                         (ipcore_readReady == 1'b1) ? fsm_read_request : fsm_idle;
    //             fsm_asking_for_buffer:          nxt_state <= fsm_reading_from_buffer;
    //             fsm_reading_from_buffer:        nxt_state <= (s_reading_from_buffer_done == 1'b1) ? fsm_write_request : fsm_reading_from_buffer;
    //             fsm_write_request:              nxt_state <= (granted == 1'b1) ? fsm_write_sending_handshake : fsm_write_request;
    //             fsm_write_sending_handshake:    nxt_state <= fsm_sending_data;
    //             fsm_sending_data:               nxt_state <= (busyIN == 1'b1)? fsm_sending_data : fsm_end_transaction; 
    //             fsm_end_transaction:            nxt_state <= fsm_idle;

    //             fsm_read_request:               nxt_state = (granted == 1'b1) ? fsm_read_sending_handshake : fsm_read_request;
    //             fsm_read_sending_handshake:     nxt_state = fsm_reading_data;
    //             fsm_reading_data:               nxt_state = (end_transactionIN == 1'b1) ? fsm_writting_buffer : fsm_reading_data;
    //             fsm_writting_buffer:            nxt_state = fsm_end_transaction;
    //             default:                        nxt_state = fsm_test;
    //         endcase
    //     end
    // end

    // always @(posedge clock) begin 
    //     if (~reset) begin
    //         buffer_data <= 32'h0;
    //         s_address <= 32'h0;
    //         s_byte_enable <= 4'h0;
    //         cur_state <= fsm_idle;
    //     end
    //     else begin 
    //         cur_state <= nxt_state;
    //         if (cur_state == fsm_reading_from_buffer) begin
    //             buffer_data <= dataOut;
    //         end else if (cur_state == fsm_reading_data && data_validIN == 1'b1) begin
    //             buffer_data <= address_dataIN;
    //         end else if (cur_state == fsm_end_transaction || errorIN == 1'b1) begin
    //             buffer_data <= 32'h0;
    //         end
    //         if (cur_state == fsm_idle && (ipcore_readReady || ipcore_dataReady)) begin
    //             s_byte_enable <= ipcore_byteEnable;
    //             s_address <= ipcore_address_to_read;
    //         end else if (cur_state == fsm_end_transaction) begin
    //             s_address <= 32'h0;
    //             s_byte_enable <= 4'h0;
    //         end
    //     end
    // end

    // // assign buffer_data = (cur_state == fsm_reading_from_buffer) ? dataOut : 
    // //                      (cur_state == fsm_reading_data && data_validIN == 1'b1) ? address_dataIN :
    // //                      (cur_state == fsm_end_transaction || errorIN == 1'b1 || reset == 1'b0) ? 32'h0 : buffer_data;


    // // Buffer interface set to read at the same location
    // assign bufferAddress = 32'h0;
    // assign dataIn = (cur_state == fsm_writting_buffer) ? buffer_data : 32'h0;
    // assign writeEnable = (cur_state == fsm_writting_buffer) ? 1'b1 : 1'b0;
    // assign s_reading_from_buffer_done = 1'b1;
    // // assign s_address = (cur_state == fsm_idle && (ipcore_readReady || ipcore_dataReady)) ? ipcore_address_to_read : 
    // //                            (reset == 1'b0 || cur_state == fsm_end_transaction) ? 32'h0 : s_address;
    // // assign s_byte_enable = (cur_state == fsm_idle && (ipcore_readReady || ipcore_dataReady)) ? ipcore_byteEnable : 
    // //                            (reset == 1'b0 || cur_state == fsm_end_transaction) ? 4'h0 : s_byte_enable;

    // assign address_dataOUT = (cur_state == fsm_write_sending_handshake ) ? s_address: 
    //                          (cur_state == fsm_read_sending_handshake) ? s_address:
    //                          (cur_state == fsm_sending_data) ? buffer_data : 32'h0; //for now only 1 byte
    // assign byte_enableOUT = (cur_state == fsm_write_sending_handshake || cur_state == fsm_read_sending_handshake) ? s_byte_enable : 4'h0; 
    // assign busrt_sizeOUT = (cur_state == fsm_write_sending_handshake) ? 8'h0 : 8'h0; //for now only 1 word
    // assign read_n_writeOUT = (cur_state == fsm_read_sending_handshake) ? 1'b1 : 1'b0; 
    // assign begin_transactionOUT = ((cur_state == fsm_write_sending_handshake) || (cur_state == fsm_read_sending_handshake)) ? 1'b1 : 1'b0;

    // assign end_transactionOUT = ((cur_state == fsm_sending_data && busyIN == 1'b0) || errorIN == 1'b1) ? 1'b1 : 1'b0;

    // assign data_validOUT = (cur_state == fsm_sending_data) ? 1'b1 : 1'b0;

    // assign busyOUT = (cur_state == fsm_sending_data) ? 1'b0 : 1'b0; //for now always 0

    // assign request = (cur_state == fsm_write_request || cur_state == fsm_read_request) ? 1'b1 : 1'b0;

    // assign ipcore_switch_ready = (cur_state == fsm_idle |
    //                                 // cur_state == fsm_write_request |
    //                                 // cur_state == fsm_write_sending_handshake |
    //                                 // cur_state == fsm_sending_data |
    //                                 cur_state == fsm_end_transaction) ? 1'b1 : 1'b0;
endmodule

project/modules/jtag_interface/testbenches/tb_DMA.v
`timescale 1ns/1ps

module tb_DMA;

    // DUT signals
    reg clock;
    reg n_reset;
    reg ipcore_launch_write;
    reg ipcore_launch_read;
    reg [3:0] ipcore_byte_enable;
    reg [31:0] ipcore_address;
    reg [7:0] ipcore_burst_size;
    wire ipcore_dma_busy;
    wire [7:0] ipcore_block_sizeOUT;
    reg [7:0] ipcore_block_sizeIN;

    wire [8:0] pp_address;
    wire [31:0] pp_dataIn;
    wire pp_writeEnable;
    reg [31:0] pp_dataOut;

    reg [31:0] address_dataIN;
    reg end_transactionIN;
    reg data_validIN;
    reg busyIN;
    reg bus_errorIN;

    wire [31:0] address_dataOUT;
    wire [3:0] byte_enableOUT;
    wire [7:0] busrt_sizeOUT;
    wire read_n_writeOUT;
    wire begin_transactionOUT;
    wire end_transactionOUT;
    wire data_validOUT;
    wire busyOUT;

    wire requestTransaction;
    reg transactionGranted;

    wire [3:0] s_dma_cur_state;

    // Instantiate the DUT
    DMA dut (
        .clock(clock),
        .n_reset(n_reset),
        .ipcore_launch_write(ipcore_launch_write),
        .ipcore_launch_read(ipcore_launch_read),
        .ipcore_byte_enable(ipcore_byte_enable),
        .ipcore_address(ipcore_address),
        .ipcore_burst_size(ipcore_burst_size),
        .ipcore_dma_busy(ipcore_dma_busy),
        .ipcore_block_sizeIN(ipcore_block_sizeIN),
        .ipcore_block_sizeOUT(ipcore_block_sizeOUT),
        .pp_address(pp_address),
        .pp_dataIn(pp_dataIn),
        .pp_writeEnable(pp_writeEnable),
        .pp_dataOut(pp_dataOut),
        .address_dataIN(address_dataIN),
        .end_transactionIN(end_transactionIN),
        .data_validIN(data_validIN),
        .busyIN(busyIN),
        .bus_errorIN(bus_errorIN),
        .address_dataOUT(address_dataOUT),
        .byte_enableOUT(byte_enableOUT),
        .busrt_sizeOUT(busrt_sizeOUT),
        .read_n_writeOUT(read_n_writeOUT),
        .begin_transactionOUT(begin_transactionOUT),
        .end_transactionOUT(end_transactionOUT),
        .data_validOUT(data_validOUT),
        .busyOUT(busyOUT),
        .requestTransaction(requestTransaction),
        .transactionGranted(transactionGranted),
        .s_dma_cur_state(s_dma_cur_state)
    );

    // Clock generation
    initial begin
        clock = 0;
        forever #2 clock = ~clock; // 100MHz clock
    end
    initial begin
        // Initialize all signals to default values
        n_reset = 0;
        ipcore_launch_write = 0;
        ipcore_launch_read = 0;
        ipcore_byte_enable = 4'b0000;
        ipcore_address = 32'b0;
        ipcore_burst_size = 8'b0;
        ipcore_block_sizeIN = 8'b0;
        pp_dataOut = 32'b0;
        address_dataIN = 32'b0;
        end_transactionIN = 0;
        data_validIN = 0;
        busyIN = 0;
        bus_errorIN = 0;
        transactionGranted = 0;

        // Release reset after 10ns
        #20 n_reset = 1;

        // Test write transaction
        #12 ipcore_launch_write = 1;
        ipcore_address = 32'hAABBCCDD;
        ipcore_burst_size = 8'd10;
        ipcore_byte_enable = 4'b1111;
        ipcore_block_sizeIN = 8'd19;

        #4 ipcore_launch_write = 0; // Deassert write signal
        transactionGranted = 1; // Grant transaction
        #20 transactionGranted = 0; // Simulate data input
        #4 busyIN = 1; // Simulate busy signal
        #40 busyIN = 0; // Simulate end of transaction
        #4 transactionGranted = 1; // Grant transaction

        #80;

        n_reset = 0; // Assert reset
        #4 n_reset = 1; // Deassert reset

        // Test write transaction with error
        #12 ipcore_launch_write = 1;
        ipcore_address = 32'hAABBCCDD;
        ipcore_burst_size = 8'd100;
        ipcore_byte_enable = 4'b1111;
        ipcore_block_sizeIN = 8'd200;
        #4 ipcore_launch_write = 0; // Deassert write signal
        transactionGranted = 1; // Grant transaction
        #20 transactionGranted = 0; // Simulate data input
        #100 bus_errorIN = 1; // Simulate bus error
        #4 bus_errorIN = 0; // Clear bus error

        // Test read transaction
        #12 ipcore_launch_read = 1;
        ipcore_address = 32'h00f00000;
        ipcore_burst_size = 8'd10;
        ipcore_byte_enable = 4'b1111;
        ipcore_block_sizeIN = 8'd20;
        #4 ipcore_launch_read = 0; // Deassert read signal
        transactionGranted = 1; // Grant transaction
        #20 transactionGranted = 0; // Simulate data input
        #4 data_validIN = 1; // Simulate data valid signal
        #80 data_validIN = 0; // Simulate end of transaction
        #4 end_transactionIN = 1; // Grant transaction



        #800
        $finish;
    end

    // Monitor signals
    initial begin
        $dumpfile("test_dma.vcd");
        $dumpvars(0, tb_DMA);
    end
    
    always @(pp_address) begin
        pp_dataOut <= {24'hFFFFFF, pp_address}; // Simulate data input
    end

    always @(posedge clock) begin
        if (n_reset == 1'b0) begin
            address_dataIN <= 32'hA0000000;
        end else if (data_validIN == 1'b1) begin
            address_dataIN <= address_dataIN + 1;
        end
    end

endmodule

project/modules/jtag_interface/testbenches/test_dma.vcd
$date
	Wed May 21 17:59:03 2025
$end
$version
	Icarus Verilog
$end
$timescale
	1ps
$end
$scope module tb_DMA $end
$var wire 1 ! busyOUT $end
$var wire 4 " s_dma_cur_state [3:0] $end
$var wire 1 # requestTransaction $end
$var wire 1 $ read_n_writeOUT $end
$var wire 1 % pp_writeEnable $end
$var wire 32 & pp_dataIn [31:0] $end
$var wire 9 ' pp_address [8:0] $end
$var wire 1 ( ipcore_dma_busy $end
$var wire 8 ) ipcore_block_sizeOUT [7:0] $end
$var wire 1 * end_transactionOUT $end
$var wire 1 + data_validOUT $end
$var wire 4 , byte_enableOUT [3:0] $end
$var wire 8 - busrt_sizeOUT [7:0] $end
$var wire 1 . begin_transactionOUT $end
$var wire 32 / address_dataOUT [31:0] $end
$var reg 32 0 address_dataIN [31:0] $end
$var reg 1 1 bus_errorIN $end
$var reg 1 2 busyIN $end
$var reg 1 3 clock $end
$var reg 1 4 data_validIN $end
$var reg 1 5 end_transactionIN $end
$var reg 32 6 ipcore_address [31:0] $end
$var reg 8 7 ipcore_block_sizeIN [7:0] $end
$var reg 8 8 ipcore_burst_size [7:0] $end
$var reg 4 9 ipcore_byte_enable [3:0] $end
$var reg 1 : ipcore_launch_read $end
$var reg 1 ; ipcore_launch_write $end
$var reg 1 < n_reset $end
$var reg 32 = pp_dataOut [31:0] $end
$var reg 1 > transactionGranted $end
$scope module dut $end
$var wire 32 ? address_dataIN [31:0] $end
$var wire 32 @ address_dataOUT [31:0] $end
$var wire 1 . begin_transactionOUT $end
$var wire 1 1 bus_errorIN $end
$var wire 8 A busrt_sizeOUT [7:0] $end
$var wire 1 2 busyIN $end
$var wire 1 ! busyOUT $end
$var wire 4 B byte_enableOUT [3:0] $end
$var wire 1 3 clock $end
$var wire 1 4 data_validIN $end
$var wire 1 + data_validOUT $end
$var wire 1 5 end_transactionIN $end
$var wire 1 * end_transactionOUT $end
$var wire 32 C ipcore_address [31:0] $end
$var wire 8 D ipcore_block_sizeIN [7:0] $end
$var wire 8 E ipcore_burst_size [7:0] $end
$var wire 4 F ipcore_byte_enable [3:0] $end
$var wire 1 : ipcore_launch_read $end
$var wire 1 ; ipcore_launch_write $end
$var wire 1 < n_reset $end
$var wire 9 G pp_address [8:0] $end
$var wire 32 H pp_dataIn [31:0] $end
$var wire 32 I pp_dataOut [31:0] $end
$var wire 1 $ read_n_writeOUT $end
$var wire 1 > transactionGranted $end
$var wire 1 J s_dma_done $end
$var wire 4 K s_dma_cur_state [3:0] $end
$var wire 1 # requestTransaction $end
$var wire 1 % pp_writeEnable $end
$var wire 1 ( ipcore_dma_busy $end
$var wire 8 L ipcore_block_sizeOUT [7:0] $end
$var wire 1 M busWrite $end
$var parameter 32 N Base $end
$var parameter 5 O fsm_end_transaction_error $end
$var parameter 5 P fsm_end_write_transaction $end
$var parameter 5 Q fsm_idle $end
$var parameter 5 R fsm_init $end
$var parameter 5 S fsm_read $end
$var parameter 5 T fsm_request_bus $end
$var parameter 5 U fsm_set_up_transaction $end
$var parameter 5 V fsm_wait_end $end
$var parameter 5 W fsm_write $end
$var reg 32 X address_dataIN_reg [31:0] $end
$var reg 32 Y address_dataOUT_reg [31:0] $end
$var reg 1 Z begin_transactionOUT_reg $end
$var reg 8 [ burst_sizeOUT_reg [7:0] $end
$var reg 32 \ bus_block_size_reg [31:0] $end
$var reg 8 ] bus_burst_size_reg [7:0] $end
$var reg 4 ^ bus_byte_enable_reg [3:0] $end
$var reg 32 _ bus_start_address_reg [31:0] $end
$var reg 4 ` byte_enableOUT_reg [3:0] $end
$var reg 5 a cur_state [4:0] $end
$var reg 1 b data_validIN_reg $end
$var reg 1 c data_validOUT_reg $end
$var reg 1 d end_transactionIN_reg $end
$var reg 1 e end_transactionOUT_reg $end
$var reg 5 f nxt_state [4:0] $end
$var reg 9 g pp_address_reg [8:0] $end
$var reg 1 h read_n_writeOUT_reg $end
$var reg 1 i read_n_write_reg $end
$var reg 9 j updated_block_size_reg [8:0] $end
$var reg 32 k updated_bus_start_address_reg [31:0] $end
$var reg 9 l words_written_reg [8:0] $end
$upscope $end
$upscope $end
$enddefinitions $end
$comment Show the parameter values. $end
$dumpall
b110 W
b101 V
b11 U
b10 T
b100 S
b1 R
b0 Q
b1000 P
b111 O
b1000000000000000000000000000000 N
$end
#0
$dumpvars
bx l
bx k
bx j
xi
xh
bx g
b0 f
xe
xd
xc
xb
bx a
bx `
bx _
bx ^
bx ]
bx \
bx [
xZ
bx Y
bx X
xM
bx L
bx K
xJ
b0 I
bx H
bx G
b0 F
b0 E
b0 D
b0 C
bx B
bx A
bx @
b0 ?
0>
b0 =
0<
0;
0:
b0 9
b0 8
b0 7
b0 6
05
04
03
02
01
b0 0
bx /
x.
bx -
bx ,
x+
x*
bx )
x(
bx '
bx &
x%
x$
x#
bx "
0!
$end
#2000
b11111111111111111111111000000000 =
b11111111111111111111111000000000 I
0M
0%
b0 )
b0 L
0(
0#
b0 "
b0 K
1J
b0 \
b0 ^
b0 ]
b0 _
0b
0d
b0 &
b0 H
b0 X
b0 a
b0 '
b0 G
b0 g
b0 j
b0 k
bx00 /
bx00 @
bx00 Y
b0 l
b10100000000000000000000000000000 0
b10100000000000000000000000000000 ?
13
#4000
03
#6000
0+
0c
0*
0e
b0 /
b0 @
b0 Y
b0 -
b0 A
b0 [
b0 ,
b0 B
b0 `
0$
0h
0.
0Z
0i
b10100000000000000000000000000000 &
b10100000000000000000000000000000 H
b10100000000000000000000000000000 X
13
#8000
03
#10000
13
#12000
03
#14000
13
#16000
03
#18000
13
#20000
03
1<
#22000
13
#24000
03
#26000
13
#28000
03
#30000
13
#32000
b1 f
03
b10011 7
b10011 D
b1111 9
b1111 F
b1010 8
b1010 E
b10101010101110111100110011011101 6
b10101010101110111100110011011101 C
1;
#34000
b10 f
b10011 )
b10011 L
1(
b1 "
b1 K
b10011 \
b1111 ^
b1010 ]
b10101010101110111100110011011101 _
b1 a
13
#36000
03
1>
0;
#38000
b11 f
0J
1#
b10 "
b10 K
b10011 j
b10101010101110111100110011011101 k
b10 a
13
#40000
03
#42000
b110 f
0#
b11 "
b11 K
b11 a
13
#44000
03
#46000
1M
b110 "
b110 K
b1010 l
b10101010101110111100110011011100 /
b10101010101110111100110011011100 @
b10101010101110111100110011011100 Y
b1010 -
b1010 A
b1010 [
b1111 ,
b1111 B
b1111 `
1.
1Z
b110 a
13
#48000
03
#50000
b11111111111111111111111000000001 =
b11111111111111111111111000000001 I
b1 '
b1 G
b1 g
b10010 j
b10101010101110111100110011100001 k
1+
1c
b11111111111111111111111000000000 /
b11111111111111111111111000000000 @
b11111111111111111111111000000000 Y
b0 -
b0 A
b0 [
b0 ,
b0 B
b0 `
0.
0Z
b1001 l
13
#52000
03
#54000
b11111111111111111111111000000010 =
b11111111111111111111111000000010 I
b1000 l
b11111111111111111111111000000001 /
b11111111111111111111111000000001 @
b11111111111111111111111000000001 Y
b10 '
b10 G
b10 g
b10001 j
b10101010101110111100110011100101 k
13
#56000
03
0>
#58000
b11111111111111111111111000000011 =
b11111111111111111111111000000011 I
b11 '
b11 G
b11 g
b10000 j
b10101010101110111100110011101001 k
b11111111111111111111111000000010 /
b11111111111111111111111000000010 @
b11111111111111111111111000000010 Y
b111 l
13
#60000
0M
03
12
#62000
b0 /
b0 @
b0 Y
13
#64000
03
#66000
13
#68000
03
#70000
13
#72000
03
#74000
13
#76000
03
#78000
13
#80000
03
#82000
13
#84000
03
#86000
13
#88000
03
#90000
13
#92000
03
#94000
13
#96000
03
#98000
13
#100000
1M
03
02
#102000
b11111111111111111111111000000100 =
b11111111111111111111111000000100 I
b110 l
b11111111111111111111111000000011 /
b11111111111111111111111000000011 @
b11111111111111111111111000000011 Y
b100 '
b100 G
b100 g
b1111 j
b10101010101110111100110011101101 k
13
#104000
03
1>
#106000
b11111111111111111111111000000101 =
b11111111111111111111111000000101 I
b101 '
b101 G
b101 g
b1110 j
b10101010101110111100110011110001 k
b11111111111111111111111000000100 /
b11111111111111111111111000000100 @
b11111111111111111111111000000100 Y
b101 l
13
#108000
03
#110000
b11111111111111111111111000000110 =
b11111111111111111111111000000110 I
b100 l
b11111111111111111111111000000101 /
b11111111111111111111111000000101 @
b11111111111111111111111000000101 Y
b110 '
b110 G
b110 g
b1101 j
b10101010101110111100110011110101 k
13
#112000
03
#114000
b11111111111111111111111000000111 =
b11111111111111111111111000000111 I
b111 '
b111 G
b111 g
b1100 j
b10101010101110111100110011111001 k
b11111111111111111111111000000110 /
b11111111111111111111111000000110 @
b11111111111111111111111000000110 Y
b11 l
13
#116000
03
#118000
b11111111111111111111111000001000 =
b11111111111111111111111000001000 I
b10 l
b11111111111111111111111000000111 /
b11111111111111111111111000000111 @
b11111111111111111111111000000111 Y
b1000 '
b1000 G
b1000 g
b1011 j
b10101010101110111100110011111101 k
13
#120000
03
#122000
b11111111111111111111111000001001 =
b11111111111111111111111000001001 I
b1000 f
b1001 '
b1001 G
b1001 g
b1010 j
b10101010101110111100110100000001 k
b11111111111111111111111000001000 /
b11111111111111111111111000001000 @
b11111111111111111111111000001000 Y
b1 l
13
#124000
03
#126000
b11111111111111111111111000001010 =
b11111111111111111111111000001010 I
b10 f
0M
b1000 "
b1000 K
b0 l
b11111111111111111111111000001001 /
b11111111111111111111111000001001 @
b11111111111111111111111000001001 Y
b1010 '
b1010 G
b1010 g
b1001 j
b10101010101110111100110100000101 k
b1000 a
13
#128000
03
#130000
b11 f
1#
b10 "
b10 K
b10 a
0+
0c
1*
1e
b0 /
b0 @
b0 Y
13
#132000
03
#134000
b110 f
0#
b11 "
b11 K
0*
0e
b11 a
13
#136000
03
#138000
1M
b110 "
b110 K
b110 a
b10101010101110111100110100000100 /
b10101010101110111100110100000100 @
b10101010101110111100110100000100 Y
b1010 -
b1010 A
b1010 [
b1111 ,
b1111 B
b1111 `
1.
1Z
b1001 l
13
#140000
03
#142000
b11111111111111111111111000001011 =
b11111111111111111111111000001011 I
b1000 l
1+
1c
b11111111111111111111111000001010 /
b11111111111111111111111000001010 @
b11111111111111111111111000001010 Y
b0 -
b0 A
b0 [
b0 ,
b0 B
b0 `
0.
0Z
b1011 '
b1011 G
b1011 g
b1000 j
b10101010101110111100110100001001 k
13
#144000
03
#146000
b11111111111111111111111000001100 =
b11111111111111111111111000001100 I
b1100 '
b1100 G
b1100 g
b111 j
b10101010101110111100110100001101 k
b11111111111111111111111000001011 /
b11111111111111111111111000001011 @
b11111111111111111111111000001011 Y
b111 l
13
#148000
03
#150000
b11111111111111111111111000001101 =
b11111111111111111111111000001101 I
b110 l
b11111111111111111111111000001100 /
b11111111111111111111111000001100 @
b11111111111111111111111000001100 Y
b1101 '
b1101 G
b1101 g
b110 j
b10101010101110111100110100010001 k
13
#152000
03
#154000
b11111111111111111111111000001110 =
b11111111111111111111111000001110 I
b1110 '
b1110 G
b1110 g
b101 j
b10101010101110111100110100010101 k
b11111111111111111111111000001101 /
b11111111111111111111111000001101 @
b11111111111111111111111000001101 Y
b101 l
13
#156000
03
