project/modules/jtag_interface/clock_synchronizer.v
module clock_synchronizer #(
    parameter WIDTH = 8  // Change this to your desired bit width
)(
    input  wire              clockIn,
    input  wire              clockOut,
    input  wire              reset,
    input  wire [WIDTH-1:0]  D,
    output wire [WIDTH-1:0]  Q
);
  // 3-stage synchronization per bit
  reg [2:0] s_states [WIDTH-1:0];
  wire [2:0] s_d     [WIDTH-1:0];
  wire       s_reset0 [WIDTH-1:0];

  genvar i;
  generate
    for (i = 0; i < WIDTH; i = i + 1) begin : sync_logic
      assign s_d[i]     = {s_states[i][1:0], s_states[i][0] | D[i]};
      assign s_reset0[i] = reset | s_states[i][1];

      // First stage (clockIn domain)
      always @(posedge clockIn or posedge s_reset0[i]) begin
        if (s_reset0[i])
          s_states[i][0] <= 1'b0;
        else
          s_states[i][0] <= s_d[i][0];
      end

      // Second and third stages (clockOut domain)
      always @(posedge clockOut or posedge reset) begin
        if (reset)
          s_states[i][2:1] <= 2'b00;
        else
          s_states[i][2:1] <= s_d[i][2:1];
      end

      assign Q[i] = s_states[i][2];
    end
  endgenerate

endmodule

// ../../../modules/jtag_interface/clock_synchronizer.v:42: ERROR: Found posedge/negedge event on a signal that is not 1 bit wide!
//     always @(posedge clk_in or negedge n_reset or posedge sync_reg_3) begin
//         if (!n_reset | sync_reg_3) begin
//             sync_reg_1 <= 0;
//         end else begin
//             sync_reg_1 <= to_sync | sync_reg_1;
//         end
//     end

//     always @(posedge clk_out or negedge n_reset or posedge sync_reg_3) begin
//         if (!n_reset | sync_reg_3) begin
//             sync_reg_2 <= 0;
//         end else begin
//             sync_reg_2 <= sync_reg_1;
//         end
//     end

//     always @(posedge clk_out or negedge n_reset) begin
//         if (!n_reset) begin
//             sync_reg_3 <= 0;
//         end else begin
//             sync_reg_3 <= sync_reg_2;
//         end
//     end

project/modules/jtag_interface/testbenches/tb_clock_synchronizer.v
`timescale 1ns/1ps

module tb_clock_synchronizer;

    // Testbench signals
    reg clk_in;
    reg clk_out;
    reg[9:0] to_sync;
    reg n_reset;
    wire[9:0] sync_out;

    // Instantiate the DUT (Device Under Test)
    clock_synchronizer #(10) uut (
        .clockIn(clk_in),
        .clockOut(clk_out),
        .D(to_sync),
        .Q(sync_out),
        .reset(~n_reset)
    );

    // Clock generation for clk_in
    initial begin
        clk_in = 0;
        forever #5 clk_in = ~clk_in; // 10ns period
    end

    // Clock generation for clk_out
    initial begin
        clk_out = 0;
        forever #3 clk_out = ~clk_out; // 14ns period
    end

    // Test stimulus
    initial begin
        // Initialize inputs
        to_sync = 0; // Set to_sync high
        n_reset = 0;
        #10 n_reset = 1; // Release reset after 10ns


        #10 to_sync = 10'h3FF;
        #10 to_sync = 10'h0; // Set to_sync low

        #10 to_sync = 10'h1FF; // Set to_sync high again

        // Finish simulation
        #100 $finish;
    end

    // Monitor signals
    initial begin
         $dumpfile("test_clock_sync.vcd");
        $dumpvars(0, tb_clock_synchronizer);
    end

endmodule

project/modules/jtag_interface/testbenches/test_clock_sync.vcd
$date
	Fri May 16 15:02:32 2025
$end
$version
	Icarus Verilog
$end
$timescale
	1ps
$end
$scope module tb_clock_synchronizer $end
$var wire 10 ! sync_out [9:0] $end
$var reg 1 " clk_in $end
$var reg 1 # clk_out $end
$var reg 1 $ n_reset $end
$var reg 10 % to_sync [9:0] $end
$scope module uut $end
$var wire 10 & D [9:0] $end
$var wire 1 " clockIn $end
$var wire 1 # clockOut $end
$var wire 1 ' reset $end
$var wire 10 ( Q [9:0] $end
$var parameter 32 ) WIDTH $end
$scope begin sync_logic[0] $end
$var parameter 2 * i $end
$upscope $end
$scope begin sync_logic[1] $end
$var parameter 2 + i $end
$upscope $end
$scope begin sync_logic[2] $end
$var parameter 3 , i $end
$upscope $end
$scope begin sync_logic[3] $end
$var parameter 3 - i $end
$upscope $end
$scope begin sync_logic[4] $end
$var parameter 4 . i $end
$upscope $end
$scope begin sync_logic[5] $end
$var parameter 4 / i $end
$upscope $end
$scope begin sync_logic[6] $end
$var parameter 4 0 i $end
$upscope $end
$scope begin sync_logic[7] $end
$var parameter 4 1 i $end
$upscope $end
$scope begin sync_logic[8] $end
$var parameter 5 2 i $end
$upscope $end
$scope begin sync_logic[9] $end
$var parameter 5 3 i $end
$upscope $end
$upscope $end
$upscope $end
$enddefinitions $end
$comment Show the parameter values. $end
$dumpall
b1001 3
b1000 2
b111 1
b110 0
b101 /
b100 .
b11 -
b10 ,
b1 +
b0 *
b1010 )
$end
#0
$dumpvars
b0 (
1'
b0 &
b0 %
0$
0#
0"
b0 !
$end
#3000
1#
#5000
1"
#6000
0#
#9000
1#
#10000
0'
0"
1$
#12000
0#
#15000
1#
1"
#18000
0#
#20000
0"
b1111111111 %
b1111111111 &
#21000
1#
#24000
0#
#25000
1"
#27000
1#
#30000
0#
0"
b0 %
b0 &
#33000
b1111111111 !
b1111111111 (
1#
#35000
1"
#36000
0#
#39000
b0 !
b0 (
1#
#40000
0"
b111111111 %
b111111111 &
#42000
0#
#45000
1#
1"
#48000
0#
#50000
0"
#51000
1#
#54000
0#
#55000
1"
#57000
b111111111 !
b111111111 (
1#
#60000
0#
0"
#63000
b0 !
b0 (
1#
#65000
1"
#66000
0#
#69000
1#
#70000
0"
#72000
0#
#75000
b111111111 !
b111111111 (
1#
1"
#78000
0#
#80000
0"
#81000
b0 !
b0 (
1#
#84000
0#
#85000
1"
#87000
1#
#90000
0#
0"
#93000
b111111111 !
b111111111 (
1#
#95000
1"
#96000
0#
#99000
b0 !
b0 (
1#
#100000
0"
#102000
0#
#105000
b111111111 !
b111111111 (
1#
1"
#108000
0#
#110000
0"
#111000
b0 !
b0 (
1#
#114000
0#
#115000
1"
#117000
1#
#120000
0#
0"
#123000
b111111111 !
b111111111 (
1#
#125000
1"
#126000
0#
#129000
b0 !
b0 (
1#
#130000
0"
#132000
0#
#135000
b111111111 !
b111111111 (
1#
1"
