project/modules/jtag_interface/dma_ci.v
module dma_ci #(parameter [7:0] customInstructionId = 8'd0 )
                           ( input wire         start, clock, reset,
                             input wire [31:0]  valueA,
                                                valueB,
                             input wire [7:0]   iseId,
                             output wire        done,
                             output wire [31:0] result, 

                            //  Interface with the DMA controller

                            output wire s_dataReady,
                            output wire s_readReady,
                            output wire [3:0] s_byteEnable,
                            output wire [31:0] s_address_to_read,
                            input wire s_endTransaction,
                            input wire s_dataValid,
                            input wire s_address_data
                             );
    
    // DMA signals
    wire s_isMyIse = (iseId == customInstructionId) ? start : 1'b0;

    localparam [2:0] fsm_idle = 3'b000;
    localparam [2:0] fsm_wait_end = 3'b001;
    localparam [2:0] fsm_initiate_transaction = 3'b010;
    localparam [2:0] fsm_end_ci = 3'b011;

    reg [2:0] cur_state, nxt_state;
    reg [31:0] result_reg;
    reg [31:0] address_reg;
    reg is_read;    

    always @(*) begin
        case(cur_state)
            fsm_idle: nxt_state = (s_isMyIse) ? fsm_initiate_transaction : fsm_idle;
            fsm_initiate_transaction: nxt_state = fsm_wait_end;
            fsm_wait_end: nxt_state = (s_endTransaction) ? fsm_end_ci : fsm_wait_end;
            fsm_end_ci: nxt_state = fsm_idle;
            default: nxt_state = fsm_idle;
        endcase
    end 

    always @(posedge clock or negedge reset) begin
        if (reset) begin
            cur_state <= fsm_idle;
        end else begin
            cur_state <= nxt_state;
        end
    end

    always @(posedge clock or negedge reset) begin
        result_reg <= (reset == 1'b1) ? 32'b0 : (s_dataValid == 1'b1) ? s_address_data : result_reg;
        address_reg <= (reset == 1'b1) ? 32'b0 : (s_isMyIse) ? valueA : address_reg;
        is_read <= (reset == 1'b1) ? 1'b0 : (s_isMyIse) ? valueB[0] : is_read;
    end
    

    assign result = (cur_state == fsm_end_ci) ? result_reg : 32'b0;
    assign done = (cur_state == fsm_end_ci) ? 1'b1 : 1'b0;
    assign s_dataReady = (cur_state == fsm_initiate_transaction) ? is_read : 1'b0;
    assign s_readReady = (cur_state == fsm_initiate_transaction) ? ~is_read : 1'b0;
    assign s_byteEnable = (cur_state == fsm_initiate_transaction) ? 4'b1111 : 4'b0000;
    assign s_address_to_read = (cur_state == fsm_initiate_transaction) ? address_reg : 32'b0;

endmodule

project/modules/jtag_interface/testbenches/tb_dma_ci.v
`timescale 1ns / 1ps

module tb_dma_ci;

    // Parameters
    localparam [7:0] CUSTOM_INSTRUCTION_ID = 8'd49;

    // Inputs
    reg start;
    reg clock;
    reg reset;
    reg [31:0] valueA;
    reg [31:0] valueB;
    reg [7:0] iseId;
    reg s_endTransaction;
    reg s_dataValid;
    reg s_address_data;

    // Outputs
    wire done;
    wire [31:0] result;
    wire s_dataReady;
    wire s_readReady;
    wire [3:0] s_byteEnable;
    wire [31:0] s_address_to_read;

    // Instantiate the Unit Under Test (UUT)
    dma_ci #(.customInstructionId(CUSTOM_INSTRUCTION_ID)) uut (
        .start(start),
        .clock(clock),
        .reset(reset),
        .valueA(valueA),
        .valueB(valueB),
        .iseId(iseId),
        .done(done),
        .result(result),
        .s_dataReady(s_dataReady),
        .s_readReady(s_readReady),
        .s_byteEnable(s_byteEnable),
        .s_address_to_read(s_address_to_read),
        .s_endTransaction(s_endTransaction),
        .s_dataValid(s_dataValid),
        .s_address_data(s_address_data)
    );

    // Clock generation
    initial begin
        clock = 0;
        forever #5 clock = ~clock; // 100 MHz clock
    end

    // Testbench logic
    initial begin
        // Initialize inputs
        start = 0;
        reset = 0;
        valueA = 32'h0;
        valueB = 32'h0;
        iseId = 8'h0;
        s_endTransaction = 0;
        s_dataValid = 0;
        s_address_data = 0;

        // Reset the design
        #10 reset = 1;
        #10 reset = 0;

        // Test case 1: Start a transaction with matching ISE ID
        #10 iseId = CUSTOM_INSTRUCTION_ID;
        valueA = 32'h12345678;
        valueB = 32'h00000001; // is_read = 1
        start = 1;
        #10 start = 0;
        valueA = 32'h0; // Reset valueA after starting
        valueB = 32'h0; // Reset valueB after starting

        // Simulate end of transaction
        #50 s_endTransaction = 1;
        #10 s_endTransaction = 0;

        // Test case 2: Start a transaction with non-matching ISE ID
        #50 iseId = 8'hFF; // Non-matching ID
        valueA = 32'h87654321;
        valueB = 32'h00000000; // is_read = 0
        start = 1;
        #10 start = 0;
        valueA = 32'h0; // Reset valueA after starting
        valueB = 32'h0; // Reset valueB after starting

        // Simulate end of transaction
        #50 s_endTransaction = 1;
        #10 s_endTransaction = 0;

        // End simulation
        #100 $finish;
    end
    initial begin
        $dumpfile("test_dma_ci.vcd");
        $dumpvars(0, tb_dma_ci);
    end

endmodule

project/modules/jtag_interface/testbenches/test_dma_ci.vcd
$date
	Thu May  8 23:49:11 2025
$end
$version
	Icarus Verilog
$end
$timescale
	1ps
$end
$scope module tb_dma_ci $end
$var wire 1 ! s_readReady $end
$var wire 1 " s_dataReady $end
$var wire 4 # s_byteEnable [3:0] $end
$var wire 32 $ s_address_to_read [31:0] $end
$var wire 32 % result [31:0] $end
$var wire 1 & done $end
$var parameter 8 ' CUSTOM_INSTRUCTION_ID $end
$var reg 1 ( clock $end
$var reg 8 ) iseId [7:0] $end
$var reg 1 * reset $end
$var reg 1 + s_address_data $end
$var reg 1 , s_dataValid $end
$var reg 1 - s_endTransaction $end
$var reg 1 . start $end
$var reg 32 / valueA [31:0] $end
$var reg 32 0 valueB [31:0] $end
$scope module uut $end
$var wire 1 ( clock $end
$var wire 8 1 iseId [7:0] $end
$var wire 1 * reset $end
$var wire 1 + s_address_data $end
$var wire 1 , s_dataValid $end
$var wire 1 - s_endTransaction $end
$var wire 1 . start $end
$var wire 32 2 valueA [31:0] $end
$var wire 32 3 valueB [31:0] $end
$var wire 1 ! s_readReady $end
$var wire 1 4 s_isMyIse $end
$var wire 1 " s_dataReady $end
$var wire 4 5 s_byteEnable [3:0] $end
$var wire 32 6 s_address_to_read [31:0] $end
$var wire 32 7 result [31:0] $end
$var wire 1 & done $end
$var parameter 8 8 customInstructionId $end
$var parameter 3 9 fsm_end_ci $end
$var parameter 3 : fsm_idle $end
$var parameter 3 ; fsm_initiate_transaction $end
$var parameter 3 < fsm_wait_end $end
$var reg 32 = address_reg [31:0] $end
$var reg 3 > cur_state [2:0] $end
$var reg 1 ? is_read $end
$var reg 3 @ nxt_state [2:0] $end
$var reg 32 A result_reg [31:0] $end
$upscope $end
$upscope $end
$enddefinitions $end
$comment Show the parameter values. $end
$dumpall
b1 <
b10 ;
b0 :
b11 9
b110001 8
b110001 '
$end
#0
$dumpvars
bx A
b0 @
x?
bx >
bx =
bx 7
bx 6
bx 5
04
b0 3
b0 2
b0 1
b0 0
b0 /
0.
0-
0,
0+
0*
b0 )
0(
x&
bx %
bx $
bx #
x"
x!
$end
#5000
b0 %
b0 7
0&
0"
0!
b0 #
b0 5
b0 $
b0 6
b0 >
1(
#10000
0(
1*
#15000
0?
b0 =
b0 A
1(
#20000
0(
0*
#25000
1(
#30000
b10 @
14
0(
1.
b1 0
b1 3
b10010001101000101011001111000 /
b10010001101000101011001111000 2
b110001 )
b110001 1
#35000
b1 @
1"
0!
b1111 #
b1111 5
b10010001101000101011001111000 $
b10010001101000101011001111000 6
1?
b10010001101000101011001111000 =
b10 >
1(
#40000
04
0(
b0 0
b0 3
b0 /
b0 2
0.
#45000
0"
b0 #
b0 5
b0 $
b0 6
b1 >
1(
#50000
0(
#55000
1(
#60000
0(
#65000
1(
#70000
0(
#75000
1(
#80000
0(
#85000
1(
#90000
b11 @
0(
1-
#95000
b0 @
1&
b11 >
1(
#100000
0(
0-
#105000
0&
b0 >
1(
#110000
0(
#115000
1(
#120000
0(
#125000
1(
#130000
0(
#135000
1(
#140000
0(
#145000
1(
#150000
0(
1.
b10000111011001010100001100100001 /
b10000111011001010100001100100001 2
b11111111 )
b11111111 1
#155000
1(
#160000
0(
b0 /
b0 2
0.
#165000
1(
#170000
0(
#175000
1(
#180000
0(
#185000
1(
#190000
0(
#195000
1(
#200000
0(
#205000
1(
#210000
0(
1-
#215000
1(
#220000
0(
0-
