project/modules/jtag_interface/chain1.v
module chain1(
    // JTAG signals
    input wire JTCK,
    input wire JTDI,
    input wire JRTI1,
    input wire JSHIFT,
    input wire JUPDATE,
    input wire JRSTN,
    input wire JCE1,
    output wire JTD1,

    // Connection to the ping-pong buffer
    output wire [8:0] pp_address,
    output wire pp_writeEnable,
    output wire [31:0] pp_dataIn,
    input wire [31:0] pp_dataOut,
    output wire pp_switch,

    // Connection with the DMA
    output wire [31:0] DMA_address,
    output wire DMA_launch_write,
    output wire DMA_launch_read,
    output wire [3:0] DMA_byte_enable,
    output wire [7:0] DMA_burst_size_OUT,
    input wire DMA_busy,
    input wire [7:0] DMA_block_size_IN,

    // Visual Clues 
    output wire [5:0] status_reg_out
);




assign n_reset = JRSTN;

reg [31:0] address_reg;
reg [3:0] byte_enable_reg;
reg [7:0] busrt_size_reg;

reg [35:0] shadow_reg;
reg [35:0] shift_reg;
reg [35:0] updated_data_reg;

reg update_reg;

reg [5:0] status_next;
reg [5:0] status_reg;

reg [31:0] data_reg;
reg [7:0] block_size_reg;

reg write_to_buffer;
reg write_operation_in_progress;

reg [7:0] buffer_read_reg;
reg read_buffer;
reg read_operation_in_progress;

reg launch_write;
reg launch_read;
reg only_switch;

localparam IDLE =                      0;
localparam ASK_FOR_BUFFER =            1;
localparam READ_BUFFER =               2; 
localparam WAIT_FOR_DMA =              3;
localparam SWITCH_BUFFER =             4;
localparam LAUNCH_DMA =                5;
localparam END_INSTRUCTION =           6;


reg [2:0] chain1_cur_state;
reg [2:0] chain1_nxt_state;

assign status_reg_out = {chain1_cur_state, DMA_launch_write, DMA_launch_read, pp_switch};

assign launch_dma = launch_write | launch_read | only_switch;

assign JTD1 = shift_reg[0];

assign operation_in_progress = write_operation_in_progress | read_operation_in_progress;
assign ready_to_launch = (block_size_reg != 8'b0 && byte_enable_reg != 4'b0) ? 1'b1 : only_switch;

assign buffer_full = (block_size_reg == 8'b11111111) ? 1'b1 : 1'b0;
assign read_complete = (buffer_read_reg == block_size_reg) ? 1'b1 : 1'b0;


always @(posedge JTCK) begin
    if (n_reset == 0) begin
        shift_reg <= 36'b0;
    end
    // handle the JTAG signals
    else begin
         if (JCE1) begin
        // Shifting data in
            if (JSHIFT) begin
                shift_reg <= {JTDI, shift_reg[35:1]};
            end
            // capture the status register
            else begin
                shift_reg <= shadow_reg;
            end
        end 

    end
    update_reg <= (n_reset == 1'b0) ? 0 : JUPDATE;
    updated_data_reg <= (n_reset == 1'b0) ? 0 : (JUPDATE == 1'b1) ? shift_reg : updated_data_reg;
    // Precompute the status register
    if (JUPDATE == 1'b1) begin
        case (shift_reg[3:0])
            4'b0001: status_next = status_reg | 6'b000001;
            4'b0010: status_next = status_reg | 6'b000010;
            4'b0011: status_next = status_reg | 6'b000100;
            default: status_next = status_reg;
        endcase
    end
end

always @(posedge JTCK) begin
    if (n_reset == 0 || updated_data_reg[3:0] == 4'b1111) begin
        shadow_reg <= 36'b0;
        address_reg <= 32'b0;
        byte_enable_reg <= 4'b1111;
        busrt_size_reg <= 8'b0;
        status_reg <= 6'b0;
        block_size_reg <= 8'b0;
        data_reg <= 32'b0;
        write_to_buffer <= 1'b0;
        write_operation_in_progress <= 1'b0;
        read_operation_in_progress <= 1'b0;
        buffer_read_reg <= 8'b0;
        read_buffer <= 1'b0;
        data_reg <= 32'b0;
        launch_read <= 1'b0;
        launch_write <= 1'b0;
        only_switch <= 1'b0;
    end
    else if (update_reg == 1'b1) begin

        status_reg <= status_next;
                        
        shadow_reg <=   (updated_data_reg[3:0] == 4'b0100) ? address_reg :
                        (updated_data_reg[3:0] == 4'b0101) ? byte_enable_reg :
                        (updated_data_reg[3:0] == 4'b0110) ? busrt_size_reg :
                        {30'b0, status_next}; 

        address_reg <= (updated_data_reg[3:0] == 4'b0001) ? updated_data_reg[35:4] : address_reg;

        byte_enable_reg <= (updated_data_reg[3:0] == 4'b0010) ? updated_data_reg[7:4] : byte_enable_reg;

        busrt_size_reg <= (updated_data_reg[3:0] == 4'b0011) ? updated_data_reg[11:4] : busrt_size_reg;

        block_size_reg <= (updated_data_reg[3:0] == 4'b1000 && buffer_full == 1'b0) ? block_size_reg + 1 : block_size_reg;

        write_to_buffer <= (updated_data_reg[3:0] == 4'b1000 && buffer_full == 1'b0) ? 1'b1 : 1'b0;

        data_reg <= (updated_data_reg[3:0] == 4'b1000 && buffer_full == 1'b0) ? updated_data_reg[35:4] : data_reg;

        write_operation_in_progress <= (updated_data_reg[3:0] == 4'b1000 && buffer_full == 1'b0) ? 1'b1 : write_operation_in_progress;

        read_operation_in_progress <= (updated_data_reg[3:0] == 4'b1001) ? 1'b1 : read_operation_in_progress;

        buffer_read_reg <= (updated_data_reg[3:0] == 4'b1001 && read_complete == 1'b0) ? buffer_read_reg + 1 : buffer_read_reg;

        read_buffer <= (updated_data_reg[3:0] == 4'b1001 && read_complete == 1'b0) ? 1'b1 : 1'b0;

        launch_read <= (updated_data_reg[3:0] == 4'b1011) ? 1'b1 : 1'b0;

        launch_write <= (updated_data_reg[3:0] == 4'b1010) ? 1'b1 : 1'b0;

        only_switch <= (updated_data_reg[3:0] == 4'b1100) ? 1'b1 : 1'b0;

    end
    else begin
        shadow_reg <= (chain1_cur_state == READ_BUFFER) ? data_reg : shadow_reg;

        data_reg <= (chain1_cur_state == READ_BUFFER) ? pp_dataOut : data_reg;

        read_buffer <= (chain1_cur_state == READ_BUFFER) ? 1'b0 : read_buffer;

        launch_read <= (chain1_cur_state == END_INSTRUCTION) ? 1'b0 : launch_read;

        launch_write <= (chain1_cur_state == END_INSTRUCTION) ? 1'b0 : launch_write;
        only_switch <= (chain1_cur_state == END_INSTRUCTION) ? 1'b0 : only_switch;

        block_size_reg <= (chain1_cur_state == SWITCH_BUFFER) ? DMA_block_size_IN : block_size_reg;

        buffer_read_reg <= (chain1_cur_state == SWITCH_BUFFER) ? 8'b0 : buffer_read_reg;
    end
end

always @(posedge JTCK) begin
    if (n_reset == 0) begin
        chain1_cur_state <= IDLE;
    end
    else begin
        chain1_cur_state <= chain1_nxt_state;
    end
end

always @(*) begin
    case (chain1_cur_state)
        IDLE: begin
            chain1_nxt_state <= (read_buffer == 1'b1) ? ASK_FOR_BUFFER :
                                (launch_dma == 1'b1 && ready_to_launch == 1'b1) ? WAIT_FOR_DMA :
                                IDLE;
        end

        // Write to buffer operaation
        ASK_FOR_BUFFER: begin
            chain1_nxt_state <= READ_BUFFER;
        end
        READ_BUFFER: begin
            chain1_nxt_state <= (JUPDATE == 1'b1) ? IDLE : READ_BUFFER;
        end

        // Send instruction to DMA
        WAIT_FOR_DMA: begin
            chain1_nxt_state <= (DMA_busy == 1'b0) ? SWITCH_BUFFER : WAIT_FOR_DMA;
        end
        SWITCH_BUFFER: begin
            chain1_nxt_state <= LAUNCH_DMA;
        end
        LAUNCH_DMA: begin
            chain1_nxt_state <= END_INSTRUCTION;
        end
        END_INSTRUCTION: begin
            chain1_nxt_state <= IDLE;
        end
        default: begin 
            chain1_nxt_state <= IDLE;
        end
    endcase
end

assign pp_address = (write_to_buffer == 1'b1) ? {1'b0, block_size_reg}: 
                    (chain1_cur_state != IDLE) ? {1'b0, buffer_read_reg} : 9'b0;
assign pp_writeEnable = (write_to_buffer == 1'b1) ? 1'b1 : 1'b0;
assign pp_dataIn = (write_to_buffer == 1'b1) ? data_reg : 32'b0;
assign pp_switch = (chain1_cur_state == SWITCH_BUFFER) ? 1'b1 : 1'b0;

assign DMA_address = address_reg;
assign DMA_burst_size_OUT = busrt_size_reg;
assign DMA_byte_enable = byte_enable_reg;
assign DMA_launch_write = (chain1_cur_state == LAUNCH_DMA) ? launch_write: 1'b0;
assign DMA_launch_read = (chain1_cur_state == LAUNCH_DMA) ? launch_read : 1'b0;

//     assign pp_switch = (chain1_cur_state == write_SWITCH_BUFFER | chain1_cur_state == read_SWITCH_BUFFER) ? 1'b1 : 1'b0;
//     assign dma_address = (chain1_cur_state == write_LAUNCH_WRITE | chain1_cur_state == read_LAUNCH_READ) ? address_reg : 32'b0;
//     assign dma_data_ready = (chain1_cur_state == write_LAUNCH_WRITE) ? 1'b1 : 1'b0;
//     assign dma_byte_enable = (chain1_cur_state == write_LAUNCH_WRITE | chain1_cur_state == read_LAUNCH_READ) ? byte_enable_reg : 4'b0;
//     assign dma_readReady = (chain1_cur_state == read_LAUNCH_READ) ? 1'b1 : 1'b0;
// always @(posedge JTCK or negedge JRSTN) begin
//     if (JRSTN == 0) begin
//         shift_reg <= 34'b0;
//         status_reg <= 6'b0;
//         address_reg <= 32'b0;
//         byte_enable_reg <= 4'b0;
//         busrt_size_reg <= 8'b0;
//         remaining_size_reg <= 8'b0;
//         pp_address_reg <= 8'b0;
//         r_data_shifted_in <= 1'b0;
//         r_launch_read <= 1'b0;
//         r_data_shifted_out <= 1'b0;
//         read_data_from_buffer <= 32'b0;
//         chain1_cur_state <= IDLE;
//     end
//     else  begin
//         // Reset the registers
//         r_data_shifted_in <= 1'b0;
//         r_launch_read <= 1'b0;
//         r_data_shifted_out <= 1'b0;
        
//         // Move to the next state
//         chain1_cur_state <= chain1_nxt_state;

//         // Handle internal signals
//         case (chain1_cur_state)
//             write_FILL_BUFFER: begin 
//                 if (remaining_size_reg != 0) begin
//                     remaining_size_reg <= remaining_size_reg - 1;
//                 end
//             end 
//             write_LAUNCH_WRITE: begin
//                 if (remaining_size_reg == 0) begin
//                     status_reg <= status_reg & 6'b0111;
//                 end
//             end
//             read_STORE_BUFFER_ANSWER: begin
//                 read_data_from_buffer <= pp_dataOut;
//                 status_reg <= status_reg | 6'b100000;
//             end
//             read_DATA_READY_TO_READ: begin
//                 if (r_data_shifted_out) begin
//                     status_reg[5] <= 1'b0;
//                     if (remaining_size_reg == 0) begin
//                         status_reg[4] <= 1'b0;
//                     end
//                     else begin
//                         remaining_size_reg <= remaining_size_reg - 1;
//                     end
//                 end
//             end
//         endcase

//         // Update datas registers based on the instruction used
//         if (JUPDATE) begin
//             case (shift_reg[3:0])
//                 4'b0001: begin
//                     // Writting to address register
//                     if (~is_operation_running) begin
//                         address_reg <= shift_reg[35:4];
//                         status_reg <= status_reg | 6'b0001;
//                     end
//                 end
//                 4'b0010: begin
//                     // writting to byte enable register
//                     if (~is_operation_running) begin
//                         byte_enable_reg <= shift_reg[7:4];
//                         status_reg <= status_reg | 6'b0010;
//                     end
//                 end
//                 4'b0011: begin
//                     // writting the size reg
//                     if (~is_operation_running) begin
//                         busrt_size_reg <= shift_reg[11:4];
//                         remaining_size_reg <= shift_reg[11:4];
//                         status_reg <= status_reg | 6'b0100;
//                     end
//                 end
//                 4'b1000: begin
//                     // Send data
//                     data_reg <= shift_reg[35:4];
//                     status_reg <= status_reg | 6'b1000;
//                     r_data_shifted_in <= 1'b1;
//                 end
//                 4'b1001: begin
//                     // Start the read operation
//                     status_reg <= status_reg | 6'b10000;
//                     r_launch_read <= 1'b1;
//                 end
//                 4'b1010: begin 
//                     // Read operation and move to next word
//                     status_reg[5] <= 1'b0;
//                 end
//             endcase 
//         end
//     end
// end

// always @(posedge JTCK or negedge JRSTN) 
//     begin
//         if (JRSTN == 0) begin
//             // chain1_cur_state <= IDLE;
//             // read_data_from_buffer <= 32'b0;
//         end
//         else begin 
//         //     chain1_cur_state = chain1_nxt_state;
//         //     case (chain1_cur_state)
//         //         write_FILL_BUFFER: begin 
//         //             if (remaining_size_reg != 0) begin
//         //                 remaining_size_reg <= remaining_size_reg - 1;
//         //             end
//         //         end 
//         //         write_LAUNCH_WRITE: begin
//         //             if (remaining_size_reg == 0) begin
//         //                 status_reg <= status_reg & 6'b0111;
//         //             end
//         //         end
//         //         read_STORE_BUFFER_ANSWER: begin
//         //             read_data_from_buffer <= pp_dataOut;
//         //             status_reg <= status_reg | 6'b100000;
//         //         end
//         //         read_DATA_READY_TO_READ: begin
//         //             if (r_data_shifted_out) begin
//         //                 status_reg[5] <= 1'b0;
//         //                 if (remaining_size_reg == 0) begin
//         //                     status_reg[4] <= 1'b0;
//         //                 end
//         //                 else begin
//         //                     remaining_size_reg <= remaining_size_reg - 1;
//         //                 end
//         //             end
//         //         end
//         // endcase
//         end
//     end 

// always @(*) begin
//     case (chain1_cur_state)
//         IDLE: begin
//             if (r_data_shifted_in) begin
//                 chain1_nxt_state <= write_FILL_BUFFER;
//             end
//             else begin
//                 if (r_launch_read) begin
//                     chain1_nxt_state <= read_LAUNCH_READ;
//                 end
//                 else begin
//                     chain1_nxt_state <= IDLE;
//                 end
//             end
//         end
//         write_FILL_BUFFER: begin
//             if (remaining_size_reg == 0) begin
//                 chain1_nxt_state <= write_WAIT_FOR_SWITCH;
//             end
//             else begin
//                 chain1_nxt_state <= IDLE;
//             end
//         end

//         write_WAIT_FOR_SWITCH: begin
//             if (s_ready_to_switch) begin
//                 chain1_nxt_state <= write_SWITCH_BUFFER;
//             end
//             else begin
//                 chain1_nxt_state <= write_WAIT_FOR_SWITCH;
//             end
//         end

//         write_SWITCH_BUFFER: begin
//             chain1_nxt_state <= write_LAUNCH_WRITE;
//         end

//         write_LAUNCH_WRITE: begin
//             chain1_nxt_state <= IDLE;
//         end

//         read_LAUNCH_READ: begin
//             chain1_nxt_state <= read_WAIT_FOR_SWITCH;
//         end

//         read_WAIT_FOR_SWITCH: begin
//             if (s_ready_to_switch) begin
//                 chain1_nxt_state <= read_SWITCH_BUFFER;
//             end
//             else begin
//                 chain1_nxt_state <= read_WAIT_FOR_SWITCH;
//             end
//         end

//         read_SWITCH_BUFFER: begin
//             chain1_nxt_state <= read_ASK_BUFFER;
//         end

//         read_ASK_BUFFER: begin
//             chain1_nxt_state <= read_STORE_BUFFER_ANSWER;
//         end

//         read_STORE_BUFFER_ANSWER: begin
//             chain1_nxt_state <= read_DATA_READY_TO_READ;
//         end

//         read_DATA_READY_TO_READ: begin
//             if (r_data_shifted_out) begin
//                 // r_data_shifted_out <= 1'b0;
//                 if (remaining_size_reg == 0) begin
//                     chain1_nxt_state <= IDLE;
//                 end
//                 else begin
//                     chain1_nxt_state <= read_ASK_BUFFER;
//                 end
//             end
//             else begin
//                 chain1_nxt_state <= read_DATA_READY_TO_READ;
//             end
            
//         end
//         default: begin
//             chain1_nxt_state <= IDLE;
//         end

//     endcase 
// end

//     assign pp_address = (chain1_cur_state == write_FILL_BUFFER | chain1_cur_state == read_ASK_BUFFER) ? {1'b0, pp_address_reg}: 9'b0;
//     assign pp_writeEnable = (chain1_cur_state == write_FILL_BUFFER) ? 1'b1 : 1'b0;
//     assign pp_dataIn = (chain1_cur_state == write_FILL_BUFFER) ? data_reg : 32'b0;
//     assign pp_switch = (chain1_cur_state == write_SWITCH_BUFFER | chain1_cur_state == read_SWITCH_BUFFER) ? 1'b1 : 1'b0;
//     assign dma_address = (chain1_cur_state == write_LAUNCH_WRITE | chain1_cur_state == read_LAUNCH_READ) ? address_reg : 32'b0;
//     assign dma_data_ready = (chain1_cur_state == write_LAUNCH_WRITE) ? 1'b1 : 1'b0;
//     assign dma_byte_enable = (chain1_cur_state == write_LAUNCH_WRITE | chain1_cur_state == read_LAUNCH_READ) ? byte_enable_reg : 4'b0;
//     assign dma_readReady = (chain1_cur_state == read_LAUNCH_READ) ? 1'b1 : 1'b0;


endmodule

project/modules/jtag_interface/testbenches/tb_chain1.v
`timescale 1ns/1ps;

module tb_chain1;
    
    reg JTCK;
    reg JTDI;
    reg JRTI1;
    reg JSHIFT;
    reg JUPDATE;
    reg JRSTN;
    reg JCE1;
    reg s_dma_busy;
    wire JTD1;

    // Instantiate the DUT (Device Under Test)
    chain1 dut (
        .JTCK(JTCK),
        .JTDI(JTDI),
        .JRTI1(JRTI1),
        .JSHIFT(JSHIFT),
        .JUPDATE(JUPDATE),
        .JRSTN(JRSTN),
        .JCE1(JCE1),
        .JTD1(JTD1),
        .pp_dataOut(32'hFFFFFFFF),
        .DMA_busy(s_dma_busy),
        .DMA_block_size_IN(8'b1)
    );

    // Clock generation
    initial begin
        JTCK = 0; // Initialize JTCK
    end

    always #2 JTCK = ~JTCK;

    integer i;
    task sendInstruction(input [35:0] instruction);
        begin
            JRTI1 = 0;
            #8;
            JCE1 = 1;
            #4;
            for (i = 0; i < 36; i = i + 1) begin
                JTDI = instruction[i];
                JSHIFT = 1;
                #4;
            end
            JCE1 = 0;
            JSHIFT = 0;
            #8;
            JUPDATE = 1;
            #4;
            JUPDATE = 0;
            JRTI1 = 1;
            #4;
        end
    endtask

    initial begin
        // Initialize signals
        JTCK = 0;
        JTDI = 0;
        JRTI1 = 0;
        JSHIFT = 0;
        JUPDATE = 0;
        JRSTN = 1;
        JCE1 = 0;
        s_dma_busy = 1;

        // Reset the DUT
        #8;
        JRSTN = 0;
        #8;
        JRSTN = 1;
        #8;
        JRTI1 = 1;
        #8;


        // // try to read the address register 
        // sendInstruction(36'b100);
        // #12;
        // sendInstruction(36'b0);

        // // try to read the byte enable register and the busrt size register
        // sendInstruction(36'b101);
        // #12;
        // sendInstruction(36'b110);
        // #12;
        // sendInstruction(36'b000);

        // // Try to write in the buffer
        // sendInstruction(36'hABCDEF8);
        // sendInstruction(36'h1ABCDEF8);
        // sendInstruction(36'h2ABCDEF8);
        // sendInstruction(36'h0);


        // //Try to read from the buffer

        // sendInstruction(36'b1001);
        // #8;       
        // sendInstruction(36'b1001);
        // #8;       
        // sendInstruction(36'b1001);



        // Try to send a burst of data

        // set the burst size to 1
        sendInstruction(36'h13);

        // set the address to 0x55555555
        sendInstruction(36'h555555551);

        // Write some data in the buffer
        sendInstruction(36'hABCDEF8);
        sendInstruction(36'h1ABCDEF8);
        sendInstruction(36'h2ABCDEF8);

        // launch write operation
        sendInstruction(36'b1010);
        #20;
        s_dma_busy = 0;

        sendInstruction(36'b1100);

        #160;
        $finish;
    end

    initial begin
        $dumpfile("test_chain1.vcd");
        $dumpvars(0, tb_chain1);
    end

endmodule

project/modules/jtag_interface/testbenches/test_chain1.vcd
$date
	Thu May 15 13:13:44 2025
$end
$version
	Icarus Verilog
$end
$timescale
	1ps
$end
$scope module tb_chain1 $end
$var wire 1 ! JTD1 $end
$var reg 1 " JCE1 $end
$var reg 1 # JRSTN $end
$var reg 1 $ JRTI1 $end
$var reg 1 % JSHIFT $end
$var reg 1 & JTCK $end
$var reg 1 ' JTDI $end
$var reg 1 ( JUPDATE $end
$var reg 1 ) s_dma_busy $end
$var integer 32 * i [31:0] $end
$scope module dut $end
$var wire 32 + DMA_address [31:0] $end
$var wire 8 , DMA_block_size_IN [7:0] $end
$var wire 8 - DMA_burst_size_OUT [7:0] $end
$var wire 1 ) DMA_busy $end
$var wire 4 . DMA_byte_enable [3:0] $end
$var wire 1 " JCE1 $end
$var wire 1 # JRSTN $end
$var wire 1 $ JRTI1 $end
$var wire 1 % JSHIFT $end
$var wire 1 & JTCK $end
$var wire 1 ' JTDI $end
$var wire 1 ( JUPDATE $end
$var wire 1 / launch_dma $end
$var wire 1 0 n_reset $end
$var wire 1 1 operation_in_progress $end
$var wire 32 2 pp_dataOut [31:0] $end
$var wire 6 3 status_reg_out [5:0] $end
$var wire 1 4 ready_to_launch $end
$var wire 1 5 read_complete $end
$var wire 1 6 pp_writeEnable $end
$var wire 1 7 pp_switch $end
$var wire 32 8 pp_dataIn [31:0] $end
$var wire 9 9 pp_address [8:0] $end
$var wire 1 : buffer_full $end
$var wire 1 ! JTD1 $end
$var wire 1 ; DMA_launch_write $end
$var wire 1 < DMA_launch_read $end
$var parameter 32 = ASK_FOR_BUFFER $end
$var parameter 32 > END_INSTRUCTION $end
$var parameter 32 ? IDLE $end
$var parameter 32 @ LAUNCH_DMA $end
$var parameter 32 A READ_BUFFER $end
$var parameter 32 B SWITCH_BUFFER $end
$var parameter 32 C WAIT_FOR_DMA $end
$var reg 32 D address_reg [31:0] $end
$var reg 8 E block_size_reg [7:0] $end
$var reg 8 F buffer_read_reg [7:0] $end
$var reg 8 G busrt_size_reg [7:0] $end
$var reg 4 H byte_enable_reg [3:0] $end
$var reg 3 I chain1_cur_state [2:0] $end
$var reg 3 J chain1_nxt_state [2:0] $end
$var reg 32 K data_reg [31:0] $end
$var reg 1 L launch_read $end
$var reg 1 M launch_write $end
$var reg 1 N only_switch $end
$var reg 1 O read_buffer $end
$var reg 1 P read_operation_in_progress $end
$var reg 36 Q shadow_reg [35:0] $end
$var reg 36 R shift_reg [35:0] $end
$var reg 6 S status_next [5:0] $end
$var reg 6 T status_reg [5:0] $end
$var reg 1 U update_reg $end
$var reg 36 V updated_data_reg [35:0] $end
$var reg 1 W write_operation_in_progress $end
$var reg 1 X write_to_buffer $end
$upscope $end
$scope task sendInstruction $end
$var reg 36 Y instruction [35:0] $end
$upscope $end
$upscope $end
$enddefinitions $end
$comment Show the parameter values. $end
$dumpall
b11 C
b100 B
b10 A
b101 @
b0 ?
b110 >
b1 =
$end
#0
$dumpvars
bx Y
xX
xW
bx V
xU
bx T
bx S
bx R
bx Q
xP
xO
xN
xM
xL
bx K
b0 J
bx I
bx H
bx G
bx F
bx E
bx D
x<
x;
x:
b0xxxxxxxx 9
bx 8
x7
x6
x5
x4
bx 3
b11111111111111111111111111111111 2
x1
10
x/
bx .
bx -
b1 ,
bx +
bx *
1)
0(
0'
0&
0%
0$
1#
0"
x!
$end
#2000
b0xx J
07
0;
0<
b0 3
0U
b0 I
1&
#4000
0&
#6000
b0 J
b0xx000 3
b0xx I
1&
#8000
0&
00
0#
#10000
b0 J
06
b0 9
0!
04
0/
15
01
b0 8
0:
b0 3
b0 V
b0 R
0N
0M
0L
0O
b0 F
0P
0W
0X
b0 K
b0 E
b0 T
b0 -
b0 G
b1111 .
b1111 H
b0 +
b0 D
b0 Q
b0 I
1&
#12000
0&
#14000
1&
#16000
0&
10
1#
#18000
1&
#20000
0&
#22000
1&
#24000
0&
1$
#26000
1&
#28000
0&
#30000
1&
#32000
0&
0$
b10011 Y
#34000
1&
#36000
0&
#38000
1&
#40000
0&
1"
#42000
1&
#44000
0&
1%
1'
b0 *
#46000
b100000000000000000000000000000000000 R
1&
#48000
0&
b1 *
#50000
b110000000000000000000000000000000000 R
1&
#52000
0&
0'
b10 *
#54000
b11000000000000000000000000000000000 R
1&
#56000
0&
b11 *
#58000
b1100000000000000000000000000000000 R
1&
#60000
0&
1'
b100 *
#62000
b100110000000000000000000000000000000 R
1&
#64000
0&
0'
b101 *
#66000
b10011000000000000000000000000000000 R
1&
#68000
0&
b110 *
#70000
b1001100000000000000000000000000000 R
1&
#72000
0&
b111 *
#74000
b100110000000000000000000000000000 R
1&
#76000
0&
b1000 *
#78000
b10011000000000000000000000000000 R
1&
#80000
0&
b1001 *
#82000
b1001100000000000000000000000000 R
1&
#84000
0&
b1010 *
#86000
b100110000000000000000000000000 R
1&
#88000
0&
b1011 *
#90000
b10011000000000000000000000000 R
1&
#92000
0&
b1100 *
#94000
b1001100000000000000000000000 R
1&
#96000
0&
b1101 *
#98000
b100110000000000000000000000 R
1&
#100000
0&
b1110 *
#102000
b10011000000000000000000000 R
1&
#104000
0&
b1111 *
#106000
b1001100000000000000000000 R
1&
#108000
0&
b10000 *
#110000
b100110000000000000000000 R
1&
#112000
0&
b10001 *
#114000
b10011000000000000000000 R
1&
#116000
0&
b10010 *
#118000
b1001100000000000000000 R
1&
#120000
0&
b10011 *
#122000
b100110000000000000000 R
1&
#124000
0&
b10100 *
#126000
b10011000000000000000 R
1&
#128000
0&
b10101 *
#130000
b1001100000000000000 R
1&
#132000
0&
b10110 *
#134000
b100110000000000000 R
1&
#136000
0&
b10111 *
#138000
b10011000000000000 R
1&
#140000
0&
b11000 *
#142000
b1001100000000000 R
1&
#144000
0&
b11001 *
#146000
b100110000000000 R
1&
#148000
0&
b11010 *
#150000
b10011000000000 R
1&
#152000
0&
b11011 *
#154000
b1001100000000 R
1&
#156000
0&
b11100 *
#158000
b100110000000 R
1&
#160000
0&
b11101 *
#162000
b10011000000 R
1&
#164000
0&
b11110 *
#166000
b1001100000 R
1&
#168000
0&
b11111 *
#170000
b100110000 R
1&
#172000
0&
b100000 *
#174000
b10011000 R
1&
#176000
0&
b100001 *
#178000
b1001100 R
1&
#180000
0&
b100010 *
#182000
b100110 R
1&
#184000
0&
b100011 *
#186000
1!
b10011 R
1&
#188000
0&
0%
0"
b100100 *
#190000
1&
#192000
0&
#194000
1&
#196000
0&
1(
#198000
b10011 V
1U
b100 S
1&
#200000
0&
1$
0(
#202000
0U
b1 -
b1 G
b100 Q
b100 T
1&
#204000
0&
0$
b10101010101010101010101010101010001 Y
#206000
1&
#208000
0&
#210000
1&
#212000
0&
1"
#214000
0!
b100 R
1&
#216000
0&
1%
1'
b0 *
#218000
b100000000000000000000000000000000010 R
1&
#220000
0&
0'
b1 *
#222000
1!
b10000000000000000000000000000000001 R
1&
#224000
0&
b10 *
#226000
0!
b1000000000000000000000000000000000 R
1&
#228000
0&
b11 *
#230000
b100000000000000000000000000000000 R
1&
#232000
0&
1'
b100 *
#234000
b100010000000000000000000000000000000 R
1&
#236000
0&
0'
b101 *
#238000
b10001000000000000000000000000000000 R
1&
#240000
0&
1'
b110 *
#242000
b101000100000000000000000000000000000 R
1&
#244000
0&
0'
b111 *
#246000
b10100010000000000000000000000000000 R
1&
#248000
0&
1'
b1000 *
#250000
b101010001000000000000000000000000000 R
1&
#252000
0&
0'
b1001 *
#254000
b10101000100000000000000000000000000 R
1&
#256000
0&
1'
b1010 *
#258000
b101010100010000000000000000000000000 R
1&
#260000
0&
0'
b1011 *
#262000
b10101010001000000000000000000000000 R
1&
#264000
0&
1'
b1100 *
#266000
b101010101000100000000000000000000000 R
1&
#268000
0&
0'
b1101 *
#270000
b10101010100010000000000000000000000 R
1&
#272000
0&
1'
b1110 *
#274000
b101010101010001000000000000000000000 R
1&
#276000
0&
0'
b1111 *
#278000
b10101010101000100000000000000000000 R
1&
#280000
0&
1'
b10000 *
#282000
b101010101010100010000000000000000000 R
1&
#284000
0&
0'
b10001 *
#286000
b10101010101010001000000000000000000 R
1&
#288000
0&
1'
b10010 *
#290000
b101010101010101000100000000000000000 R
1&
#292000
0&
0'
b10011 *
#294000
b10101010101010100010000000000000000 R
1&
#296000
0&
1'
b10100 *
#298000
b101010101010101010001000000000000000 R
1&
#300000
0&
0'
b10101 *
#302000
b10101010101010101000100000000000000 R
1&
#304000
0&
1'
b10110 *
#306000
b101010101010101010100010000000000000 R
1&
#308000
0&
0'
b10111 *
#310000
b10101010101010101010001000000000000 R
1&
#312000
0&
1'
b11000 *
#314000
b101010101010101010101000100000000000 R
1&
#316000
0&
0'
b11001 *
#318000
b10101010101010101010100010000000000 R
1&
#320000
0&
1'
b11010 *
#322000
b101010101010101010101010001000000000 R
1&
#324000
0&
0'
b11011 *
#326000
b10101010101010101010101000100000000 R
1&
#328000
0&
1'
b11100 *
#330000
b101010101010101010101010100010000000 R
1&
#332000
0&
0'
b11101 *
#334000
b10101010101010101010101010001000000 R
1&
#336000
0&
1'
b11110 *
#338000
b101010101010101010101010101000100000 R
1&
#340000
0&
0'
b11111 *
#342000
b10101010101010101010101010100010000 R
1&
#344000
0&
1'
b100000 *
#346000
b101010101010101010101010101010001000 R
1&
#348000
0&
0'
b100001 *
#350000
b10101010101010101010101010101000100 R
1&
#352000
0&
1'
b100010 *
#354000
b101010101010101010101010101010100010 R
1&
#356000
0&
0'
b100011 *
#358000
1!
b10101010101010101010101010101010001 R
1&
#360000
0&
0%
0"
b100100 *
#362000
1&
#364000
0&
#366000
1&
#368000
0&
1(
#370000
b10101010101010101010101010101010001 V
1U
b101 S
1&
#372000
0&
1$
0(
#374000
b1010101010101010101010101010101 +
b1010101010101010101010101010101 D
b101 Q
b101 T
0U
1&
#376000
0&
0$
b1010101111001101111011111000 Y
#378000
1&
#380000
0&
#382000
1&
#384000
0&
1"
#386000
b101 R
1&
#388000
0&
1%
b0 *
#390000
0!
b10 R
1&
#392000
0&
b1 *
#394000
1!
b1 R
1&
#396000
0&
b10 *
#398000
0!
b0 R
1&
#400000
0&
1'
b11 *
#402000
b100000000000000000000000000000000000 R
1&
#404000
0&
b100 *
#406000
b110000000000000000000000000000000000 R
1&
#408000
0&
b101 *
#410000
b111000000000000000000000000000000000 R
1&
#412000
0&
b110 *
#414000
b111100000000000000000000000000000000 R
1&
#416000
0&
b111 *
#418000
b111110000000000000000000000000000000 R
1&
#420000
0&
0'
b1000 *
#422000
b11111000000000000000000000000000000 R
1&
#424000
0&
1'
b1001 *
#426000
b101111100000000000000000000000000000 R
1&
#428000
0&
b1010 *
#430000
b110111110000000000000000000000000000 R
1&
#432000
0&
b1011 *
#434000
b111011111000000000000000000000000000 R
1&
#436000
0&
b1100 *
#438000
b111101111100000000000000000000000000 R
1&
#440000
0&
0'
b1101 *
#442000
b11110111110000000000000000000000000 R
1&
#444000
0&
1'
b1110 *
#446000
b101111011111000000000000000000000000 R
1&
#448000
0&
b1111 *
#450000
b110111101111100000000000000000000000 R
1&
#452000
0&
0'
b10000 *
#454000
b11011110111110000000000000000000000 R
1&
#456000
0&
b10001 *
#458000
b1101111011111000000000000000000000 R
1&
#460000
0&
1'
b10010 *
#462000
b100110111101111100000000000000000000 R
1&
#464000
0&
b10011 *
#466000
b110011011110111110000000000000000000 R
1&
#468000
0&
b10100 *
#470000
b111001101111011111000000000000000000 R
1&
#472000
0&
b10101 *
#474000
b111100110111101111100000000000000000 R
1&
#476000
0&
0'
b10110 *
#478000
b11110011011110111110000000000000000 R
1&
#480000
0&
1'
b10111 *
#482000
b101111001101111011111000000000000000 R
1&
#484000
0&
0'
b11000 *
#486000
b10111100110111101111100000000000000 R
1&
#488000
0&
1'
b11001 *
#490000
b101011110011011110111110000000000000 R
1&
#492000
0&
0'
b11010 *
#494000
b10101111001101111011111000000000000 R
1&
